Workbook

Sheet Dashboard
A1: Bridg Competitive Benchmark
A2: 100 USDC → USDC · 6 routes · quotes read from each site's own web UI, no wallet connected · collected 2026-09-23 14:18 – 14:30 UTC
A4: Headline
A5: Routes where Bridg's best beat every direct quote | B5: =COUNTIF('Competitor Matrix'!$E$28:$E$33,">=-2")&" / 6"
A6: Venue pairs where Bridg's listing matches the venue's site | B6: =COUNTIF('Venue Analysis'!$Z$5:$Z$74,"Match*")&" / "&COUNTA('Venue Analysis'!$Z$5:$Z$74)
A7: … Bridg lists LESS than the venue's own site | B7: =COUNTIF('Venue Analysis'!$Z$5:$Z$74,"Bridg LOWER*")
A8: … Bridg lists MORE than the venue's own site | B8: =COUNTIF('Venue Analysis'!$Z$5:$Z$74,"Bridg HIGHER*")
A9: … venue quotes on its site but is missing from Bridg | B9: =COUNTIF('Venue Analysis'!$Z$5:$Z$74,"NOT LISTED*")
A10: Worst venue-accuracy gap (bps, ex-Bridg fee) | B10: =MIN('Venue Analysis'!$X$5:$X$74)
A11: Campaign (all quotes collected in one window) | B11: 20260923T141817Z · 2026-09-23 14:18:34 – 14:30:59 UTC
A12: Worst value-read spread within a run (s) | B12: =MAX('Raw Quotes'!$S:$S)
A13: Venues / platforms compared | B13: 13 venues + 1 platforms
A14: Blocked (no public quote) | B14: 3 venues + 4 platforms
A17: Route winners (Bridg best vs best direct quote)
A18: Route | B18: Bridg best | C18: Best elsewhere | D18: Site | E18: Bridg vs best (bps) | F18: Sites Bridg beats | G18: Sites beating Bridg
A19: ='Competitor Matrix'!A28 | B19: ='Competitor Matrix'!B28 | C19: ='Competitor Matrix'!C28 | D19: ='Competitor Matrix'!D28 | E19: ='Competitor Matrix'!E28 | F19: ='Competitor Matrix'!F28 | G19: ='Competitor Matrix'!G28
A20: ='Competitor Matrix'!A29 | B20: ='Competitor Matrix'!B29 | C20: ='Competitor Matrix'!C29 | D20: ='Competitor Matrix'!D29 | E20: ='Competitor Matrix'!E29 | F20: ='Competitor Matrix'!F29 | G20: ='Competitor Matrix'!G29
A21: ='Competitor Matrix'!A30 | B21: ='Competitor Matrix'!B30 | C21: ='Competitor Matrix'!C30 | D21: ='Competitor Matrix'!D30 | E21: ='Competitor Matrix'!E30 | F21: ='Competitor Matrix'!F30 | G21: ='Competitor Matrix'!G30
A22: ='Competitor Matrix'!A31 | B22: ='Competitor Matrix'!B31 | C22: ='Competitor Matrix'!C31 | D22: ='Competitor Matrix'!D31 | E22: ='Competitor Matrix'!E31 | F22: ='Competitor Matrix'!F31 | G22: ='Competitor Matrix'!G31
A23: ='Competitor Matrix'!A32 | B23: ='Competitor Matrix'!B32 | C23: ='Competitor Matrix'!C32 | D23: ='Competitor Matrix'!D32 | E23: ='Competitor Matrix'!E32 | F23: ='Competitor Matrix'!F32 | G23: ='Competitor Matrix'!G32
A24: ='Competitor Matrix'!A33 | B24: ='Competitor Matrix'!B33 | C24: ='Competitor Matrix'!C33 | D24: ='Competitor Matrix'!D33 | E24: ='Competitor Matrix'!E33 | F24: ='Competitor Matrix'!F33 | G24: ='Competitor Matrix'!G33
A26: Venue accuracy (avg gap ex-Bridg fee, bps) — Bridg listed vs venue's own site
A27: Venue | B27: SOL → ETH | C27: ETH → SOL | D27: SOL → BSC | E27: BSC → SOL | F27: SOL → Base | G27: Base → SOL
A28: Relay | B28: =IF('Venue Analysis'!T5=0,"not listed",'Venue Analysis'!X5) | C28: =IF('Venue Analysis'!T18=0,"not listed",'Venue Analysis'!X18) | D28: =IF('Venue Analysis'!T31=0,"not listed",'Venue Analysis'!X31) | E28: =IF('Venue Analysis'!T40=0,"not listed",'Venue Analysis'!X40) | F28: =IF('Venue Analysis'!T50=0,"not listed",'Venue Analysis'!X50) | G28: =IF('Venue Analysis'!T62=0,"not listed",'Venue Analysis'!X62)
A29: deBridge | B29: =IF('Venue Analysis'!T6=0,"not listed",'Venue Analysis'!X6) | C29: =IF('Venue Analysis'!T19=0,"not listed",'Venue Analysis'!X19) | D29: =IF('Venue Analysis'!T32=0,"not listed",'Venue Analysis'!X32) | E29: =IF('Venue Analysis'!T41=0,"not listed",'Venue Analysis'!X41) | F29: =IF('Venue Analysis'!T51=0,"not listed",'Venue Analysis'!X51) | G29: =IF('Venue Analysis'!T63=0,"not listed",'Venue Analysis'!X63)
A30: LI.FI (Jumper) | B30: =IF('Venue Analysis'!T7=0,"not listed",'Venue Analysis'!X7) | C30: =IF('Venue Analysis'!T20=0,"not listed",'Venue Analysis'!X20) | D30: =IF('Venue Analysis'!T33=0,"not listed",'Venue Analysis'!X33) | E30: =IF('Venue Analysis'!T42=0,"not listed",'Venue Analysis'!X42) | F30: =IF('Venue Analysis'!T52=0,"not listed",'Venue Analysis'!X52) | G30: =IF('Venue Analysis'!T64=0,"not listed",'Venue Analysis'!X64)
A31: Across | B31: =IF('Venue Analysis'!T8=0,"not listed",'Venue Analysis'!X8) | C31: =IF('Venue Analysis'!T21=0,"not listed",'Venue Analysis'!X21) | D31: =IF('Venue Analysis'!T34=0,"not listed",'Venue Analysis'!X34) | E31: =IF('Venue Analysis'!T43=0,"not listed",'Venue Analysis'!X43) | F31: =IF('Venue Analysis'!T53=0,"not listed",'Venue Analysis'!X53) | G31: =IF('Venue Analysis'!T65=0,"not listed",'Venue Analysis'!X65)
A32: Mayan | B32: =IF('Venue Analysis'!T9=0,"not listed",'Venue Analysis'!X9) | C32: =IF('Venue Analysis'!T22=0,"not listed",'Venue Analysis'!X22) | D32: =IF('Venue Analysis'!T35=0,"not listed",'Venue Analysis'!X35) | E32: =IF('Venue Analysis'!T44=0,"not listed",'Venue Analysis'!X44) | F32: =IF('Venue Analysis'!T54=0,"not listed",'Venue Analysis'!X54) | G32: =IF('Venue Analysis'!T66=0,"not listed",'Venue Analysis'!X66)
A33: Allbridge Core | B33: =IF('Venue Analysis'!T10=0,"not listed",'Venue Analysis'!X10) | C33: =IF('Venue Analysis'!T23=0,"not listed",'Venue Analysis'!X23) | D33: n/a | E33: n/a | F33: =IF('Venue Analysis'!T55=0,"not listed",'Venue Analysis'!X55) | G33: =IF('Venue Analysis'!T67=0,"not listed",'Venue Analysis'!X67)
A34: CCTP (via Portal) | B34: =IF('Venue Analysis'!T11=0,"not listed",'Venue Analysis'!X11) | C34: =IF('Venue Analysis'!T24=0,"not listed",'Venue Analysis'!X24) | D34: n/a | E34: n/a | F34: =IF('Venue Analysis'!T56=0,"not listed",'Venue Analysis'!X56) | G34: =IF('Venue Analysis'!T68=0,"not listed",'Venue Analysis'!X68)
A35: Husher | B35: =IF('Venue Analysis'!T12=0,"not listed",'Venue Analysis'!X12) | C35: =IF('Venue Analysis'!T25=0,"not listed",'Venue Analysis'!X25) | D35: =IF('Venue Analysis'!T36=0,"not listed",'Venue Analysis'!X36) | E35: =IF('Venue Analysis'!T45=0,"not listed",'Venue Analysis'!X45) | F35: =IF('Venue Analysis'!T57=0,"not listed",'Venue Analysis'!X57) | G35: =IF('Venue Analysis'!T69=0,"not listed",'Venue Analysis'!X69)
A36: Layerswap | B36: =IF('Venue Analysis'!T13=0,"not listed",'Venue Analysis'!X13) | C36: =IF('Venue Analysis'!T26=0,"not listed",'Venue Analysis'!X26) | D36: =IF('Venue Analysis'!T37=0,"not listed",'Venue Analysis'!X37) | E36: =IF('Venue Analysis'!T46=0,"not listed",'Venue Analysis'!X46) | F36: =IF('Venue Analysis'!T58=0,"not listed",'Venue Analysis'!X58) | G36: =IF('Venue Analysis'!T70=0,"not listed",'Venue Analysis'!X70)
A37: Meson | B37: =IF('Venue Analysis'!T14=0,"not listed",'Venue Analysis'!X14) | C37: =IF('Venue Analysis'!T27=0,"not listed",'Venue Analysis'!X27) | D37: =IF('Venue Analysis'!T38=0,"not listed",'Venue Analysis'!X38) | E37: =IF('Venue Analysis'!T47=0,"not listed",'Venue Analysis'!X47) | F37: =IF('Venue Analysis'!T59=0,"not listed",'Venue Analysis'!X59) | G37: =IF('Venue Analysis'!T71=0,"not listed",'Venue Analysis'!X71)
A38: SimpleSwap | B38: =IF('Venue Analysis'!T15=0,"not listed",'Venue Analysis'!X15) | C38: =IF('Venue Analysis'!T28=0,"not listed",'Venue Analysis'!X28) | D38: =IF('Venue Analysis'!T39=0,"not listed",'Venue Analysis'!X39) | E38: =IF('Venue Analysis'!T48=0,"not listed",'Venue Analysis'!X48) | F38: =IF('Venue Analysis'!T60=0,"not listed",'Venue Analysis'!X60) | G38: =IF('Venue Analysis'!T72=0,"not listed",'Venue Analysis'!X72)
A39: Skip Go | B39: =IF('Venue Analysis'!T16=0,"not listed",'Venue Analysis'!X16) | C39: =IF('Venue Analysis'!T29=0,"not listed",'Venue Analysis'!X29) | D39: n/a | E39: n/a | F39: =IF('Venue Analysis'!T61=0,"not listed",'Venue Analysis'!X61) | G39: =IF('Venue Analysis'!T73=0,"not listed",'Venue Analysis'!X73)
A40: Symbiosis | B40: =IF('Venue Analysis'!T17=0,"not listed",'Venue Analysis'!X17) | C40: =IF('Venue Analysis'!T30=0,"not listed",'Venue Analysis'!X30) | D40: n/a | E40: =IF('Venue Analysis'!T49=0,"not listed",'Venue Analysis'!X49) | F40: n/a | G40: =IF('Venue Analysis'!T74=0,"not listed",'Venue Analysis'!X74)
A42: Green = linked from other sheets. Red cells: Bridg lower / going direct pays more; blue: Bridg higher / Bridg pays more. Hypotheses in Issues are unverified.
A44: Run timing — every site typed at one instant, then all read their compared value at one instant
A45: Route | B45: Sample | C45: Typed at (UTC) | D45: Values read at (UTC) | E45: Typed spread (s) | F45: Read spread (s) | G45: Screenshot spread (s) | H45: Sites OK
A46: SOL → ETH | B46: 1 | C46: 2026-09-23T14:18:34.538Z | D46: 2026-09-23T14:18:55.406Z | E46: 0.187 | F46: 0.006 | G46: 0.183 | H46: 15/15
A47: ETH → SOL | B47: 1 | C47: 2026-09-23T14:19:22.123Z | D47: 2026-09-23T14:19:28.697Z | E47: 0.01 | F47: 0.006 | G47: 0.919 | H47: 15/15
A48: SOL → BSC | B48: 1 | C48: 2026-09-23T14:19:52.315Z | D48: 2026-09-23T14:19:58.625Z | E48: 0.011 | F48: 0.004 | G48: 0.079 | H48: 10/10
A49: BSC → SOL | B49: 1 | C49: 2026-09-23T14:20:23.792Z | D49: 2026-09-23T14:20:29.480Z | E49: 0.004 | F49: 0.004 | G49: 0.147 | H49: 11/11
A50: SOL → Base | B50: 1 | C50: 2026-09-23T14:21:02.757Z | D50: 2026-09-23T14:21:09.321Z | E50: 0.005 | F50: 0.006 | G50: 0.285 | H50: 14/14
A51: Base → SOL | B51: 1 | C51: 2026-09-23T14:21:37.200Z | D51: 2026-09-23T14:21:44.562Z | E51: 0.054 | F51: 0.008 | G51: 1.073 | H51: 15/15
A52: SOL → ETH | B52: 2 | C52: 2026-09-23T14:22:16.319Z | D52: 2026-09-23T14:22:28.648Z | E52: 0.005 | F52: 0.01 | G52: 3.016 | H52: 15/15
A53: ETH → SOL | B53: 2 | C53: 2026-09-23T14:23:01.562Z | D53: 2026-09-23T14:23:47.144Z | E53: 0.035 | F53: 0.008 | G53: 0.332 | H53: 15/15
A54: SOL → BSC | B54: 2 | C54: 2026-09-23T14:24:12.906Z | D54: 2026-09-23T14:24:42.081Z | E54: 0.015 | F54: 0.005 | G54: 0.095 | H54: 10/10
A55: BSC → SOL | B55: 2 | C55: 2026-09-23T14:25:07.466Z | D55: 2026-09-23T14:25:12.872Z | E55: 0.023 | F55: 0.003 | G55: 0.087 | H55: 11/11
A56: SOL → Base | B56: 2 | C56: 2026-09-23T14:25:40.428Z | D56: 2026-09-23T14:25:46.682Z | E56: 0.008 | F56: 0.004 | G56: 0.536 | H56: 14/14
A57: Base → SOL | B57: 2 | C57: 2026-09-23T14:26:14.638Z | D57: 2026-09-23T14:26:20.602Z | E57: 0.009 | F57: 0.004 | G57: 0.491 | H57: 15/15
... A63: Base → SOL | B63: 3 | C63: 2026-09-23T14:30:52.317Z | D63: 2026-09-23T14:30:58.847Z | E63: 0.012 | F63: 0.004 | G63: 0.854 | H63: 15/15

Sheet Competitor Matrix
A1: Competitor Matrix — does a user get more on Bridg, or by going direct?
A2: Savings (bps) = (Bridg best − other) / 100 × 10,000. Positive = Bridg pays more. Bridg best = what Bridg's own page says you receive on its best-price route. Source-chain gas paid separately is not counted on either side.
A4: Average savings (bps) by site and route
A5: Site | B5: Kind | C5: SOL → ETH | D5: ETH → SOL | E5: SOL → BSC | F5: BSC → SOL | G5: SOL → Base | H5: Base → SOL | N5: Avg other out (helper) | O5: SOL → ETH | P5: ETH → SOL | Q5: SOL → BSC | R5: BSC → SOL | S5: SOL → Base | T5: Base → SOL
A6: OpenSea | B6: platform | C6: =IFERROR(AVERAGEIFS($H$37:$H$256,$A$37:$A$256,"SOL → ETH",$C$37:$C$256,$A6),"n/a") | D6: =IFERROR(AVERAGEIFS($H$37:$H$256,$A$37:$A$256,"ETH → SOL",$C$37:$C$256,$A6),"n/a") | E6: =IFERROR(AVERAGEIFS($H$37:$H$256,$A$37:$A$256,"SOL → BSC",$C$37:$C$256,$A6),"n/a") | F6: =IFERROR(AVERAGEIFS($H$37:$H$256,$A$37:$A$256,"BSC → SOL",$C$37:$C$256,$A6),"n/a") | G6: =IFERROR(AVERAGEIFS($H$37:$H$256,$A$37:$A$256,"SOL → Base",$C$37:$C$256,$A6),"n/a") | H6: =IFERROR(AVERAGEIFS($H$37:$H$256,$A$37:$A$256,"Base → SOL",$C$37:$C$256,$A6),"n/a") | N6: OpenSea | O6: =IFERROR(AVERAGEIFS($G$37:$G$256,$A$37:$A$256,"SOL → ETH",$C$37:$C$256,$N6),"") | P6: =IFERROR(AVERAGEIFS($G$37:$G$256,$A$37:$A$256,"ETH → SOL",$C$37:$C$256,$N6),"") | Q6: =IFERROR(AVERAGEIFS($G$37:$G$256,$A$37:$A$256,"SOL → BSC",$C$37:$C$256,$N6),"") | R6: =IFERROR(AVERAGEIFS($G$37:$G$256,$A$37:$A$256,"BSC → SOL",$C$37:$C$256,$N6),"") | S6: =IFERROR(AVERAGEIFS($G$37:$G$256,$A$37:$A$256,"SOL → Base",$C$37:$C$256,$N6),"") | T6: =IFERROR(AVERAGEIFS($G$37:$G$256,$A$37:$A$256,"Base → SOL",$C$37:$C$256,$N6),"")
A7: Relay | B7: venue | C7: =IFERROR(AVERAGEIFS($H$37:$H$256,$A$37:$A$256,"SOL → ETH",$C$37:$C$256,$A7),"n/a") | D7: =IFERROR(AVERAGEIFS($H$37:$H$256,$A$37:$A$256,"ETH → SOL",$C$37:$C$256,$A7),"n/a") | E7: =IFERROR(AVERAGEIFS($H$37:$H$256,$A$37:$A$256,"SOL → BSC",$C$37:$C$256,$A7),"n/a") | F7: =IFERROR(AVERAGEIFS($H$37:$H$256,$A$37:$A$256,"BSC → SOL",$C$37:$C$256,$A7),"n/a") | G7: =IFERROR(AVERAGEIFS($H$37:$H$256,$A$37:$A$256,"SOL → Base",$C$37:$C$256,$A7),"n/a") | H7: =IFERROR(AVERAGEIFS($H$37:$H$256,$A$37:$A$256,"Base → SOL",$C$37:$C$256,$A7),"n/a") | N7: Relay | O7: =IFERROR(AVERAGEIFS($G$37:$G$256,$A$37:$A$256,"SOL → ETH",$C$37:$C$256,$N7),"") | P7: =IFERROR(AVERAGEIFS($G$37:$G$256,$A$37:$A$256,"ETH → SOL",$C$37:$C$256,$N7),"") | Q7: =IFERROR(AVERAGEIFS($G$37:$G$256,$A$37:$A$256,"SOL → BSC",$C$37:$C$256,$N7),"") | R7: =IFERROR(AVERAGEIFS($G$37:$G$256,$A$37:$A$256,"BSC → SOL",$C$37:$C$256,$N7),"") | S7: =IFERROR(AVERAGEIFS($G$37:$G$256,$A$37:$A$256,"SOL → Base",$C$37:$C$256,$N7),"") | T7: =IFERROR(AVERAGEIFS($G$37:$G$256,$A$37:$A$256,"Base → SOL",$C$37:$C$256,$N7),"")
A8: deBridge | B8: venue | C8: =IFERROR(AVERAGEIFS($H$37:$H$256,$A$37:$A$256,"SOL → ETH",$C$37:$C$256,$A8),"n/a") | D8: =IFERROR(AVERAGEIFS($H$37:$H$256,$A$37:$A$256,"ETH → SOL",$C$37:$C$256,$A8),"n/a") | E8: =IFERROR(AVERAGEIFS($H$37:$H$256,$A$37:$A$256,"SOL → BSC",$C$37:$C$256,$A8),"n/a") | F8: =IFERROR(AVERAGEIFS($H$37:$H$256,$A$37:$A$256,"BSC → SOL",$C$37:$C$256,$A8),"n/a") | G8: =IFERROR(AVERAGEIFS($H$37:$H$256,$A$37:$A$256,"SOL → Base",$C$37:$C$256,$A8),"n/a") | H8: =IFERROR(AVERAGEIFS($H$37:$H$256,$A$37:$A$256,"Base → SOL",$C$37:$C$256,$A8),"n/a") | N8: deBridge | O8: =IFERROR(AVERAGEIFS($G$37:$G$256,$A$37:$A$256,"SOL → ETH",$C$37:$C$256,$N8),"") | P8: =IFERROR(AVERAGEIFS($G$37:$G$256,$A$37:$A$256,"ETH → SOL",$C$37:$C$256,$N8),"") | Q8: =IFERROR(AVERAGEIFS($G$37:$G$256,$A$37:$A$256,"SOL → BSC",$C$37:$C$256,$N8),"") | R8: =IFERROR(AVERAGEIFS($G$37:$G$256,$A$37:$A$256,"BSC → SOL",$C$37:$C$256,$N8),"") | S8: =IFERROR(AVERAGEIFS($G$37:$G$256,$A$37:$A$256,"SOL → Base",$C$37:$C$256,$N8),"") | T8: =IFERROR(AVERAGEIFS($G$37:$G$256,$A$37:$A$256,"Base → SOL",$C$37:$C$256,$N8),"")
A9: LI.FI (Jumper) | B9: venue | C9: =IFERROR(AVERAGEIFS($H$37:$H$256,$A$37:$A$256,"SOL → ETH",$C$37:$C$256,$A9),"n/a") | D9: =IFERROR(AVERAGEIFS($H$37:$H$256,$A$37:$A$256,"ETH → SOL",$C$37:$C$256,$A9),"n/a") | E9: =IFERROR(AVERAGEIFS($H$37:$H$256,$A$37:$A$256,"SOL → BSC",$C$37:$C$256,$A9),"n/a") | F9: =IFERROR(AVERAGEIFS($H$37:$H$256,$A$37:$A$256,"BSC → SOL",$C$37:$C$256,$A9),"n/a") | G9: =IFERROR(AVERAGEIFS($H$37:$H$256,$A$37:$A$256,"SOL → Base",$C$37:$C$256,$A9),"n/a") | H9: =IFERROR(AVERAGEIFS($H$37:$H$256,$A$37:$A$256,"Base → SOL",$C$37:$C$256,$A9),"n/a") | N9: LI.FI (Jumper) | O9: =IFERROR(AVERAGEIFS($G$37:$G$256,$A$37:$A$256,"SOL → ETH",$C$37:$C$256,$N9),"") | P9: =IFERROR(AVERAGEIFS($G$37:$G$256,$A$37:$A$256,"ETH → SOL",$C$37:$C$256,$N9),"") | Q9: =IFERROR(AVERAGEIFS($G$37:$G$256,$A$37:$A$256,"SOL → BSC",$C$37:$C$256,$N9),"") | R9: =IFERROR(AVERAGEIFS($G$37:$G$256,$A$37:$A$256,"BSC → SOL",$C$37:$C$256,$N9),"") | S9: =IFERROR(AVERAGEIFS($G$37:$G$256,$A$37:$A$256,"SOL → Base",$C$37:$C$256,$N9),"") | T9: =IFERROR(AVERAGEIFS($G$37:$G$256,$A$37:$A$256,"Base → SOL",$C$37:$C$256,$N9),"")
A10: Across | B10: venue | C10: =IFERROR(AVERAGEIFS($H$37:$H$256,$A$37:$A$256,"SOL → ETH",$C$37:$C$256,$A10),"n/a") | D10: =IFERROR(AVERAGEIFS($H$37:$H$256,$A$37:$A$256,"ETH → SOL",$C$37:$C$256,$A10),"n/a") | E10: =IFERROR(AVERAGEIFS($H$37:$H$256,$A$37:$A$256,"SOL → BSC",$C$37:$C$256,$A10),"n/a") | F10: =IFERROR(AVERAGEIFS($H$37:$H$256,$A$37:$A$256,"BSC → SOL",$C$37:$C$256,$A10),"n/a") | G10: =IFERROR(AVERAGEIFS($H$37:$H$256,$A$37:$A$256,"SOL → Base",$C$37:$C$256,$A10),"n/a") | H10: =IFERROR(AVERAGEIFS($H$37:$H$256,$A$37:$A$256,"Base → SOL",$C$37:$C$256,$A10),"n/a") | N10: Across | O10: =IFERROR(AVERAGEIFS($G$37:$G$256,$A$37:$A$256,"SOL → ETH",$C$37:$C$256,$N10),"") | P10: =IFERROR(AVERAGEIFS($G$37:$G$256,$A$37:$A$256,"ETH → SOL",$C$37:$C$256,$N10),"") | Q10: =IFERROR(AVERAGEIFS($G$37:$G$256,$A$37:$A$256,"SOL → BSC",$C$37:$C$256,$N10),"") | R10: =IFERROR(AVERAGEIFS($G$37:$G$256,$A$37:$A$256,"BSC → SOL",$C$37:$C$256,$N10),"") | S10: =IFERROR(AVERAGEIFS($G$37:$G$256,$A$37:$A$256,"SOL → Base",$C$37:$C$256,$N10),"") | T10: =IFERROR(AVERAGEIFS($G$37:$G$256,$A$37:$A$256,"Base → SOL",$C$37:$C$256,$N10),"")
A11: Mayan | B11: venue | C11: =IFERROR(AVERAGEIFS($H$37:$H$256,$A$37:$A$256,"SOL → ETH",$C$37:$C$256,$A11),"n/a") | D11: =IFERROR(AVERAGEIFS($H$37:$H$256,$A$37:$A$256,"ETH → SOL",$C$37:$C$256,$A11),"n/a") | E11: =IFERROR(AVERAGEIFS($H$37:$H$256,$A$37:$A$256,"SOL → BSC",$C$37:$C$256,$A11),"n/a") | F11: =IFERROR(AVERAGEIFS($H$37:$H$256,$A$37:$A$256,"BSC → SOL",$C$37:$C$256,$A11),"n/a") | G11: =IFERROR(AVERAGEIFS($H$37:$H$256,$A$37:$A$256,"SOL → Base",$C$37:$C$256,$A11),"n/a") | H11: =IFERROR(AVERAGEIFS($H$37:$H$256,$A$37:$A$256,"Base → SOL",$C$37:$C$256,$A11),"n/a") | N11: Mayan | O11: =IFERROR(AVERAGEIFS($G$37:$G$256,$A$37:$A$256,"SOL → ETH",$C$37:$C$256,$N11),"") | P11: =IFERROR(AVERAGEIFS($G$37:$G$256,$A$37:$A$256,"ETH → SOL",$C$37:$C$256,$N11),"") | Q11: =IFERROR(AVERAGEIFS($G$37:$G$256,$A$37:$A$256,"SOL → BSC",$C$37:$C$256,$N11),"") | R11: =IFERROR(AVERAGEIFS($G$37:$G$256,$A$37:$A$256,"BSC → SOL",$C$37:$C$256,$N11),"") | S11: =IFERROR(AVERAGEIFS($G$37:$G$256,$A$37:$A$256,"SOL → Base",$C$37:$C$256,$N11),"") | T11: =IFERROR(AVERAGEIFS($G$37:$G$256,$A$37:$A$256,"Base → SOL",$C$37:$C$256,$N11),"")
A12: Allbridge Core | B12: venue | C12: =IFERROR(AVERAGEIFS($H$37:$H$256,$A$37:$A$256,"SOL → ETH",$C$37:$C$256,$A12),"n/a") | D12: =IFERROR(AVERAGEIFS($H$37:$H$256,$A$37:$A$256,"ETH → SOL",$C$37:$C$256,$A12),"n/a") | E12: =IFERROR(AVERAGEIFS($H$37:$H$256,$A$37:$A$256,"SOL → BSC",$C$37:$C$256,$A12),"n/a") | F12: =IFERROR(AVERAGEIFS($H$37:$H$256,$A$37:$A$256,"BSC → SOL",$C$37:$C$256,$A12),"n/a") | G12: =IFERROR(AVERAGEIFS($H$37:$H$256,$A$37:$A$256,"SOL → Base",$C$37:$C$256,$A12),"n/a") | H12: =IFERROR(AVERAGEIFS($H$37:$H$256,$A$37:$A$256,"Base → SOL",$C$37:$C$256,$A12),"n/a") | N12: Allbridge Core | O12: =IFERROR(AVERAGEIFS($G$37:$G$256,$A$37:$A$256,"SOL → ETH",$C$37:$C$256,$N12),"") | P12: =IFERROR(AVERAGEIFS($G$37:$G$256,$A$37:$A$256,"ETH → SOL",$C$37:$C$256,$N12),"") | Q12: =IFERROR(AVERAGEIFS($G$37:$G$256,$A$37:$A$256,"SOL → BSC",$C$37:$C$256,$N12),"") | R12: =IFERROR(AVERAGEIFS($G$37:$G$256,$A$37:$A$256,"BSC → SOL",$C$37:$C$256,$N12),"") | S12: =IFERROR(AVERAGEIFS($G$37:$G$256,$A$37:$A$256,"SOL → Base",$C$37:$C$256,$N12),"") | T12: =IFERROR(AVERAGEIFS($G$37:$G$256,$A$37:$A$256,"Base → SOL",$C$37:$C$256,$N12),"")
A13: CCTP (via Portal) | B13: venue | C13: =IFERROR(AVERAGEIFS($H$37:$H$256,$A$37:$A$256,"SOL → ETH",$C$37:$C$256,$A13),"n/a") | D13: =IFERROR(AVERAGEIFS($H$37:$H$256,$A$37:$A$256,"ETH → SOL",$C$37:$C$256,$A13),"n/a") | E13: =IFERROR(AVERAGEIFS($H$37:$H$256,$A$37:$A$256,"SOL → BSC",$C$37:$C$256,$A13),"n/a") | F13: =IFERROR(AVERAGEIFS($H$37:$H$256,$A$37:$A$256,"BSC → SOL",$C$37:$C$256,$A13),"n/a") | G13: =IFERROR(AVERAGEIFS($H$37:$H$256,$A$37:$A$256,"SOL → Base",$C$37:$C$256,$A13),"n/a") | H13: =IFERROR(AVERAGEIFS($H$37:$H$256,$A$37:$A$256,"Base → SOL",$C$37:$C$256,$A13),"n/a") | N13: CCTP (via Portal) | O13: =IFERROR(AVERAGEIFS($G$37:$G$256,$A$37:$A$256,"SOL → ETH",$C$37:$C$256,$N13),"") | P13: =IFERROR(AVERAGEIFS($G$37:$G$256,$A$37:$A$256,"ETH → SOL",$C$37:$C$256,$N13),"") | Q13: =IFERROR(AVERAGEIFS($G$37:$G$256,$A$37:$A$256,"SOL → BSC",$C$37:$C$256,$N13),"") | R13: =IFERROR(AVERAGEIFS($G$37:$G$256,$A$37:$A$256,"BSC → SOL",$C$37:$C$256,$N13),"") | S13: =IFERROR(AVERAGEIFS($G$37:$G$256,$A$37:$A$256,"SOL → Base",$C$37:$C$256,$N13),"") | T13: =IFERROR(AVERAGEIFS($G$37:$G$256,$A$37:$A$256,"Base → SOL",$C$37:$C$256,$N13),"")
A14: Husher | B14: venue | C14: =IFERROR(AVERAGEIFS($H$37:$H$256,$A$37:$A$256,"SOL → ETH",$C$37:$C$256,$A14),"n/a") | D14: =IFERROR(AVERAGEIFS($H$37:$H$256,$A$37:$A$256,"ETH → SOL",$C$37:$C$256,$A14),"n/a") | E14: =IFERROR(AVERAGEIFS($H$37:$H$256,$A$37:$A$256,"SOL → BSC",$C$37:$C$256,$A14),"n/a") | F14: =IFERROR(AVERAGEIFS($H$37:$H$256,$A$37:$A$256,"BSC → SOL",$C$37:$C$256,$A14),"n/a") | G14: =IFERROR(AVERAGEIFS($H$37:$H$256,$A$37:$A$256,"SOL → Base",$C$37:$C$256,$A14),"n/a") | H14: =IFERROR(AVERAGEIFS($H$37:$H$256,$A$37:$A$256,"Base → SOL",$C$37:$C$256,$A14),"n/a") | N14: Husher | O14: =IFERROR(AVERAGEIFS($G$37:$G$256,$A$37:$A$256,"SOL → ETH",$C$37:$C$256,$N14),"") | P14: =IFERROR(AVERAGEIFS($G$37:$G$256,$A$37:$A$256,"ETH → SOL",$C$37:$C$256,$N14),"") | Q14: =IFERROR(AVERAGEIFS($G$37:$G$256,$A$37:$A$256,"SOL → BSC",$C$37:$C$256,$N14),"") | R14: =IFERROR(AVERAGEIFS($G$37:$G$256,$A$37:$A$256,"BSC → SOL",$C$37:$C$256,$N14),"") | S14: =IFERROR(AVERAGEIFS($G$37:$G$256,$A$37:$A$256,"SOL → Base",$C$37:$C$256,$N14),"") | T14: =IFERROR(AVERAGEIFS($G$37:$G$256,$A$37:$A$256,"Base → SOL",$C$37:$C$256,$N14),"")
A15: Layerswap | B15: venue | C15: =IFERROR(AVERAGEIFS($H$37:$H$256,$A$37:$A$256,"SOL → ETH",$C$37:$C$256,$A15),"n/a") | D15: =IFERROR(AVERAGEIFS($H$37:$H$256,$A$37:$A$256,"ETH → SOL",$C$37:$C$256,$A15),"n/a") | E15: =IFERROR(AVERAGEIFS($H$37:$H$256,$A$37:$A$256,"SOL → BSC",$C$37:$C$256,$A15),"n/a") | F15: =IFERROR(AVERAGEIFS($H$37:$H$256,$A$37:$A$256,"BSC → SOL",$C$37:$C$256,$A15),"n/a") | G15: =IFERROR(AVERAGEIFS($H$37:$H$256,$A$37:$A$256,"SOL → Base",$C$37:$C$256,$A15),"n/a") | H15: =IFERROR(AVERAGEIFS($H$37:$H$256,$A$37:$A$256,"Base → SOL",$C$37:$C$256,$A15),"n/a") | N15: Layerswap | O15: =IFERROR(AVERAGEIFS($G$37:$G$256,$A$37:$A$256,"SOL → ETH",$C$37:$C$256,$N15),"") | P15: =IFERROR(AVERAGEIFS($G$37:$G$256,$A$37:$A$256,"ETH → SOL",$C$37:$C$256,$N15),"") | Q15: =IFERROR(AVERAGEIFS($G$37:$G$256,$A$37:$A$256,"SOL → BSC",$C$37:$C$256,$N15),"") | R15: =IFERROR(AVERAGEIFS($G$37:$G$256,$A$37:$A$256,"BSC → SOL",$C$37:$C$256,$N15),"") | S15: =IFERROR(AVERAGEIFS($G$37:$G$256,$A$37:$A$256,"SOL → Base",$C$37:$C$256,$N15),"") | T15: =IFERROR(AVERAGEIFS($G$37:$G$256,$A$37:$A$256,"Base → SOL",$C$37:$C$256,$N15),"")
A16: Meson | B16: venue | C16: =IFERROR(AVERAGEIFS($H$37:$H$256,$A$37:$A$256,"SOL → ETH",$C$37:$C$256,$A16),"n/a") | D16: =IFERROR(AVERAGEIFS($H$37:$H$256,$A$37:$A$256,"ETH → SOL",$C$37:$C$256,$A16),"n/a") | E16: =IFERROR(AVERAGEIFS($H$37:$H$256,$A$37:$A$256,"SOL → BSC",$C$37:$C$256,$A16),"n/a") | F16: =IFERROR(AVERAGEIFS($H$37:$H$256,$A$37:$A$256,"BSC → SOL",$C$37:$C$256,$A16),"n/a") | G16: =IFERROR(AVERAGEIFS($H$37:$H$256,$A$37:$A$256,"SOL → Base",$C$37:$C$256,$A16),"n/a") | H16: =IFERROR(AVERAGEIFS($H$37:$H$256,$A$37:$A$256,"Base → SOL",$C$37:$C$256,$A16),"n/a") | N16: Meson | O16: =IFERROR(AVERAGEIFS($G$37:$G$256,$A$37:$A$256,"SOL → ETH",$C$37:$C$256,$N16),"") | P16: =IFERROR(AVERAGEIFS($G$37:$G$256,$A$37:$A$256,"ETH → SOL",$C$37:$C$256,$N16),"") | Q16: =IFERROR(AVERAGEIFS($G$37:$G$256,$A$37:$A$256,"SOL → BSC",$C$37:$C$256,$N16),"") | R16: =IFERROR(AVERAGEIFS($G$37:$G$256,$A$37:$A$256,"BSC → SOL",$C$37:$C$256,$N16),"") | S16: =IFERROR(AVERAGEIFS($G$37:$G$256,$A$37:$A$256,"SOL → Base",$C$37:$C$256,$N16),"") | T16: =IFERROR(AVERAGEIFS($G$37:$G$256,$A$37:$A$256,"Base → SOL",$C$37:$C$256,$N16),"")
A17: SimpleSwap | B17: venue | C17: =IFERROR(AVERAGEIFS($H$37:$H$256,$A$37:$A$256,"SOL → ETH",$C$37:$C$256,$A17),"n/a") | D17: =IFERROR(AVERAGEIFS($H$37:$H$256,$A$37:$A$256,"ETH → SOL",$C$37:$C$256,$A17),"n/a") | E17: =IFERROR(AVERAGEIFS($H$37:$H$256,$A$37:$A$256,"SOL → BSC",$C$37:$C$256,$A17),"n/a") | F17: =IFERROR(AVERAGEIFS($H$37:$H$256,$A$37:$A$256,"BSC → SOL",$C$37:$C$256,$A17),"n/a") | G17: =IFERROR(AVERAGEIFS($H$37:$H$256,$A$37:$A$256,"SOL → Base",$C$37:$C$256,$A17),"n/a") | H17: =IFERROR(AVERAGEIFS($H$37:$H$256,$A$37:$A$256,"Base → SOL",$C$37:$C$256,$A17),"n/a") | N17: SimpleSwap | O17: =IFERROR(AVERAGEIFS($G$37:$G$256,$A$37:$A$256,"SOL → ETH",$C$37:$C$256,$N17),"") | P17: =IFERROR(AVERAGEIFS($G$37:$G$256,$A$37:$A$256,"ETH → SOL",$C$37:$C$256,$N17),"") | Q17: =IFERROR(AVERAGEIFS($G$37:$G$256,$A$37:$A$256,"SOL → BSC",$C$37:$C$256,$N17),"") | R17: =IFERROR(AVERAGEIFS($G$37:$G$256,$A$37:$A$256,"BSC → SOL",$C$37:$C$256,$N17),"") | S17: =IFERROR(AVERAGEIFS($G$37:$G$256,$A$37:$A$256,"SOL → Base",$C$37:$C$256,$N17),"") | T17: =IFERROR(AVERAGEIFS($G$37:$G$256,$A$37:$A$256,"Base → SOL",$C$37:$C$256,$N17),"")
... A19: Symbiosis | B19: venue | C19: =IFERROR(AVERAGEIFS($H$37:$H$256,$A$37:$A$256,"SOL → ETH",$C$37:$C$256,$A19),"n/a") | D19: =IFERROR(AVERAGEIFS($H$37:$H$256,$A$37:$A$256,"ETH → SOL",$C$37:$C$256,$A19),"n/a") | E19: =IFERROR(AVERAGEIFS($H$37:$H$256,$A$37:$A$256,"SOL → BSC",$C$37:$C$256,$A19),"n/a") | F19: =IFERROR(AVERAGEIFS($H$37:$H$256,$A$37:$A$256,"BSC → SOL",$C$37:$C$256,$A19),"n/a") | G19: =IFERROR(AVERAGEIFS($H$37:$H$256,$A$37:$A$256,"SOL → Base",$C$37:$C$256,$A19),"n/a") | H19: =IFERROR(AVERAGEIFS($H$37:$H$256,$A$37:$A$256,"Base → SOL",$C$37:$C$256,$A19),"n/a") | N19: Symbiosis | O19: =IFERROR(AVERAGEIFS($G$37:$G$256,$A$37:$A$256,"SOL → ETH",$C$37:$C$256,$N19),"") | P19: =IFERROR(AVERAGEIFS($G$37:$G$256,$A$37:$A$256,"ETH → SOL",$C$37:$C$256,$N19),"") | Q19: =IFERROR(AVERAGEIFS($G$37:$G$256,$A$37:$A$256,"SOL → BSC",$C$37:$C$256,$N19),"") | R19: =IFERROR(AVERAGEIFS($G$37:$G$256,$A$37:$A$256,"BSC → SOL",$C$37:$C$256,$N19),"") | S19: =IFERROR(AVERAGEIFS($G$37:$G$256,$A$37:$A$256,"SOL → Base",$C$37:$C$256,$N19),"") | T19: =IFERROR(AVERAGEIFS($G$37:$G$256,$A$37:$A$256,"Base → SOL",$C$37:$C$256,$N19),"")
A20: Axiom | B20: platform | C20: BLOCKED — PARTIAL — no 100 USDC quote without funds. Signed-in check (user logged in; built-in browser, 2026-09-23): Axiom 'Exchange' has a cross-chain Convert (e.g. 'Swap USDC on Solana for USDC on Ethereum', indicative 1 USDC = 1.0000 USDC) but the amount field clamps to the wallet balance (0), so 100 can't be priced. Deposit auto-bridges EVM→Solana and shows fees only at its minimum: ETH→SOL USDC ($3 min) ~26s, impact −0.388%, fees ~$0.27 (gas $0.27, routing/liquidity <$0.01); BSC→SOL ($2 min) ~26s, impact −8.357%, fees ~$0.21 (gas); Base→SOL ($2 min) ~26s, impact −0.455%, fees ~$0.02. Indicative only — not comparable to a 100 USDC quote.
A21: FOMO | B21: platform | C21: BLOCKED — BLOCKED — signed-in check (user logged in): deposits accept USDC from Solana, Base, BNB Chain, Monad, Robinhood Chain, Arc, Ethereum into one USD cash balance; no fee/quote is shown at deposit and moving funds out needs a balance. No chain-to-chain quote.
A22: GMGN | B22: platform | C22: BLOCKED — BLOCKED — signed-in check (user logged in): wallet menu has Convert, but it requires binding 2FA (a security-setting change the user must make) and then a 3-hour lock before Convert works. Deposit accepts SOL/USDT/USDC/USD1 on the Solana network only.
A23: Pump.fun | B23: platform | C23: BLOCKED — BLOCKED — signed-in check (user logged in): web Deposit is Solana-only ('Only send assets on the Solana network', min 0.01 SOL). No cross-chain quote on web; the MoonPay cross-chain deposit reported in news may be mobile-only.
A26: Route winners
A27: Route | B27: Bridg best (avg) | C27: Best elsewhere (avg out) | D27: Site | E27: Bridg vs best (bps) | F27: Sites Bridg beats | G27: Sites beating Bridg
A28: SOL → ETH | B28: =IFERROR(AVERAGEIFS('Raw Quotes'!$K:$K,'Raw Quotes'!$B:$B,"SOL->ETH",'Raw Quotes'!$D:$D,"Bridg",'Raw Quotes'!$F:$F,"OK"),"") | C28: =MAX($O$6:$O$19) | D28: =INDEX($N$6:$N$19,MATCH(C28,$O$6:$O$19,0)) | E28: =(B28-C28)/100*10000 | F28: =COUNTIF($C$6:$C$19,">2") | G28: =COUNTIF($C$6:$C$19,"<-2") | H28: Bridg best is averaged per synchronized run (Raw Quotes); savings compare it with the best per-site average.
A29: ETH → SOL | B29: =IFERROR(AVERAGEIFS('Raw Quotes'!$K:$K,'Raw Quotes'!$B:$B,"ETH->SOL",'Raw Quotes'!$D:$D,"Bridg",'Raw Quotes'!$F:$F,"OK"),"") | C29: =MAX($P$6:$P$19) | D29: =INDEX($N$6:$N$19,MATCH(C29,$P$6:$P$19,0)) | E29: =(B29-C29)/100*10000 | F29: =COUNTIF($D$6:$D$19,">2") | G29: =COUNTIF($D$6:$D$19,"<-2")
A30: SOL → BSC | B30: =IFERROR(AVERAGEIFS('Raw Quotes'!$K:$K,'Raw Quotes'!$B:$B,"SOL->BSC",'Raw Quotes'!$D:$D,"Bridg",'Raw Quotes'!$F:$F,"OK"),"") | C30: =MAX($Q$6:$Q$19) | D30: =INDEX($N$6:$N$19,MATCH(C30,$Q$6:$Q$19,0)) | E30: =(B30-C30)/100*10000 | F30: =COUNTIF($E$6:$E$19,">2") | G30: =COUNTIF($E$6:$E$19,"<-2")
A31: BSC → SOL | B31: =IFERROR(AVERAGEIFS('Raw Quotes'!$K:$K,'Raw Quotes'!$B:$B,"BSC->SOL",'Raw Quotes'!$D:$D,"Bridg",'Raw Quotes'!$F:$F,"OK"),"") | C31: =MAX($R$6:$R$19) | D31: =INDEX($N$6:$N$19,MATCH(C31,$R$6:$R$19,0)) | E31: =(B31-C31)/100*10000 | F31: =COUNTIF($F$6:$F$19,">2") | G31: =COUNTIF($F$6:$F$19,"<-2")
A32: SOL → Base | B32: =IFERROR(AVERAGEIFS('Raw Quotes'!$K:$K,'Raw Quotes'!$B:$B,"SOL->Base",'Raw Quotes'!$D:$D,"Bridg",'Raw Quotes'!$F:$F,"OK"),"") | C32: =MAX($S$6:$S$19) | D32: =INDEX($N$6:$N$19,MATCH(C32,$S$6:$S$19,0)) | E32: =(B32-C32)/100*10000 | F32: =COUNTIF($G$6:$G$19,">2") | G32: =COUNTIF($G$6:$G$19,"<-2")
A33: Base → SOL | B33: =IFERROR(AVERAGEIFS('Raw Quotes'!$K:$K,'Raw Quotes'!$B:$B,"Base->SOL",'Raw Quotes'!$D:$D,"Bridg",'Raw Quotes'!$F:$F,"OK"),"") | C33: =MAX($T$6:$T$19) | D33: =INDEX($N$6:$N$19,MATCH(C33,$T$6:$T$19,0)) | E33: =(B33-C33)/100*10000 | F33: =COUNTIF($H$6:$H$19,">2") | G33: =COUNTIF($H$6:$H$19,"<-2")
A35: Per-sample observations
A36: Route | B36: Sample | C36: Site | D36: Kind | E36: Bridg best | F36: Bridg best via | G36: Other out (cmp) | H36: Savings bps | I36: Fee on top in SOL/ETH (not counted) | J36: Bridg value read (UTC) | K36: Other value read (UTC) | L36: Δ read (s)
A37: SOL → ETH | B37: 1 | C37: OpenSea | D37: platform | E37: 99.840015 | F37: Across | G37: 98.9896 | H37: =(E37-G37)/100*10000 | I37: yes | J37: 2026-09-23T14:18:55.406Z | K37: 2026-09-23T14:18:55.405Z | L37: 0.001
A38: SOL → ETH | B38: 2 | C38: OpenSea | D38: platform | E38: 99.840015 | F38: Across | G38: 98.7874 | H38: =(E38-G38)/100*10000 | J38: 2026-09-23T14:22:28.648Z | K38: 2026-09-23T14:22:28.640Z | L38: 0.008
A39: SOL → ETH | B39: 3 | C39: OpenSea | D39: platform | E39: 99.840015 | F39: Across | G39: 99.067 | H39: =(E39-G39)/100*10000 | I39: yes | J39: 2026-09-23T14:26:54.591Z | K39: 2026-09-23T14:26:54.593Z | L39: 0.002
A40: SOL → ETH | B40: 1 | C40: Relay | D40: venue | E40: 99.840015 | F40: Across | G40: 99.193956 | H40: =(E40-G40)/100*10000 | J40: 2026-09-23T14:18:55.406Z | K40: 2026-09-23T14:18:55.404Z | L40: 0.002
A41: SOL → ETH | B41: 2 | C41: Relay | D41: venue | E41: 99.840015 | F41: Across | G41: 99.087326 | H41: =(E41-G41)/100*10000 | J41: 2026-09-23T14:22:28.648Z | K41: 2026-09-23T14:22:28.645Z | L41: 0.003
A42: SOL → ETH | B42: 3 | C42: Relay | D42: venue | E42: 99.840015 | F42: Across | G42: 99.260036 | H42: =(E42-G42)/100*10000 | J42: 2026-09-23T14:26:54.591Z | K42: 2026-09-23T14:26:54.589Z | L42: 0.002
A43: SOL → ETH | B43: 1 | C43: deBridge | D43: venue | E43: 99.840015 | F43: Across | G43: 96.984618 | H43: =(E43-G43)/100*10000 | J43: 2026-09-23T14:18:55.406Z | K43: 2026-09-23T14:18:55.402Z | L43: 0.004
A44: SOL → ETH | B44: 2 | C44: deBridge | D44: venue | E44: 99.840015 | F44: Across | G44: 96.646618 | H44: =(E44-G44)/100*10000 | J44: 2026-09-23T14:22:28.648Z | K44: 2026-09-23T14:22:28.646Z | L44: 0.002
A45: SOL → ETH | B45: 3 | C45: deBridge | D45: venue | E45: 99.840015 | F45: Across | G45: 97.060133 | H45: =(E45-G45)/100*10000 | J45: 2026-09-23T14:26:54.591Z | K45: 2026-09-23T14:26:54.593Z | L45: 0.002
A46: SOL → ETH | B46: 1 | C46: LI.FI (Jumper) | D46: venue | E46: 99.840015 | F46: Across | G46: 99.193956 | H46: =(E46-G46)/100*10000 | J46: 2026-09-23T14:18:55.406Z | K46: 2026-09-23T14:18:55.400Z | L46: 0.006
A47: SOL → ETH | B47: 2 | C47: LI.FI (Jumper) | D47: venue | E47: 99.840015 | F47: Across | G47: 99.087326 | H47: =(E47-G47)/100*10000 | J47: 2026-09-23T14:22:28.648Z | K47: 2026-09-23T14:22:28.650Z | L47: 0.002
A48: SOL → ETH | B48: 3 | C48: LI.FI (Jumper) | D48: venue | E48: 99.840015 | F48: Across | G48: 99.260036 | H48: =(E48-G48)/100*10000 | J48: 2026-09-23T14:26:54.591Z | K48: 2026-09-23T14:26:54.591Z | L48: 0
A49: SOL → ETH | B49: 1 | C49: Across | D49: venue | E49: 99.840015 | F49: Across | G49: 99.99 | H49: =(E49-G49)/100*10000 | J49: 2026-09-23T14:18:55.406Z | K49: 2026-09-23T14:18:55.400Z | L49: 0.006
A50: SOL → ETH | B50: 2 | C50: Across | D50: venue | E50: 99.840015 | F50: Across | G50: 99.99 | H50: =(E50-G50)/100*10000 | J50: 2026-09-23T14:22:28.648Z | K50: 2026-09-23T14:22:28.644Z | L50: 0.004
A51: SOL → ETH | B51: 3 | C51: Across | D51: venue | E51: 99.840015 | F51: Across | G51: 99.99 | H51: =(E51-G51)/100*10000 | J51: 2026-09-23T14:26:54.591Z | K51: 2026-09-23T14:26:54.589Z | L51: 0.002
... A54: SOL → ETH | B54: 3 | C54: Mayan | D54: venue | E54: 99.840015 | F54: Across | G54: 96.851 | H54: =(E54-G54)/100*10000 | J54: 2026-09-23T14:26:54.591Z | K54: 2026-09-23T14:26:54.588Z | L54: 0.003
A55: SOL → ETH | B55: 1 | C55: Allbridge Core | D55: venue | E55: 99.840015 | F55: Across | G55: 99.9 | H55: =(E55-G55)/100*10000 | I55: yes | J55: 2026-09-23T14:18:55.406Z | K55: 2026-09-23T14:18:55.401Z | L55: 0.005
A56: SOL → ETH | B56: 2 | C56: Allbridge Core | D56: venue | E56: 99.840015 | F56: Across | G56: 99.9 | H56: =(E56-G56)/100*10000 | I56: yes | J56: 2026-09-23T14:22:28.648Z | K56: 2026-09-23T14:22:28.644Z | L56: 0.004
A57: SOL → ETH | B57: 3 | C57: Allbridge Core | D57: venue | E57: 99.840015 | F57: Across | G57: 99.9 | H57: =(E57-G57)/100*10000 | I57: yes | J57: 2026-09-23T14:26:54.591Z | K57: 2026-09-23T14:26:54.590Z | L57: 0.001
A58: SOL → ETH | B58: 1 | C58: CCTP (via Portal) | D58: venue | E58: 99.840015 | F58: Across | G58: 99.99 | H58: =(E58-G58)/100*10000 | J58: 2026-09-23T14:18:55.406Z | K58: 2026-09-23T14:18:55.406Z | L58: 0
A59: SOL → ETH | B59: 2 | C59: CCTP (via Portal) | D59: venue | E59: 99.840015 | F59: Across | G59: 99.99 | H59: =(E59-G59)/100*10000 | J59: 2026-09-23T14:22:28.648Z | K59: 2026-09-23T14:22:28.649Z | L59: 0.001
A60: SOL → ETH | B60: 3 | C60: CCTP (via Portal) | D60: venue | E60: 99.840015 | F60: Across | G60: 99.99 | H60: =(E60-G60)/100*10000 | J60: 2026-09-23T14:26:54.591Z | K60: 2026-09-23T14:26:54.588Z | L60: 0.003
A61: SOL → ETH | B61: 1 | C61: Husher | D61: venue | E61: 99.840015 | F61: Across | G61: 99.05 | H61: =(E61-G61)/100*10000 | J61: 2026-09-23T14:18:55.406Z | K61: 2026-09-23T14:18:55.401Z | L61: 0.005
A62: SOL → ETH | B62: 2 | C62: Husher | D62: venue | E62: 99.840015 | F62: Across | G62: 99.05 | H62: =(E62-G62)/100*10000 | J62: 2026-09-23T14:22:28.648Z | K62: 2026-09-23T14:22:28.643Z | L62: 0.005
A63: SOL → ETH | B63: 3 | C63: Husher | D63: venue | E63: 99.840015 | F63: Across | G63: 99.05 | H63: =(E63-G63)/100*10000 | J63: 2026-09-23T14:26:54.591Z | K63: 2026-09-23T14:26:54.589Z | L63: 0.002
A64: SOL → ETH | B64: 1 | C64: Layerswap | D64: venue | E64: 99.840015 | F64: Across | G64: 99.716863 | H64: =(E64-G64)/100*10000 | J64: 2026-09-23T14:18:55.406Z | K64: 2026-09-23T14:18:55.402Z | L64: 0.004
A65: SOL → ETH | B65: 2 | C65: Layerswap | D65: venue | E65: 99.840015 | F65: Across | G65: 99.717755 | H65: =(E65-G65)/100*10000 | J65: 2026-09-23T14:22:28.648Z | K65: 2026-09-23T14:22:28.646Z | L65: 0.002
A66: SOL → ETH | B66: 3 | C66: Layerswap | D66: venue | E66: 99.840015 | F66: Across | G66: 99.706546 | H66: =(E66-G66)/100*10000 | J66: 2026-09-23T14:26:54.591Z | K66: 2026-09-23T14:26:54.592Z | L66: 0.001
A67: SOL → ETH | B67: 1 | C67: Meson | D67: venue | E67: 99.840015 | F67: Across | G67: 98.65 | H67: =(E67-G67)/100*10000 | J67: 2026-09-23T14:18:55.406Z | K67: 2026-09-23T14:18:55.400Z | L67: 0.006
A68: SOL → ETH | B68: 2 | C68: Meson | D68: venue | E68: 99.840015 | F68: Across | G68: 98.37 | H68: =(E68-G68)/100*10000 | J68: 2026-09-23T14:22:28.648Z | K68: 2026-09-23T14:22:28.642Z | L68: 0.006
A69: SOL → ETH | B69: 3 | C69: Meson | D69: venue | E69: 99.840015 | F69: Across | G69: 98.67 | H69: =(E69-G69)/100*10000 | J69: 2026-09-23T14:26:54.591Z | K69: 2026-09-23T14:26:54.588Z | L69: 0.003
... A78: SOL → ETH | B78: 3 | C78: Symbiosis | D78: venue | E78: 99.840015 | F78: Across | G78: 96.510498 | H78: =(E78-G78)/100*10000 | J78: 2026-09-23T14:26:54.591Z | K78: 2026-09-23T14:26:54.591Z | L78: 0
A79: ETH → SOL | B79: 1 | C79: OpenSea | D79: platform | E79: 99.85005 | F79: Allbridge Core | G79: 99.7459 | H79: =(E79-G79)/100*10000 | I79: yes | J79: 2026-09-23T14:19:28.697Z | K79: 2026-09-23T14:19:28.701Z | L79: 0.004
A80: ETH → SOL | B80: 2 | C80: OpenSea | D80: platform | E80: 99.85005 | F80: Allbridge Core | G80: 99.7453 | H80: =(E80-G80)/100*10000 | I80: yes | J80: 2026-09-23T14:23:47.144Z | K80: 2026-09-23T14:23:47.145Z | L80: 0.001
A81: ETH → SOL | B81: 3 | C81: OpenSea | D81: platform | E81: 99.85005 | F81: Allbridge Core | G81: 99.7466 | H81: =(E81-G81)/100*10000 | I81: yes | J81: 2026-09-23T14:27:28.356Z | K81: 2026-09-23T14:27:28.357Z | L81: 0.001
A82: ETH → SOL | B82: 1 | C82: Relay | D82: venue | E82: 99.85005 | F82: Allbridge Core | G82: 99.945703 | H82: =(E82-G82)/100*10000 | J82: 2026-09-23T14:19:28.697Z | K82: 2026-09-23T14:19:28.698Z | L82: 0.001
A83: ETH → SOL | B83: 2 | C83: Relay | D83: venue | E83: 99.85005 | F83: Allbridge Core | G83: 99.945717 | H83: =(E83-G83)/100*10000 | J83: 2026-09-23T14:23:47.144Z | K83: 2026-09-23T14:23:47.141Z | L83: 0.003
A84: ETH → SOL | B84: 3 | C84: Relay | D84: venue | E84: 99.85005 | F84: Allbridge Core | G84: 99.945713 | H84: =(E84-G84)/100*10000 | J84: 2026-09-23T14:27:28.356Z | K84: 2026-09-23T14:27:28.355Z | L84: 0.001
A85: ETH → SOL | B85: 1 | C85: deBridge | D85: venue | E85: 99.85005 | F85: Allbridge Core | G85: 97.955018 | H85: =(E85-G85)/100*10000 | J85: 2026-09-23T14:19:28.697Z | K85: 2026-09-23T14:19:28.698Z | L85: 0.001
A86: ETH → SOL | B86: 2 | C86: deBridge | D86: venue | E86: 99.85005 | F86: Allbridge Core | G86: 97.835618 | H86: =(E86-G86)/100*10000 | J86: 2026-09-23T14:23:47.144Z | K86: 2026-09-23T14:23:47.140Z | L86: 0.004
A87: ETH → SOL | B87: 3 | C87: deBridge | D87: venue | E87: 99.85005 | F87: Allbridge Core | G87: 93.263435 | H87: =(E87-G87)/100*10000 | J87: 2026-09-23T14:27:28.356Z | K87: 2026-09-23T14:27:28.355Z | L87: 0.001
A88: ETH → SOL | B88: 1 | C88: LI.FI (Jumper) | D88: venue | E88: 99.85005 | F88: Allbridge Core | G88: 99.945703 | H88: =(E88-G88)/100*10000 | J88: 2026-09-23T14:19:28.697Z | K88: 2026-09-23T14:19:28.698Z | L88: 0.001
A89: ETH → SOL | B89: 2 | C89: LI.FI (Jumper) | D89: venue | E89: 99.85005 | F89: Allbridge Core | G89: 99.945717 | H89: =(E89-G89)/100*10000 | J89: 2026-09-23T14:23:47.144Z | K89: 2026-09-23T14:23:47.142Z | L89: 0.002
A90: ETH → SOL | B90: 3 | C90: LI.FI (Jumper) | D90: venue | E90: 99.85005 | F90: Allbridge Core | G90: 99.945713 | H90: =(E90-G90)/100*10000 | J90: 2026-09-23T14:27:28.356Z | K90: 2026-09-23T14:27:28.356Z | L90: 0
A91: ETH → SOL | B91: 1 | C91: Across | D91: venue | E91: 99.85005 | F91: Allbridge Core | G91: 99.99 | H91: =(E91-G91)/100*10000 | J91: 2026-09-23T14:19:28.697Z | K91: 2026-09-23T14:19:28.697Z | L91: 0
A92: ETH → SOL | B92: 2 | C92: Across | D92: venue | E92: 99.85005 | F92: Allbridge Core | G92: 99.99 | H92: =(E92-G92)/100*10000 | J92: 2026-09-23T14:23:47.144Z | K92: 2026-09-23T14:23:47.139Z | L92: 0.005
A93: ETH → SOL | B93: 3 | C93: Across | D93: venue | E93: 99.85005 | F93: Allbridge Core | G93: 99.99 | H93: =(E93-G93)/100*10000 | J93: 2026-09-23T14:27:28.356Z | K93: 2026-09-23T14:27:28.355Z | L93: 0.001
... A96: ETH → SOL | B96: 3 | C96: Mayan | D96: venue | E96: 99.85005 | F96: Allbridge Core | G96: 99.0287 | H96: =(E96-G96)/100*10000 | J96: 2026-09-23T14:27:28.356Z | K96: 2026-09-23T14:27:28.354Z | L96: 0.002
A97: ETH → SOL | B97: 1 | C97: Allbridge Core | D97: venue | E97: 99.85005 | F97: Allbridge Core | G97: 99.9 | H97: =(E97-G97)/100*10000 | I97: yes | J97: 2026-09-23T14:19:28.697Z | K97: 2026-09-23T14:19:28.697Z | L97: 0
A98: ETH → SOL | B98: 2 | C98: Allbridge Core | D98: venue | E98: 99.85005 | F98: Allbridge Core | G98: 99.9 | H98: =(E98-G98)/100*10000 | I98: yes | J98: 2026-09-23T14:23:47.144Z | K98: 2026-09-23T14:23:47.139Z | L98: 0.005
A99: ETH → SOL | B99: 3 | C99: Allbridge Core | D99: venue | E99: 99.85005 | F99: Allbridge Core | G99: 99.9 | H99: =(E99-G99)/100*10000 | I99: yes | J99: 2026-09-23T14:27:28.356Z | K99: 2026-09-23T14:27:28.354Z | L99: 0.002
A100: ETH → SOL | B100: 1 | C100: CCTP (via Portal) | D100: venue | E100: 99.85005 | F100: Allbridge Core | G100: 99.980001 | H100: =(E100-G100)/100*10000 | J100: 2026-09-23T14:19:28.697Z | K100: 2026-09-23T14:19:28.696Z | L100: 0.001
A101: ETH → SOL | B101: 2 | C101: CCTP (via Portal) | D101: venue | E101: 99.85005 | F101: Allbridge Core | G101: 99.980001 | H101: =(E101-G101)/100*10000 | J101: 2026-09-23T14:23:47.144Z | K101: 2026-09-23T14:23:47.145Z | L101: 0.001
A102: ETH → SOL | B102: 3 | C102: CCTP (via Portal) | D102: venue | E102: 99.85005 | F102: Allbridge Core | G102: 99.980001 | H102: =(E102-G102)/100*10000 | J102: 2026-09-23T14:27:28.356Z | K102: 2026-09-23T14:27:28.353Z | L102: 0.003
A103: ETH → SOL | B103: 1 | C103: Husher | D103: venue | E103: 99.85005 | F103: Allbridge Core | G103: 99.35 | H103: =(E103-G103)/100*10000 | J103: 2026-09-23T14:19:28.697Z | K103: 2026-09-23T14:19:28.696Z | L103: 0.001
A104: ETH → SOL | B104: 2 | C104: Husher | D104: venue | E104: 99.85005 | F104: Allbridge Core | G104: 99.35 | H104: =(E104-G104)/100*10000 | J104: 2026-09-23T14:23:47.144Z | K104: 2026-09-23T14:23:47.140Z | L104: 0.004
A105: ETH → SOL | B105: 3 | C105: Husher | D105: venue | E105: 99.85005 | F105: Allbridge Core | G105: 99.35 | H105: =(E105-G105)/100*10000 | J105: 2026-09-23T14:27:28.356Z | K105: 2026-09-23T14:27:28.354Z | L105: 0.002
A106: ETH → SOL | B106: 1 | C106: Layerswap | D106: venue | E106: 99.85005 | F106: Allbridge Core | G106: 99.681249 | H106: =(E106-G106)/100*10000 | J106: 2026-09-23T14:19:28.697Z | K106: 2026-09-23T14:19:28.699Z | L106: 0.002
A107: ETH → SOL | B107: 2 | C107: Layerswap | D107: venue | E107: 99.85005 | F107: Allbridge Core | G107: 99.682776 | H107: =(E107-G107)/100*10000 | J107: 2026-09-23T14:23:47.144Z | K107: 2026-09-23T14:23:47.143Z | L107: 0.001
A108: ETH → SOL | B108: 3 | C108: Layerswap | D108: venue | E108: 99.85005 | F108: Allbridge Core | G108: 99.682757 | H108: =(E108-G108)/100*10000 | J108: 2026-09-23T14:27:28.356Z | K108: 2026-09-23T14:27:28.356Z | L108: 0
A109: ETH → SOL | B109: 1 | C109: Meson | D109: venue | E109: 99.85005 | F109: Allbridge Core | G109: 99.1 | H109: =(E109-G109)/100*10000 | J109: 2026-09-23T14:19:28.697Z | K109: 2026-09-23T14:19:28.696Z | L109: 0.001
A110: ETH → SOL | B110: 2 | C110: Meson | D110: venue | E110: 99.85005 | F110: Allbridge Core | G110: 99.1 | H110: =(E110-G110)/100*10000 | J110: 2026-09-23T14:23:47.144Z | K110: 2026-09-23T14:23:47.137Z | L110: 0.007
A111: ETH → SOL | B111: 3 | C111: Meson | D111: venue | E111: 99.85005 | F111: Allbridge Core | G111: 99.1 | H111: =(E111-G111)/100*10000 | J111: 2026-09-23T14:27:28.356Z | K111: 2026-09-23T14:27:28.354Z | L111: 0.002
... A175: BSC → SOL | B175: 3 | C175: Symbiosis | D175: venue | E175: 99.640843 | F175: Mayan | G175: 98.357827 | H175: =(E175-G175)/100*10000 | J175: 2026-09-23T14:29:48.304Z | K175: 2026-09-23T14:29:48.305Z | L175: 0.001
A176: SOL → Base | B176: 1 | C176: OpenSea | D176: platform | E176: 99.943099 | F176: Skip Go | G176: 99.9332 | H176: =(E176-G176)/100*10000 | I176: yes | J176: 2026-09-23T14:21:09.321Z | K176: 2026-09-23T14:21:09.322Z | L176: 0.001
A177: SOL → Base | B177: 2 | C177: OpenSea | D177: platform | E177: 99.943099 | F177: Skip Go | G177: 99.9254 | H177: =(E177-G177)/100*10000 | I177: yes | J177: 2026-09-23T14:25:46.682Z | K177: 2026-09-23T14:25:46.683Z | L177: 0.001
A178: SOL → Base | B178: 3 | C178: OpenSea | D178: platform | E178: 99.943883 | F178: Skip Go | G178: 99.9409 | H178: =(E178-G178)/100*10000 | I178: yes | J178: 2026-09-23T14:30:23.906Z | K178: 2026-09-23T14:30:23.906Z | L178: 0
A179: SOL → Base | B179: 1 | C179: Relay | D179: venue | E179: 99.943099 | F179: Skip Go | G179: 99.937898 | H179: =(E179-G179)/100*10000 | J179: 2026-09-23T14:21:09.321Z | K179: 2026-09-23T14:21:09.318Z | L179: 0.003
A180: SOL → Base | B180: 2 | C180: Relay | D180: venue | E180: 99.943099 | F180: Skip Go | G180: 99.933529 | H180: =(E180-G180)/100*10000 | J180: 2026-09-23T14:25:46.682Z | K180: 2026-09-23T14:25:46.682Z | L180: 0
...

Sheet Venue Analysis
A1: Venue Analysis — is Bridg's listed quote for each venue the same as the venue's own site?
A2: Gap (bps) = (Bridg listed − venue direct) / 100 × 10,000. Ex-fee adds Bridg's platform fee back. Direct = venue out − any USDC fee charged on top of the 100 input. Blue = observed inputs; black = formulas.
A4: Route | B4: Sample | C4: Venue | D4: Bridg listed | E4: Compare only | F4: Venue out | G4: USDC fee on top | H4: Direct (cmp) | I4: Gap bps | J4: Bridg fee (USDC) | K4: Gap ex-fee bps | L4: Δ read (s) | M4: Note | N4: Bridg value read (UTC) | O4: Venue value read (UTC) | Q4: Route | R4: Venue | S4: Samples | T4: Listed on Bridg | U4: Bridg avg | V4: Direct avg | W4: Gap bps (avg) | X4: Ex-fee bps (avg) | Y4: Tolerance bps | Z4: Verdict
A5: SOL → ETH | B5: 1 | C5: Relay | D5: 98.880917 | F5: 99.193956 | H5: =IF(ISNUMBER(F5),F5-N(G5),"") | I5: =IF(AND(ISNUMBER(D5),ISNUMBER(H5)),(D5-H5)/100*10000,"") | J5: 0.05 | K5: =IF(ISNUMBER(I5),I5+N(J5)/100*10000,"") | L5: 0.002 | N5: 2026-09-23T14:18:55.406Z | O5: 2026-09-23T14:18:55.404Z | Q5: SOL → ETH | R5: Relay | S5: =COUNTIFS($A$5:$A$214,Q5,$C$5:$C$214,R5) | T5: =COUNTIFS($A$5:$A$214,Q5,$C$5:$C$214,R5,$D$5:$D$214,">0") | U5: =IFERROR(AVERAGEIFS($D$5:$D$214,$A$5:$A$214,Q5,$C$5:$C$214,R5),"—") | V5: =IFERROR(AVERAGEIFS($H$5:$H$214,$A$5:$A$214,Q5,$C$5:$C$214,R5),"—") | W5: =IFERROR(AVERAGEIFS($I$5:$I$214,$A$5:$A$214,Q5,$C$5:$C$214,R5),"—") | X5: =IFERROR(AVERAGEIFS($K$5:$K$214,$A$5:$A$214,Q5,$C$5:$C$214,R5),"—") | Y5: 2 | Z5: =IF(T5=0,"NOT LISTED on Bridg",IF(NOT(ISNUMBER(X5)),"No direct quote",IF(ABS(X5)<=Y5,"Match (net of Bridg fee)",IF(ABS(W5)<=Y5,"Match (Bridg fee not applied)",IF(X5<0,"Bridg LOWER than venue","Bridg HIGHER than venue")))))
A6: SOL → ETH | B6: 2 | C6: Relay | D6: 98.744355 | F6: 99.087326 | H6: =IF(ISNUMBER(F6),F6-N(G6),"") | I6: =IF(AND(ISNUMBER(D6),ISNUMBER(H6)),(D6-H6)/100*10000,"") | J6: 0.05 | K6: =IF(ISNUMBER(I6),I6+N(J6)/100*10000,"") | L6: 0.003 | N6: 2026-09-23T14:22:28.648Z | O6: 2026-09-23T14:22:28.645Z | Q6: SOL → ETH | R6: deBridge | S6: =COUNTIFS($A$5:$A$214,Q6,$C$5:$C$214,R6) | T6: =COUNTIFS($A$5:$A$214,Q6,$C$5:$C$214,R6,$D$5:$D$214,">0") | U6: =IFERROR(AVERAGEIFS($D$5:$D$214,$A$5:$A$214,Q6,$C$5:$C$214,R6),"—") | V6: =IFERROR(AVERAGEIFS($H$5:$H$214,$A$5:$A$214,Q6,$C$5:$C$214,R6),"—") | W6: =IFERROR(AVERAGEIFS($I$5:$I$214,$A$5:$A$214,Q6,$C$5:$C$214,R6),"—") | X6: =IFERROR(AVERAGEIFS($K$5:$K$214,$A$5:$A$214,Q6,$C$5:$C$214,R6),"—") | Y6: 2 | Z6: =IF(T6=0,"NOT LISTED on Bridg",IF(NOT(ISNUMBER(X6)),"No direct quote",IF(ABS(X6)<=Y6,"Match (net of Bridg fee)",IF(ABS(W6)<=Y6,"Match (Bridg fee not applied)",IF(X6<0,"Bridg LOWER than venue","Bridg HIGHER than venue")))))
A7: SOL → ETH | B7: 3 | C7: Relay | D7: 99.017721 | F7: 99.260036 | H7: =IF(ISNUMBER(F7),F7-N(G7),"") | I7: =IF(AND(ISNUMBER(D7),ISNUMBER(H7)),(D7-H7)/100*10000,"") | J7: 0.05 | K7: =IF(ISNUMBER(I7),I7+N(J7)/100*10000,"") | L7: 0.002 | N7: 2026-09-23T14:26:54.591Z | O7: 2026-09-23T14:26:54.589Z | Q7: SOL → ETH | R7: LI.FI (Jumper) | S7: =COUNTIFS($A$5:$A$214,Q7,$C$5:$C$214,R7) | T7: =COUNTIFS($A$5:$A$214,Q7,$C$5:$C$214,R7,$D$5:$D$214,">0") | U7: =IFERROR(AVERAGEIFS($D$5:$D$214,$A$5:$A$214,Q7,$C$5:$C$214,R7),"—") | V7: =IFERROR(AVERAGEIFS($H$5:$H$214,$A$5:$A$214,Q7,$C$5:$C$214,R7),"—") | W7: =IFERROR(AVERAGEIFS($I$5:$I$214,$A$5:$A$214,Q7,$C$5:$C$214,R7),"—") | X7: =IFERROR(AVERAGEIFS($K$5:$K$214,$A$5:$A$214,Q7,$C$5:$C$214,R7),"—") | Y7: 2 | Z7: =IF(T7=0,"NOT LISTED on Bridg",IF(NOT(ISNUMBER(X7)),"No direct quote",IF(ABS(X7)<=Y7,"Match (net of Bridg fee)",IF(ABS(W7)<=Y7,"Match (Bridg fee not applied)",IF(X7<0,"Bridg LOWER than venue","Bridg HIGHER than venue")))))
A8: SOL → ETH | B8: 1 | C8: deBridge | D8: 96.986978 | F8: 99.920018 | G8: 2.9354 | H8: =IF(ISNUMBER(F8),F8-N(G8),"") | I8: =IF(AND(ISNUMBER(D8),ISNUMBER(H8)),(D8-H8)/100*10000,"") | J8: 0.15 | K8: =IF(ISNUMBER(I8),I8+N(J8)/100*10000,"") | L8: 0.004 | M8: +2.9354 USDC charged on top of 100 input (subtracted) | N8: 2026-09-23T14:18:55.406Z | O8: 2026-09-23T14:18:55.402Z | Q8: SOL → ETH | R8: Across | S8: =COUNTIFS($A$5:$A$214,Q8,$C$5:$C$214,R8) | T8: =COUNTIFS($A$5:$A$214,Q8,$C$5:$C$214,R8,$D$5:$D$214,">0") | U8: =IFERROR(AVERAGEIFS($D$5:$D$214,$A$5:$A$214,Q8,$C$5:$C$214,R8),"—") | V8: =IFERROR(AVERAGEIFS($H$5:$H$214,$A$5:$A$214,Q8,$C$5:$C$214,R8),"—") | W8: =IFERROR(AVERAGEIFS($I$5:$I$214,$A$5:$A$214,Q8,$C$5:$C$214,R8),"—") | X8: =IFERROR(AVERAGEIFS($K$5:$K$214,$A$5:$A$214,Q8,$C$5:$C$214,R8),"—") | Y8: 2 | Z8: =IF(T8=0,"NOT LISTED on Bridg",IF(NOT(ISNUMBER(X8)),"No direct quote",IF(ABS(X8)<=Y8,"Match (net of Bridg fee)",IF(ABS(W8)<=Y8,"Match (Bridg fee not applied)",IF(X8<0,"Bridg LOWER than venue","Bridg HIGHER than venue")))))
A9: SOL → ETH | B9: 2 | C9: deBridge | D9: 96.649264 | F9: 99.920018 | G9: 3.2734 | H9: =IF(ISNUMBER(F9),F9-N(G9),"") | I9: =IF(AND(ISNUMBER(D9),ISNUMBER(H9)),(D9-H9)/100*10000,"") | J9: 0.15 | K9: =IF(ISNUMBER(I9),I9+N(J9)/100*10000,"") | L9: 0.002 | M9: +3.2734 USDC charged on top of 100 input (subtracted) | N9: 2026-09-23T14:22:28.648Z | O9: 2026-09-23T14:22:28.646Z | Q9: SOL → ETH | R9: Mayan | S9: =COUNTIFS($A$5:$A$214,Q9,$C$5:$C$214,R9) | T9: =COUNTIFS($A$5:$A$214,Q9,$C$5:$C$214,R9,$D$5:$D$214,">0") | U9: =IFERROR(AVERAGEIFS($D$5:$D$214,$A$5:$A$214,Q9,$C$5:$C$214,R9),"—") | V9: =IFERROR(AVERAGEIFS($H$5:$H$214,$A$5:$A$214,Q9,$C$5:$C$214,R9),"—") | W9: =IFERROR(AVERAGEIFS($I$5:$I$214,$A$5:$A$214,Q9,$C$5:$C$214,R9),"—") | X9: =IFERROR(AVERAGEIFS($K$5:$K$214,$A$5:$A$214,Q9,$C$5:$C$214,R9),"—") | Y9: 4 | Z9: =IF(T9=0,"NOT LISTED on Bridg",IF(NOT(ISNUMBER(X9)),"No direct quote",IF(ABS(X9)<=Y9,"Match (net of Bridg fee)",IF(ABS(W9)<=Y9,"Match (Bridg fee not applied)",IF(X9<0,"Bridg LOWER than venue","Bridg HIGHER than venue")))))
A10: SOL → ETH | B10: 3 | C10: deBridge | D10: 97.026152 | F10: 99.880033 | G10: 2.8199 | H10: =IF(ISNUMBER(F10),F10-N(G10),"") | I10: =IF(AND(ISNUMBER(D10),ISNUMBER(H10)),(D10-H10)/100*10000,"") | J10: 0.15 | K10: =IF(ISNUMBER(I10),I10+N(J10)/100*10000,"") | L10: 0.002 | M10: +2.8199 USDC charged on top of 100 input (subtracted) | N10: 2026-09-23T14:26:54.591Z | O10: 2026-09-23T14:26:54.593Z | Q10: SOL → ETH | R10: Allbridge Core | S10: =COUNTIFS($A$5:$A$214,Q10,$C$5:$C$214,R10) | T10: =COUNTIFS($A$5:$A$214,Q10,$C$5:$C$214,R10,$D$5:$D$214,">0") | U10: =IFERROR(AVERAGEIFS($D$5:$D$214,$A$5:$A$214,Q10,$C$5:$C$214,R10),"—") | V10: =IFERROR(AVERAGEIFS($H$5:$H$214,$A$5:$A$214,Q10,$C$5:$C$214,R10),"—") | W10: =IFERROR(AVERAGEIFS($I$5:$I$214,$A$5:$A$214,Q10,$C$5:$C$214,R10),"—") | X10: =IFERROR(AVERAGEIFS($K$5:$K$214,$A$5:$A$214,Q10,$C$5:$C$214,R10),"—") | Y10: 2 | Z10: =IF(T10=0,"NOT LISTED on Bridg",IF(NOT(ISNUMBER(X10)),"No direct quote",IF(ABS(X10)<=Y10,"Match (net of Bridg fee)",IF(ABS(W10)<=Y10,"Match (Bridg fee not applied)",IF(X10<0,"Bridg LOWER than venue","Bridg HIGHER than venue")))))
A11: SOL → ETH | B11: 1 | C11: LI.FI (Jumper) | D11: 98.887005 | F11: 99.193956 | H11: =IF(ISNUMBER(F11),F11-N(G11),"") | I11: =IF(AND(ISNUMBER(D11),ISNUMBER(H11)),(D11-H11)/100*10000,"") | J11: 0.15 | K11: =IF(ISNUMBER(I11),I11+N(J11)/100*10000,"") | L11: 0.006 | M11: Jumper Best Return via Relay; max route 99.99 | N11: 2026-09-23T14:18:55.406Z | O11: 2026-09-23T14:18:55.400Z | Q11: SOL → ETH | R11: CCTP (via Portal) | S11: =COUNTIFS($A$5:$A$214,Q11,$C$5:$C$214,R11) | T11: =COUNTIFS($A$5:$A$214,Q11,$C$5:$C$214,R11,$D$5:$D$214,">0") | U11: =IFERROR(AVERAGEIFS($D$5:$D$214,$A$5:$A$214,Q11,$C$5:$C$214,R11),"—") | V11: =IFERROR(AVERAGEIFS($H$5:$H$214,$A$5:$A$214,Q11,$C$5:$C$214,R11),"—") | W11: =IFERROR(AVERAGEIFS($I$5:$I$214,$A$5:$A$214,Q11,$C$5:$C$214,R11),"—") | X11: =IFERROR(AVERAGEIFS($K$5:$K$214,$A$5:$A$214,Q11,$C$5:$C$214,R11),"—") | Y11: 2 | Z11: =IF(T11=0,"NOT LISTED on Bridg",IF(NOT(ISNUMBER(X11)),"No direct quote",IF(ABS(X11)<=Y11,"Match (net of Bridg fee)",IF(ABS(W11)<=Y11,"Match (Bridg fee not applied)",IF(X11<0,"Bridg LOWER than venue","Bridg HIGHER than venue")))))
A12: SOL → ETH | B12: 2 | C12: LI.FI (Jumper) | D12: 98.889246 | F12: 99.087326 | H12: =IF(ISNUMBER(F12),F12-N(G12),"") | I12: =IF(AND(ISNUMBER(D12),ISNUMBER(H12)),(D12-H12)/100*10000,"") | J12: 0.15 | K12: =IF(ISNUMBER(I12),I12+N(J12)/100*10000,"") | L12: 0.002 | M12: Jumper Best Return via Relay; max route 99.99 | N12: 2026-09-23T14:22:28.648Z | O12: 2026-09-23T14:22:28.650Z | Q12: SOL → ETH | R12: Husher | S12: =COUNTIFS($A$5:$A$214,Q12,$C$5:$C$214,R12) | T12: =COUNTIFS($A$5:$A$214,Q12,$C$5:$C$214,R12,$D$5:$D$214,">0") | U12: =IFERROR(AVERAGEIFS($D$5:$D$214,$A$5:$A$214,Q12,$C$5:$C$214,R12),"—") | V12: =IFERROR(AVERAGEIFS($H$5:$H$214,$A$5:$A$214,Q12,$C$5:$C$214,R12),"—") | W12: =IFERROR(AVERAGEIFS($I$5:$I$214,$A$5:$A$214,Q12,$C$5:$C$214,R12),"—") | X12: =IFERROR(AVERAGEIFS($K$5:$K$214,$A$5:$A$214,Q12,$C$5:$C$214,R12),"—") | Y12: 2 | Z12: =IF(T12=0,"NOT LISTED on Bridg",IF(NOT(ISNUMBER(X12)),"No direct quote",IF(ABS(X12)<=Y12,"Match (net of Bridg fee)",IF(ABS(W12)<=Y12,"Match (Bridg fee not applied)",IF(X12<0,"Bridg LOWER than venue","Bridg HIGHER than venue")))))
A13: SOL → ETH | B13: 3 | C13: LI.FI (Jumper) | D13: 98.86696 | F13: 99.260036 | H13: =IF(ISNUMBER(F13),F13-N(G13),"") | I13: =IF(AND(ISNUMBER(D13),ISNUMBER(H13)),(D13-H13)/100*10000,"") | J13: 0.15 | K13: =IF(ISNUMBER(I13),I13+N(J13)/100*10000,"") | L13: 0 | M13: Jumper Best Return via Relay; max route 99.99 | N13: 2026-09-23T14:26:54.591Z | O13: 2026-09-23T14:26:54.591Z | Q13: SOL → ETH | R13: Layerswap | S13: =COUNTIFS($A$5:$A$214,Q13,$C$5:$C$214,R13) | T13: =COUNTIFS($A$5:$A$214,Q13,$C$5:$C$214,R13,$D$5:$D$214,">0") | U13: =IFERROR(AVERAGEIFS($D$5:$D$214,$A$5:$A$214,Q13,$C$5:$C$214,R13),"—") | V13: =IFERROR(AVERAGEIFS($H$5:$H$214,$A$5:$A$214,Q13,$C$5:$C$214,R13),"—") | W13: =IFERROR(AVERAGEIFS($I$5:$I$214,$A$5:$A$214,Q13,$C$5:$C$214,R13),"—") | X13: =IFERROR(AVERAGEIFS($K$5:$K$214,$A$5:$A$214,Q13,$C$5:$C$214,R13),"—") | Y13: 2 | Z13: =IF(T13=0,"NOT LISTED on Bridg",IF(NOT(ISNUMBER(X13)),"No direct quote",IF(ABS(X13)<=Y13,"Match (net of Bridg fee)",IF(ABS(W13)<=Y13,"Match (Bridg fee not applied)",IF(X13<0,"Bridg LOWER than venue","Bridg HIGHER than venue")))))
A14: SOL → ETH | B14: 1 | C14: Across | D14: 99.840015 | F14: 99.99 | H14: =IF(ISNUMBER(F14),F14-N(G14),"") | I14: =IF(AND(ISNUMBER(D14),ISNUMBER(H14)),(D14-H14)/100*10000,"") | J14: 0.15 | K14: =IF(ISNUMBER(I14),I14+N(J14)/100*10000,"") | L14: 0.006 | N14: 2026-09-23T14:18:55.406Z | O14: 2026-09-23T14:18:55.400Z | Q14: SOL → ETH | R14: Meson | S14: =COUNTIFS($A$5:$A$214,Q14,$C$5:$C$214,R14) | T14: =COUNTIFS($A$5:$A$214,Q14,$C$5:$C$214,R14,$D$5:$D$214,">0") | U14: =IFERROR(AVERAGEIFS($D$5:$D$214,$A$5:$A$214,Q14,$C$5:$C$214,R14),"—") | V14: =IFERROR(AVERAGEIFS($H$5:$H$214,$A$5:$A$214,Q14,$C$5:$C$214,R14),"—") | W14: =IFERROR(AVERAGEIFS($I$5:$I$214,$A$5:$A$214,Q14,$C$5:$C$214,R14),"—") | X14: =IFERROR(AVERAGEIFS($K$5:$K$214,$A$5:$A$214,Q14,$C$5:$C$214,R14),"—") | Y14: 2 | Z14: =IF(T14=0,"NOT LISTED on Bridg",IF(NOT(ISNUMBER(X14)),"No direct quote",IF(ABS(X14)<=Y14,"Match (net of Bridg fee)",IF(ABS(W14)<=Y14,"Match (Bridg fee not applied)",IF(X14<0,"Bridg LOWER than venue","Bridg HIGHER than venue")))))
A15: SOL → ETH | B15: 2 | C15: Across | D15: 99.840015 | F15: 99.99 | H15: =IF(ISNUMBER(F15),F15-N(G15),"") | I15: =IF(AND(ISNUMBER(D15),ISNUMBER(H15)),(D15-H15)/100*10000,"") | J15: 0.15 | K15: =IF(ISNUMBER(I15),I15+N(J15)/100*10000,"") | L15: 0.004 | N15: 2026-09-23T14:22:28.648Z | O15: 2026-09-23T14:22:28.644Z | Q15: SOL → ETH | R15: SimpleSwap | S15: =COUNTIFS($A$5:$A$214,Q15,$C$5:$C$214,R15) | T15: =COUNTIFS($A$5:$A$214,Q15,$C$5:$C$214,R15,$D$5:$D$214,">0") | U15: =IFERROR(AVERAGEIFS($D$5:$D$214,$A$5:$A$214,Q15,$C$5:$C$214,R15),"—") | V15: =IFERROR(AVERAGEIFS($H$5:$H$214,$A$5:$A$214,Q15,$C$5:$C$214,R15),"—") | W15: =IFERROR(AVERAGEIFS($I$5:$I$214,$A$5:$A$214,Q15,$C$5:$C$214,R15),"—") | X15: =IFERROR(AVERAGEIFS($K$5:$K$214,$A$5:$A$214,Q15,$C$5:$C$214,R15),"—") | Y15: 2 | Z15: =IF(T15=0,"NOT LISTED on Bridg",IF(NOT(ISNUMBER(X15)),"No direct quote",IF(ABS(X15)<=Y15,"Match (net of Bridg fee)",IF(ABS(W15)<=Y15,"Match (Bridg fee not applied)",IF(X15<0,"Bridg LOWER than venue","Bridg HIGHER than venue")))))
A16: SOL → ETH | B16: 3 | C16: Across | D16: 99.840015 | F16: 99.99 | H16: =IF(ISNUMBER(F16),F16-N(G16),"") | I16: =IF(AND(ISNUMBER(D16),ISNUMBER(H16)),(D16-H16)/100*10000,"") | J16: 0.15 | K16: =IF(ISNUMBER(I16),I16+N(J16)/100*10000,"") | L16: 0.002 | N16: 2026-09-23T14:26:54.591Z | O16: 2026-09-23T14:26:54.589Z | Q16: SOL → ETH | R16: Skip Go | S16: =COUNTIFS($A$5:$A$214,Q16,$C$5:$C$214,R16) | T16: =COUNTIFS($A$5:$A$214,Q16,$C$5:$C$214,R16,$D$5:$D$214,">0") | U16: =IFERROR(AVERAGEIFS($D$5:$D$214,$A$5:$A$214,Q16,$C$5:$C$214,R16),"—") | V16: =IFERROR(AVERAGEIFS($H$5:$H$214,$A$5:$A$214,Q16,$C$5:$C$214,R16),"—") | W16: =IFERROR(AVERAGEIFS($I$5:$I$214,$A$5:$A$214,Q16,$C$5:$C$214,R16),"—") | X16: =IFERROR(AVERAGEIFS($K$5:$K$214,$A$5:$A$214,Q16,$C$5:$C$214,R16),"—") | Y16: 2 | Z16: =IF(T16=0,"NOT LISTED on Bridg",IF(NOT(ISNUMBER(X16)),"No direct quote",IF(ABS(X16)<=Y16,"Match (net of Bridg fee)",IF(ABS(W16)<=Y16,"Match (Bridg fee not applied)",IF(X16<0,"Bridg LOWER than venue","Bridg HIGHER than venue")))))
A17: SOL → ETH | B17: 1 | C17: Mayan | D17: 96.488949 | E17: yes | F17: 96.6446 | H17: =IF(ISNUMBER(F17),F17-N(G17),"") | I17: =IF(AND(ISNUMBER(D17),ISNUMBER(H17)),(D17-H17)/100*10000,"") | J17: 0.15 | K17: =IF(ISNUMBER(I17),I17+N(J17)/100*10000,"") | L17: 0.006 | M17: Swift v2; UI shows 4 dp | N17: 2026-09-23T14:18:55.406Z | O17: 2026-09-23T14:18:55.400Z | Q17: SOL → ETH | R17: Symbiosis | S17: =COUNTIFS($A$5:$A$214,Q17,$C$5:$C$214,R17) | T17: =COUNTIFS($A$5:$A$214,Q17,$C$5:$C$214,R17,$D$5:$D$214,">0") | U17: =IFERROR(AVERAGEIFS($D$5:$D$214,$A$5:$A$214,Q17,$C$5:$C$214,R17),"—") | V17: =IFERROR(AVERAGEIFS($H$5:$H$214,$A$5:$A$214,Q17,$C$5:$C$214,R17),"—") | W17: =IFERROR(AVERAGEIFS($I$5:$I$214,$A$5:$A$214,Q17,$C$5:$C$214,R17),"—") | X17: =IFERROR(AVERAGEIFS($K$5:$K$214,$A$5:$A$214,Q17,$C$5:$C$214,R17),"—") | Y17: 2 | Z17: =IF(T17=0,"NOT LISTED on Bridg",IF(NOT(ISNUMBER(X17)),"No direct quote",IF(ABS(X17)<=Y17,"Match (net of Bridg fee)",IF(ABS(W17)<=Y17,"Match (Bridg fee not applied)",IF(X17<0,"Bridg LOWER than venue","Bridg HIGHER than venue")))))
A18: SOL → ETH | B18: 2 | C18: Mayan | D18: 96.68446 | E18: yes | F18: 96.6844 | H18: =IF(ISNUMBER(F18),F18-N(G18),"") | I18: =IF(AND(ISNUMBER(D18),ISNUMBER(H18)),(D18-H18)/100*10000,"") | J18: 0.15 | K18: =IF(ISNUMBER(I18),I18+N(J18)/100*10000,"") | L18: 0.005 | M18: Swift v2; UI shows 4 dp | N18: 2026-09-23T14:22:28.648Z | O18: 2026-09-23T14:22:28.643Z | Q18: ETH → SOL | R18: Relay | S18: =COUNTIFS($A$5:$A$214,Q18,$C$5:$C$214,R18) | T18: =COUNTIFS($A$5:$A$214,Q18,$C$5:$C$214,R18,$D$5:$D$214,">0") | U18: =IFERROR(AVERAGEIFS($D$5:$D$214,$A$5:$A$214,Q18,$C$5:$C$214,R18),"—") | V18: =IFERROR(AVERAGEIFS($H$5:$H$214,$A$5:$A$214,Q18,$C$5:$C$214,R18),"—") | W18: =IFERROR(AVERAGEIFS($I$5:$I$214,$A$5:$A$214,Q18,$C$5:$C$214,R18),"—") | X18: =IFERROR(AVERAGEIFS($K$5:$K$214,$A$5:$A$214,Q18,$C$5:$C$214,R18),"—") | Y18: 2 | Z18: =IF(T18=0,"NOT LISTED on Bridg",IF(NOT(ISNUMBER(X18)),"No direct quote",IF(ABS(X18)<=Y18,"Match (net of Bridg fee)",IF(ABS(W18)<=Y18,"Match (Bridg fee not applied)",IF(X18<0,"Bridg LOWER than venue","Bridg HIGHER than venue")))))
A19: SOL → ETH | B19: 3 | C19: Mayan | D19: 96.851035 | E19: yes | F19: 96.851 | H19: =IF(ISNUMBER(F19),F19-N(G19),"") | I19: =IF(AND(ISNUMBER(D19),ISNUMBER(H19)),(D19-H19)/100*10000,"") | J19: 0.15 | K19: =IF(ISNUMBER(I19),I19+N(J19)/100*10000,"") | L19: 0.003 | M19: Swift v2; UI shows 3 dp | N19: 2026-09-23T14:26:54.591Z | O19: 2026-09-23T14:26:54.588Z | Q19: ETH → SOL | R19: deBridge | S19: =COUNTIFS($A$5:$A$214,Q19,$C$5:$C$214,R19) | T19: =COUNTIFS($A$5:$A$214,Q19,$C$5:$C$214,R19,$D$5:$D$214,">0") | U19: =IFERROR(AVERAGEIFS($D$5:$D$214,$A$5:$A$214,Q19,$C$5:$C$214,R19),"—") | V19: =IFERROR(AVERAGEIFS($H$5:$H$214,$A$5:$A$214,Q19,$C$5:$C$214,R19),"—") | W19: =IFERROR(AVERAGEIFS($I$5:$I$214,$A$5:$A$214,Q19,$C$5:$C$214,R19),"—") | X19: =IFERROR(AVERAGEIFS($K$5:$K$214,$A$5:$A$214,Q19,$C$5:$C$214,R19),"—") | Y19: 2 | Z19: =IF(T19=0,"NOT LISTED on Bridg",IF(NOT(ISNUMBER(X19)),"No direct quote",IF(ABS(X19)<=Y19,"Match (net of Bridg fee)",IF(ABS(W19)<=Y19,"Match (Bridg fee not applied)",IF(X19<0,"Bridg LOWER than venue","Bridg HIGHER than venue")))))
A20: SOL → ETH | B20: 1 | C20: Allbridge Core | D20: 99.75015 | E20: yes | F20: 99.9 | H20: =IF(ISNUMBER(F20),F20-N(G20),"") | I20: =IF(AND(ISNUMBER(D20),ISNUMBER(H20)),(D20-H20)/100*10000,"") | J20: 0.15 | K20: =IF(ISNUMBER(I20),I20+N(J20)/100*10000,"") | L20: 0.005 | M20: +0.014082 SOL (relayer fee, fee=native) charged on top of 100 input (not converted) | N20: 2026-09-23T14:18:55.406Z | O20: 2026-09-23T14:18:55.401Z | Q20: ETH → SOL | R20: LI.FI (Jumper) | S20: =COUNTIFS($A$5:$A$214,Q20,$C$5:$C$214,R20) | T20: =COUNTIFS($A$5:$A$214,Q20,$C$5:$C$214,R20,$D$5:$D$214,">0") | U20: =IFERROR(AVERAGEIFS($D$5:$D$214,$A$5:$A$214,Q20,$C$5:$C$214,R20),"—") | V20: =IFERROR(AVERAGEIFS($H$5:$H$214,$A$5:$A$214,Q20,$C$5:$C$214,R20),"—") | W20: =IFERROR(AVERAGEIFS($I$5:$I$214,$A$5:$A$214,Q20,$C$5:$C$214,R20),"—") | X20: =IFERROR(AVERAGEIFS($K$5:$K$214,$A$5:$A$214,Q20,$C$5:$C$214,R20),"—") | Y20: 2 | Z20: =IF(T20=0,"NOT LISTED on Bridg",IF(NOT(ISNUMBER(X20)),"No direct quote",IF(ABS(X20)<=Y20,"Match (net of Bridg fee)",IF(ABS(W20)<=Y20,"Match (Bridg fee not applied)",IF(X20<0,"Bridg LOWER than venue","Bridg HIGHER than venue")))))
A21: SOL → ETH | B21: 2 | C21: Allbridge Core | D21: 99.75015 | E21: yes | F21: 99.9 | H21: =IF(ISNUMBER(F21),F21-N(G21),"") | I21: =IF(AND(ISNUMBER(D21),ISNUMBER(H21)),(D21-H21)/100*10000,"") | J21: 0.15 | K21: =IF(ISNUMBER(I21),I21+N(J21)/100*10000,"") | L21: 0.004 | M21: +0.014082 SOL (relayer fee, fee=native) charged on top of 100 input (not converted) | N21: 2026-09-23T14:22:28.648Z | O21: 2026-09-23T14:22:28.644Z | Q21: ETH → SOL | R21: Across | S21: =COUNTIFS($A$5:$A$214,Q21,$C$5:$C$214,R21) | T21: =COUNTIFS($A$5:$A$214,Q21,$C$5:$C$214,R21,$D$5:$D$214,">0") | U21: =IFERROR(AVERAGEIFS($D$5:$D$214,$A$5:$A$214,Q21,$C$5:$C$214,R21),"—") | V21: =IFERROR(AVERAGEIFS($H$5:$H$214,$A$5:$A$214,Q21,$C$5:$C$214,R21),"—") | W21: =IFERROR(AVERAGEIFS($I$5:$I$214,$A$5:$A$214,Q21,$C$5:$C$214,R21),"—") | X21: =IFERROR(AVERAGEIFS($K$5:$K$214,$A$5:$A$214,Q21,$C$5:$C$214,R21),"—") | Y21: 2 | Z21: =IF(T21=0,"NOT LISTED on Bridg",IF(NOT(ISNUMBER(X21)),"No direct quote",IF(ABS(X21)<=Y21,"Match (net of Bridg fee)",IF(ABS(W21)<=Y21,"Match (Bridg fee not applied)",IF(X21<0,"Bridg LOWER than venue","Bridg HIGHER than venue")))))
A22: SOL → ETH | B22: 3 | C22: Allbridge Core | D22: 99.75015 | E22: yes | F22: 99.9 | H22: =IF(ISNUMBER(F22),F22-N(G22),"") | I22: =IF(AND(ISNUMBER(D22),ISNUMBER(H22)),(D22-H22)/100*10000,"") | J22: 0.15 | K22: =IF(ISNUMBER(I22),I22+N(J22)/100*10000,"") | L22: 0.001 | M22: +0.015393 SOL (relayer fee, fee=native) charged on top of 100 input (not converted) | N22: 2026-09-23T14:26:54.591Z | O22: 2026-09-23T14:26:54.590Z | Q22: ETH → SOL | R22: Mayan | S22: =COUNTIFS($A$5:$A$214,Q22,$C$5:$C$214,R22) | T22: =COUNTIFS($A$5:$A$214,Q22,$C$5:$C$214,R22,$D$5:$D$214,">0") | U22: =IFERROR(AVERAGEIFS($D$5:$D$214,$A$5:$A$214,Q22,$C$5:$C$214,R22),"—") | V22: =IFERROR(AVERAGEIFS($H$5:$H$214,$A$5:$A$214,Q22,$C$5:$C$214,R22),"—") | W22: =IFERROR(AVERAGEIFS($I$5:$I$214,$A$5:$A$214,Q22,$C$5:$C$214,R22),"—") | X22: =IFERROR(AVERAGEIFS($K$5:$K$214,$A$5:$A$214,Q22,$C$5:$C$214,R22),"—") | Y22: 4 | Z22: =IF(T22=0,"NOT LISTED on Bridg",IF(NOT(ISNUMBER(X22)),"No direct quote",IF(ABS(X22)<=Y22,"Match (net of Bridg fee)",IF(ABS(W22)<=Y22,"Match (Bridg fee not applied)",IF(X22<0,"Bridg LOWER than venue","Bridg HIGHER than venue")))))
A23: SOL → ETH | B23: 1 | C23: CCTP (via Portal) | D23: 96.584008 | E23: yes | F23: 99.99 | H23: =IF(ISNUMBER(F23),F23-N(G23),"") | I23: =IF(AND(ISNUMBER(D23),ISNUMBER(H23)),(D23-H23)/100*10000,"") | J23: 0.15 | K23: =IF(ISNUMBER(I23),I23+N(J23)/100*10000,"") | L23: 0 | M23: via Portal (CCTPv2StandardExecutorRoute); executor fee hidden until wallet connect | N23: 2026-09-23T14:18:55.406Z | O23: 2026-09-23T14:18:55.406Z | Q23: ETH → SOL | R23: Allbridge Core | S23: =COUNTIFS($A$5:$A$214,Q23,$C$5:$C$214,R23) | T23: =COUNTIFS($A$5:$A$214,Q23,$C$5:$C$214,R23,$D$5:$D$214,">0") | U23: =IFERROR(AVERAGEIFS($D$5:$D$214,$A$5:$A$214,Q23,$C$5:$C$214,R23),"—") | V23: =IFERROR(AVERAGEIFS($H$5:$H$214,$A$5:$A$214,Q23,$C$5:$C$214,R23),"—") | W23: =IFERROR(AVERAGEIFS($I$5:$I$214,$A$5:$A$214,Q23,$C$5:$C$214,R23),"—") | X23: =IFERROR(AVERAGEIFS($K$5:$K$214,$A$5:$A$214,Q23,$C$5:$C$214,R23),"—") | Y23: 2 | Z23: =IF(T23=0,"NOT LISTED on Bridg",IF(NOT(ISNUMBER(X23)),"No direct quote",IF(ABS(X23)<=Y23,"Match (net of Bridg fee)",IF(ABS(W23)<=Y23,"Match (Bridg fee not applied)",IF(X23<0,"Bridg LOWER than venue","Bridg HIGHER than venue")))))
A24: SOL → ETH | B24: 2 | C24: CCTP (via Portal) | D24: 96.584008 | E24: yes | F24: 99.99 | H24: =IF(ISNUMBER(F24),F24-N(G24),"") | I24: =IF(AND(ISNUMBER(D24),ISNUMBER(H24)),(D24-H24)/100*10000,"") | J24: 0.15 | K24: =IF(ISNUMBER(I24),I24+N(J24)/100*10000,"") | L24: 0.001 | M24: via Portal (CCTPv2StandardExecutorRoute); executor fee hidden until wallet connect | N24: 2026-09-23T14:22:28.648Z | O24: 2026-09-23T14:22:28.649Z | Q24: ETH → SOL | R24: CCTP (via Portal) | S24: =COUNTIFS($A$5:$A$214,Q24,$C$5:$C$214,R24) | T24: =COUNTIFS($A$5:$A$214,Q24,$C$5:$C$214,R24,$D$5:$D$214,">0") | U24: =IFERROR(AVERAGEIFS($D$5:$D$214,$A$5:$A$214,Q24,$C$5:$C$214,R24),"—") | V24: =IFERROR(AVERAGEIFS($H$5:$H$214,$A$5:$A$214,Q24,$C$5:$C$214,R24),"—") | W24: =IFERROR(AVERAGEIFS($I$5:$I$214,$A$5:$A$214,Q24,$C$5:$C$214,R24),"—") | X24: =IFERROR(AVERAGEIFS($K$5:$K$214,$A$5:$A$214,Q24,$C$5:$C$214,R24),"—") | Y24: 2 | Z24: =IF(T24=0,"NOT LISTED on Bridg",IF(NOT(ISNUMBER(X24)),"No direct quote",IF(ABS(X24)<=Y24,"Match (net of Bridg fee)",IF(ABS(W24)<=Y24,"Match (Bridg fee not applied)",IF(X24<0,"Bridg LOWER than venue","Bridg HIGHER than venue")))))
A25: SOL → ETH | B25: 3 | C25: CCTP (via Portal) | D25: 96.397468 | E25: yes | F25: 99.99 | H25: =IF(ISNUMBER(F25),F25-N(G25),"") | I25: =IF(AND(ISNUMBER(D25),ISNUMBER(H25)),(D25-H25)/100*10000,"") | J25: 0.15 | K25: =IF(ISNUMBER(I25),I25+N(J25)/100*10000,"") | L25: 0.003 | M25: via Portal (CCTPv2StandardExecutorRoute); executor fee hidden until wallet connect | N25: 2026-09-23T14:26:54.591Z | O25: 2026-09-23T14:26:54.588Z | Q25: ETH → SOL | R25: Husher | S25: =COUNTIFS($A$5:$A$214,Q25,$C$5:$C$214,R25) | T25: =COUNTIFS($A$5:$A$214,Q25,$C$5:$C$214,R25,$D$5:$D$214,">0") | U25: =IFERROR(AVERAGEIFS($D$5:$D$214,$A$5:$A$214,Q25,$C$5:$C$214,R25),"—") | V25: =IFERROR(AVERAGEIFS($H$5:$H$214,$A$5:$A$214,Q25,$C$5:$C$214,R25),"—") | W25: =IFERROR(AVERAGEIFS($I$5:$I$214,$A$5:$A$214,Q25,$C$5:$C$214,R25),"—") | X25: =IFERROR(AVERAGEIFS($K$5:$K$214,$A$5:$A$214,Q25,$C$5:$C$214,R25),"—") | Y25: 2 | Z25: =IF(T25=0,"NOT LISTED on Bridg",IF(NOT(ISNUMBER(X25)),"No direct quote",IF(ABS(X25)<=Y25,"Match (net of Bridg fee)",IF(ABS(W25)<=Y25,"Match (Bridg fee not applied)",IF(X25<0,"Bridg LOWER than venue","Bridg HIGHER than venue")))))
A26: SOL → ETH | B26: 1 | C26: Husher | D26: 99.1504 | F26: 99.05 | H26: =IF(ISNUMBER(F26),F26-N(G26),"") | I26: =IF(AND(ISNUMBER(D26),ISNUMBER(H26)),(D26-H26)/100*10000,"") | J26: 0.15 | K26: =IF(ISNUMBER(I26),I26+N(J26)/100*10000,"") | L26: 0.005 | N26: 2026-09-23T14:18:55.406Z | O26: 2026-09-23T14:18:55.401Z | Q26: ETH → SOL | R26: Layerswap | S26: =COUNTIFS($A$5:$A$214,Q26,$C$5:$C$214,R26) | T26: =COUNTIFS($A$5:$A$214,Q26,$C$5:$C$214,R26,$D$5:$D$214,">0") | U26: =IFERROR(AVERAGEIFS($D$5:$D$214,$A$5:$A$214,Q26,$C$5:$C$214,R26),"—") | V26: =IFERROR(AVERAGEIFS($H$5:$H$214,$A$5:$A$214,Q26,$C$5:$C$214,R26),"—") | W26: =IFERROR(AVERAGEIFS($I$5:$I$214,$A$5:$A$214,Q26,$C$5:$C$214,R26),"—") | X26: =IFERROR(AVERAGEIFS($K$5:$K$214,$A$5:$A$214,Q26,$C$5:$C$214,R26),"—") | Y26: 2 | Z26: =IF(T26=0,"NOT LISTED on Bridg",IF(NOT(ISNUMBER(X26)),"No direct quote",IF(ABS(X26)<=Y26,"Match (net of Bridg fee)",IF(ABS(W26)<=Y26,"Match (Bridg fee not applied)",IF(X26<0,"Bridg LOWER than venue","Bridg HIGHER than venue")))))
A27: SOL → ETH | B27: 2 | C27: Husher | D27: 99.1504 | F27: 99.05 | H27: =IF(ISNUMBER(F27),F27-N(G27),"") | I27: =IF(AND(ISNUMBER(D27),ISNUMBER(H27)),(D27-H27)/100*10000,"") | J27: 0.15 | K27: =IF(ISNUMBER(I27),I27+N(J27)/100*10000,"") | L27: 0.005 | N27: 2026-09-23T14:22:28.648Z | O27: 2026-09-23T14:22:28.643Z | Q27: ETH → SOL | R27: Meson | S27: =COUNTIFS($A$5:$A$214,Q27,$C$5:$C$214,R27) | T27: =COUNTIFS($A$5:$A$214,Q27,$C$5:$C$214,R27,$D$5:$D$214,">0") | U27: =IFERROR(AVERAGEIFS($D$5:$D$214,$A$5:$A$214,Q27,$C$5:$C$214,R27),"—") | V27: =IFERROR(AVERAGEIFS($H$5:$H$214,$A$5:$A$214,Q27,$C$5:$C$214,R27),"—") | W27: =IFERROR(AVERAGEIFS($I$5:$I$214,$A$5:$A$214,Q27,$C$5:$C$214,R27),"—") | X27: =IFERROR(AVERAGEIFS($K$5:$K$214,$A$5:$A$214,Q27,$C$5:$C$214,R27),"—") | Y27: 2 | Z27: =IF(T27=0,"NOT LISTED on Bridg",IF(NOT(ISNUMBER(X27)),"No direct quote",IF(ABS(X27)<=Y27,"Match (net of Bridg fee)",IF(ABS(W27)<=Y27,"Match (Bridg fee not applied)",IF(X27<0,"Bridg LOWER than venue","Bridg HIGHER than venue")))))
A28: SOL → ETH | B28: 3 | C28: Husher | D28: 99.1504 | F28: 99.05 | H28: =IF(ISNUMBER(F28),F28-N(G28),"") | I28: =IF(AND(ISNUMBER(D28),ISNUMBER(H28)),(D28-H28)/100*10000,"") | J28: 0.15 | K28: =IF(ISNUMBER(I28),I28+N(J28)/100*10000,"") | L28: 0.002 | N28: 2026-09-23T14:26:54.591Z | O28: 2026-09-23T14:26:54.589Z | Q28: ETH → SOL | R28: SimpleSwap | S28: =COUNTIFS($A$5:$A$214,Q28,$C$5:$C$214,R28) | T28: =COUNTIFS($A$5:$A$214,Q28,$C$5:$C$214,R28,$D$5:$D$214,">0") | U28: =IFERROR(AVERAGEIFS($D$5:$D$214,$A$5:$A$214,Q28,$C$5:$C$214,R28),"—") | V28: =IFERROR(AVERAGEIFS($H$5:$H$214,$A$5:$A$214,Q28,$C$5:$C$214,R28),"—") | W28: =IFERROR(AVERAGEIFS($I$5:$I$214,$A$5:$A$214,Q28,$C$5:$C$214,R28),"—") | X28: =IFERROR(AVERAGEIFS($K$5:$K$214,$A$5:$A$214,Q28,$C$5:$C$214,R28),"—") | Y28: 2 | Z28: =IF(T28=0,"NOT LISTED on Bridg",IF(NOT(ISNUMBER(X28)),"No direct quote",IF(ABS(X28)<=Y28,"Match (net of Bridg fee)",IF(ABS(W28)<=Y28,"Match (Bridg fee not applied)",IF(X28<0,"Bridg LOWER than venue","Bridg HIGHER than venue")))))
A29: SOL → ETH | B29: 1 | C29: Layerswap | D29: 99.433011 | F29: 99.716863 | H29: =IF(ISNUMBER(F29),F29-N(G29),"") | I29: =IF(AND(ISNUMBER(D29),ISNUMBER(H29)),(D29-H29)/100*10000,"") | J29: 0.15 | K29: =IF(ISNUMBER(I29),I29+N(J29)/100*10000,"") | L29: 0.004 | N29: 2026-09-23T14:18:55.406Z | O29: 2026-09-23T14:18:55.402Z | Q29: ETH → SOL | R29: Skip Go | S29: =COUNTIFS($A$5:$A$214,Q29,$C$5:$C$214,R29) | T29: =COUNTIFS($A$5:$A$214,Q29,$C$5:$C$214,R29,$D$5:$D$214,">0") | U29: =IFERROR(AVERAGEIFS($D$5:$D$214,$A$5:$A$214,Q29,$C$5:$C$214,R29),"—") | V29: =IFERROR(AVERAGEIFS($H$5:$H$214,$A$5:$A$214,Q29,$C$5:$C$214,R29),"—") | W29: =IFERROR(AVERAGEIFS($I$5:$I$214,$A$5:$A$214,Q29,$C$5:$C$214,R29),"—") | X29: =IFERROR(AVERAGEIFS($K$5:$K$214,$A$5:$A$214,Q29,$C$5:$C$214,R29),"—") | Y29: 2 | Z29: =IF(T29=0,"NOT LISTED on Bridg",IF(NOT(ISNUMBER(X29)),"No direct quote",IF(ABS(X29)<=Y29,"Match (net of Bridg fee)",IF(ABS(W29)<=Y29,"Match (Bridg fee not applied)",IF(X29<0,"Bridg LOWER than venue","Bridg HIGHER than venue")))))
A30: SOL → ETH | B30: 2 | C30: Layerswap | D30: 99.4339 | F30: 99.717755 | H30: =IF(ISNUMBER(F30),F30-N(G30),"") | I30: =IF(AND(ISNUMBER(D30),ISNUMBER(H30)),(D30-H30)/100*10000,"") | J30: 0.15 | K30: =IF(ISNUMBER(I30),I30+N(J30)/100*10000,"") | L30: 0.002 | N30: 2026-09-23T14:22:28.648Z | O30: 2026-09-23T14:22:28.646Z | Q30: ETH → SOL | R30: Symbiosis | S30: =COUNTIFS($A$5:$A$214,Q30,$C$5:$C$214,R30) | T30: =COUNTIFS($A$5:$A$214,Q30,$C$5:$C$214,R30,$D$5:$D$214,">0") | U30: =IFERROR(AVERAGEIFS($D$5:$D$214,$A$5:$A$214,Q30,$C$5:$C$214,R30),"—") | V30: =IFERROR(AVERAGEIFS($H$5:$H$214,$A$5:$A$214,Q30,$C$5:$C$214,R30),"—") | W30: =IFERROR(AVERAGEIFS($I$5:$I$214,$A$5:$A$214,Q30,$C$5:$C$214,R30),"—") | X30: =IFERROR(AVERAGEIFS($K$5:$K$214,$A$5:$A$214,Q30,$C$5:$C$214,R30),"—") | Y30: 2 | Z30: =IF(T30=0,"NOT LISTED on Bridg",IF(NOT(ISNUMBER(X30)),"No direct quote",IF(ABS(X30)<=Y30,"Match (net of Bridg fee)",IF(ABS(W30)<=Y30,"Match (Bridg fee not applied)",IF(X30<0,"Bridg LOWER than venue","Bridg HIGHER than venue")))))
A31: SOL → ETH | B31: 3 | C31: Layerswap | D31: 99.42273 | F31: 99.706546 | H31: =IF(ISNUMBER(F31),F31-N(G31),"") | I31: =IF(AND(ISNUMBER(D31),ISNUMBER(H31)),(D31-H31)/100*10000,"") | J31: 0.15 | K31: =IF(ISNUMBER(I31),I31+N(J31)/100*10000,"") | L31: 0.001 | N31: 2026-09-23T14:26:54.591Z | O31: 2026-09-23T14:26:54.592Z | Q31: SOL → BSC | R31: Relay | S31: =COUNTIFS($A$5:$A$214,Q31,$C$5:$C$214,R31) | T31: =COUNTIFS($A$5:$A$214,Q31,$C$5:$C$214,R31,$D$5:$D$214,">0") | U31: =IFERROR(AVERAGEIFS($D$5:$D$214,$A$5:$A$214,Q31,$C$5:$C$214,R31),"—") | V31: =IFERROR(AVERAGEIFS($H$5:$H$214,$A$5:$A$214,Q31,$C$5:$C$214,R31),"—") | W31: =IFERROR(AVERAGEIFS($I$5:$I$214,$A$5:$A$214,Q31,$C$5:$C$214,R31),"—") | X31: =IFERROR(AVERAGEIFS($K$5:$K$214,$A$5:$A$214,Q31,$C$5:$C$214,R31),"—") | Y31: 2 | Z31: =IF(T31=0,"NOT LISTED on Bridg",IF(NOT(ISNUMBER(X31)),"No direct quote",IF(ABS(X31)<=Y31,"Match (net of Bridg fee)",IF(ABS(W31)<=Y31,"Match (Bridg fee not applied)",IF(X31<0,"Bridg LOWER than venue","Bridg HIGHER than venue")))))
A32: SOL → ETH | B32: 1 | C32: Meson | D32: 99.75015 | E32: yes | F32: 98.65 | H32: =IF(ISNUMBER(F32),F32-N(G32),"") | I32: =IF(AND(ISNUMBER(D32),ISNUMBER(H32)),(D32-H32)/100*10000,"") | J32: 0.15 | K32: =IF(ISNUMBER(I32),I32+N(J32)/100*10000,"") | L32: 0.006 | N32: 2026-09-23T14:18:55.406Z | O32: 2026-09-23T14:18:55.400Z | Q32: SOL → BSC | R32: deBridge | S32: =COUNTIFS($A$5:$A$214,Q32,$C$5:$C$214,R32) | T32: =COUNTIFS($A$5:$A$214,Q32,$C$5:$C$214,R32,$D$5:$D$214,">0") | U32: =IFERROR(AVERAGEIFS($D$5:$D$214,$A$5:$A$214,Q32,$C$5:$C$214,R32),"—") | V32: =IFERROR(AVERAGEIFS($H$5:$H$214,$A$5:$A$214,Q32,$C$5:$C$214,R32),"—") | W32: =IFERROR(AVERAGEIFS($I$5:$I$214,$A$5:$A$214,Q32,$C$5:$C$214,R32),"—") | X32: =IFERROR(AVERAGEIFS($K$5:$K$214,$A$5:$A$214,Q32,$C$5:$C$214,R32),"—") | Y32: 2 | Z32: =IF(T32=0,"NOT LISTED on Bridg",IF(NOT(ISNUMBER(X32)),"No direct quote",IF(ABS(X32)<=Y32,"Match (net of Bridg fee)",IF(ABS(W32)<=Y32,"Match (Bridg fee not applied)",IF(X32<0,"Bridg LOWER than venue","Bridg HIGHER than venue")))))
A33: SOL → ETH | B33: 2 | C33: Meson | D33: 99.75015 | E33: yes | F33: 98.37 | H33: =IF(ISNUMBER(F33),F33-N(G33),"") | I33: =IF(AND(ISNUMBER(D33),ISNUMBER(H33)),(D33-H33)/100*10000,"") | J33: 0.15 | K33: =IF(ISNUMBER(I33),I33+N(J33)/100*10000,"") | L33: 0.006 | N33: 2026-09-23T14:22:28.648Z | O33: 2026-09-23T14:22:28.642Z | Q33: SOL → BSC | R33: LI.FI (Jumper) | S33: =COUNTIFS($A$5:$A$214,Q33,$C$5:$C$214,R33) | T33: =COUNTIFS($A$5:$A$214,Q33,$C$5:$C$214,R33,$D$5:$D$214,">0") | U33: =IFERROR(AVERAGEIFS($D$5:$D$214,$A$5:$A$214,Q33,$C$5:$C$214,R33),"—") | V33: =IFERROR(AVERAGEIFS($H$5:$H$214,$A$5:$A$214,Q33,$C$5:$C$214,R33),"—") | W33: =IFERROR(AVERAGEIFS($I$5:$I$214,$A$5:$A$214,Q33,$C$5:$C$214,R33),"—") | X33: =IFERROR(AVERAGEIFS($K$5:$K$214,$A$5:$A$214,Q33,$C$5:$C$214,R33),"—") | Y33: 2 | Z33: =IF(T33=0,"NOT LISTED on Bridg",IF(NOT(ISNUMBER(X33)),"No direct quote",IF(ABS(X33)<=Y33,"Match (net of Bridg fee)",IF(ABS(W33)<=Y33,"Match (Bridg fee not applied)",IF(X33<0,"Bridg LOWER than venue","Bridg HIGHER than venue")))))
A34: SOL → ETH | B34: 3 | C34: Meson | D34: 99.75015 | E34: yes | F34: 98.67 | H34: =IF(ISNUMBER(F34),F34-N(G34),"") | I34: =IF(AND(ISNUMBER(D34),ISNUMBER(H34)),(D34-H34)/100*10000,"") | J34: 0.15 | K34: =IF(ISNUMBER(I34),I34+N(J34)/100*10000,"") | L34: 0.003 | N34: 2026-09-23T14:26:54.591Z | O34: 2026-09-23T14:26:54.588Z | Q34: SOL → BSC | R34: Across | S34: =COUNTIFS($A$5:$A$214,Q34,$C$5:$C$214,R34) | T34: =COUNTIFS($A$5:$A$214,Q34,$C$5:$C$214,R34,$D$5:$D$214,">0") | U34: =IFERROR(AVERAGEIFS($D$5:$D$214,$A$5:$A$214,Q34,$C$5:$C$214,R34),"—") | V34: =IFERROR(AVERAGEIFS($H$5:$H$214,$A$5:$A$214,Q34,$C$5:$C$214,R34),"—") | W34: =IFERROR(AVERAGEIFS($I$5:$I$214,$A$5:$A$214,Q34,$C$5:$C$214,R34),"—") | X34: =IFERROR(AVERAGEIFS($K$5:$K$214,$A$5:$A$214,Q34,$C$5:$C$214,R34),"—") | Y34: 2 | Z34: =IF(T34=0,"NOT LISTED on Bridg",IF(NOT(ISNUMBER(X34)),"No direct quote",IF(ABS(X34)<=Y34,"Match (net of Bridg fee)",IF(ABS(W34)<=Y34,"Match (Bridg fee not applied)",IF(X34<0,"Bridg LOWER than venue","Bridg HIGHER than venue")))))
A35: SOL → ETH | B35: 1 | C35: SimpleSwap | D35: 96.775023 | F35: 98.206302 | H35: =IF(ISNUMBER(F35),F35-N(G35),"") | I35: =IF(AND(ISNUMBER(D35),ISNUMBER(H35)),(D35-H35)/100*10000,"") | J35: 0.15 | K35: =IF(ISNUMBER(I35),I35+N(J35)/100*10000,"") | L35: 0.001 | M35: selected card: Best rate / Decentralized; best card 98.206302 | N35: 2026-09-23T14:18:55.406Z | O35: 2026-09-23T14:18:55.405Z | Q35: SOL → BSC | R35: Mayan | S35: =COUNTIFS($A$5:$A$214,Q35,$C$5:$C$214,R35) | T35: =COUNTIFS($A$5:$A$214,Q35,$C$5:$C$214,R35,$D$5:$D$214,">0") | U35: =IFERROR(AVERAGEIFS($D$5:$D$214,$A$5:$A$214,Q35,$C$5:$C$214,R35),"—") | V35: =IFERROR(AVERAGEIFS($H$5:$H$214,$A$5:$A$214,Q35,$C$5:$C$214,R35),"—") | W35: =IFERROR(AVERAGEIFS($I$5:$I$214,$A$5:$A$214,Q35,$C$5:$C$214,R35),"—") | X35: =IFERROR(AVERAGEIFS($K$5:$K$214,$A$5:$A$214,Q35,$C$5:$C$214,R35),"—") | Y35: 4 | Z35: =IF(T35=0,"NOT LISTED on Bridg",IF(NOT(ISNUMBER(X35)),"No direct quote",IF(ABS(X35)<=Y35,"Match (net of Bridg fee)",IF(ABS(W35)<=Y35,"Match (Bridg fee not applied)",IF(X35<0,"Bridg LOWER than venue","Bridg HIGHER than venue")))))
A36: SOL → ETH | B36: 2 | C36: SimpleSwap | D36: 96.801717 | F36: 98.205703 | H36: =IF(ISNUMBER(F36),F36-N(G36),"") | I36: =IF(AND(ISNUMBER(D36),ISNUMBER(H36)),(D36-H36)/100*10000,"") | J36: 0.15 | K36: =IF(ISNUMBER(I36),I36+N(J36)/100*10000,"") | L36: 0.002 | M36: selected card: Best rate / Decentralized; best card 98.205703 | N36: 2026-09-23T14:22:28.648Z | O36: 2026-09-23T14:22:28.646Z | Q36: SOL → BSC | R36: Husher | S36: =COUNTIFS($A$5:$A$214,Q36,$C$5:$C$214,R36) | T36: =COUNTIFS($A$5:$A$214,Q36,$C$5:$C$214,R36,$D$5:$D$214,">0") | U36: =IFERROR(AVERAGEIFS($D$5:$D$214,$A$5:$A$214,Q36,$C$5:$C$214,R36),"—") | V36: =IFERROR(AVERAGEIFS($H$5:$H$214,$A$5:$A$214,Q36,$C$5:$C$214,R36),"—") | W36: =IFERROR(AVERAGEIFS($I$5:$I$214,$A$5:$A$214,Q36,$C$5:$C$214,R36),"—") | X36: =IFERROR(AVERAGEIFS($K$5:$K$214,$A$5:$A$214,Q36,$C$5:$C$214,R36),"—") | Y36: 2 | Z36: =IF(T36=0,"NOT LISTED on Bridg",IF(NOT(ISNUMBER(X36)),"No direct quote",IF(ABS(X36)<=Y36,"Match (net of Bridg fee)",IF(ABS(W36)<=Y36,"Match (Bridg fee not applied)",IF(X36<0,"Bridg LOWER than venue","Bridg HIGHER than venue")))))
A37: SOL → ETH | B37: 3 | C37: SimpleSwap | D37: 96.790074 | F37: 98.205814 | H37: =IF(ISNUMBER(F37),F37-N(G37),"") | I37: =IF(AND(ISNUMBER(D37),ISNUMBER(H37)),(D37-H37)/100*10000,"") | J37: 0.15 | K37: =IF(ISNUMBER(I37),I37+N(J37)/100*10000,"") | L37: 0.003 | M37: selected card: Best rate / Decentralized; best card 98.205814 | N37: 2026-09-23T14:26:54.591Z | O37: 2026-09-23T14:26:54.594Z | Q37: SOL → BSC | R37: Layerswap | S37: =COUNTIFS($A$5:$A$214,Q37,$C$5:$C$214,R37) | T37: =COUNTIFS($A$5:$A$214,Q37,$C$5:$C$214,R37,$D$5:$D$214,">0") | U37: =IFERROR(AVERAGEIFS($D$5:$D$214,$A$5:$A$214,Q37,$C$5:$C$214,R37),"—") | V37: =IFERROR(AVERAGEIFS($H$5:$H$214,$A$5:$A$214,Q37,$C$5:$C$214,R37),"—") | W37: =IFERROR(AVERAGEIFS($I$5:$I$214,$A$5:$A$214,Q37,$C$5:$C$214,R37),"—") | X37: =IFERROR(AVERAGEIFS($K$5:$K$214,$A$5:$A$214,Q37,$C$5:$C$214,R37),"—") | Y37: 2 | Z37: =IF(T37=0,"NOT LISTED on Bridg",IF(NOT(ISNUMBER(X37)),"No direct quote",IF(ABS(X37)<=Y37,"Match (net of Bridg fee)",IF(ABS(W37)<=Y37,"Match (Bridg fee not applied)",IF(X37<0,"Bridg LOWER than venue","Bridg HIGHER than venue")))))
A38: SOL → ETH | B38: 1 | C38: Skip Go | D38: 96.961212 | F38: 96.94911 | H38: =IF(ISNUMBER(F38),F38-N(G38),"") | I38: =IF(AND(ISNUMBER(D38),ISNUMBER(H38)),(D38-H38)/100*10000,"") | J38: 0.15 | K38: =IF(ISNUMBER(I38),I38+N(J38)/100*10000,"") | L38: 0 | N38: 2026-09-23T14:18:55.406Z | O38: 2026-09-23T14:18:55.406Z | Q38: SOL → BSC | R38: Meson | S38: =COUNTIFS($A$5:$A$214,Q38,$C$5:$C$214,R38) | T38: =COUNTIFS($A$5:$A$214,Q38,$C$5:$C$214,R38,$D$5:$D$214,">0") | U38: =IFERROR(AVERAGEIFS($D$5:$D$214,$A$5:$A$214,Q38,$C$5:$C$214,R38),"—") | V38: =IFERROR(AVERAGEIFS($H$5:$H$214,$A$5:$A$214,Q38,$C$5:$C$214,R38),"—") | W38: =IFERROR(AVERAGEIFS($I$5:$I$214,$A$5:$A$214,Q38,$C$5:$C$214,R38),"—") | X38: =IFERROR(AVERAGEIFS($K$5:$K$214,$A$5:$A$214,Q38,$C$5:$C$214,R38),"—") | Y38: 2 | Z38: =IF(T38=0,"NOT LISTED on Bridg",IF(NOT(ISNUMBER(X38)),"No direct quote",IF(ABS(X38)<=Y38,"Match (net of Bridg fee)",IF(ABS(W38)<=Y38,"Match (Bridg fee not applied)",IF(X38<0,"Bridg LOWER than venue","Bridg HIGHER than venue")))))
A39: SOL → ETH | B39: 2 | C39: Skip Go | D39: 96.961212 | F39: 96.94911 | H39: =IF(ISNUMBER(F39),F39-N(G39),"") | I39: =IF(AND(ISNUMBER(D39),ISNUMBER(H39)),(D39-H39)/100*10000,"") | J39: 0.15 | K39: =IF(ISNUMBER(I39),I39+N(J39)/100*10000,"") | L39: 0 | N39: 2026-09-23T14:22:28.648Z | O39: 2026-09-23T14:22:28.648Z | Q39: SOL → BSC | R39: SimpleSwap | S39: =COUNTIFS($A$5:$A$214,Q39,$C$5:$C$214,R39) | T39: =COUNTIFS($A$5:$A$214,Q39,$C$5:$C$214,R39,$D$5:$D$214,">0") | U39: =IFERROR(AVERAGEIFS($D$5:$D$214,$A$5:$A$214,Q39,$C$5:$C$214,R39),"—") | V39: =IFERROR(AVERAGEIFS($H$5:$H$214,$A$5:$A$214,Q39,$C$5:$C$214,R39),"—") | W39: =IFERROR(AVERAGEIFS($I$5:$I$214,$A$5:$A$214,Q39,$C$5:$C$214,R39),"—") | X39: =IFERROR(AVERAGEIFS($K$5:$K$214,$A$5:$A$214,Q39,$C$5:$C$214,R39),"—") | Y39: 2 | Z39: =IF(T39=0,"NOT LISTED on Bridg",IF(NOT(ISNUMBER(X39)),"No direct quote",IF(ABS(X39)<=Y39,"Match (net of Bridg fee)",IF(ABS(W39)<=Y39,"Match (Bridg fee not applied)",IF(X39<0,"Bridg LOWER than venue","Bridg HIGHER than venue")))))
A40: SOL → ETH | B40: 3 | C40: Skip Go | D40: 96.711186 | F40: 97.44691 | H40: =IF(ISNUMBER(F40),F40-N(G40),"") | I40: =IF(AND(ISNUMBER(D40),ISNUMBER(H40)),(D40-H40)/100*10000,"") | J40: 0.15 | K40: =IF(ISNUMBER(I40),I40+N(J40)/100*10000,"") | L40: 0.001 | N40: 2026-09-23T14:26:54.591Z | O40: 2026-09-23T14:26:54.592Z | Q40: BSC → SOL | R40: Relay | S40: =COUNTIFS($A$5:$A$214,Q40,$C$5:$C$214,R40) | T40: =COUNTIFS($A$5:$A$214,Q40,$C$5:$C$214,R40,$D$5:$D$214,">0") | U40: =IFERROR(AVERAGEIFS($D$5:$D$214,$A$5:$A$214,Q40,$C$5:$C$214,R40),"—") | V40: =IFERROR(AVERAGEIFS($H$5:$H$214,$A$5:$A$214,Q40,$C$5:$C$214,R40),"—") | W40: =IFERROR(AVERAGEIFS($I$5:$I$214,$A$5:$A$214,Q40,$C$5:$C$214,R40),"—") | X40: =IFERROR(AVERAGEIFS($K$5:$K$214,$A$5:$A$214,Q40,$C$5:$C$214,R40),"—") | Y40: 2 | Z40: =IF(T40=0,"NOT LISTED on Bridg",IF(NOT(ISNUMBER(X40)),"No direct quote",IF(ABS(X40)<=Y40,"Match (net of Bridg fee)",IF(ABS(W40)<=Y40,"Match (Bridg fee not applied)",IF(X40<0,"Bridg LOWER than venue","Bridg HIGHER than venue")))))
A41: SOL → ETH | B41: 1 | C41: Symbiosis | D41: 96.165275 | F41: 96.860997 | H41: =IF(ISNUMBER(F41),F41-N(G41),"") | I41: =IF(AND(ISNUMBER(D41),ISNUMBER(H41)),(D41-H41)/100*10000,"") | J41: 0.15 | K41: =IF(ISNUMBER(I41),I41+N(J41)/100*10000,"") | L41: 0.002 | N41: 2026-09-23T14:18:55.406Z | O41: 2026-09-23T14:18:55.404Z | Q41: BSC → SOL | R41: deBridge | S41: =COUNTIFS($A$5:$A$214,Q41,$C$5:$C$214,R41) | T41: =COUNTIFS($A$5:$A$214,Q41,$C$5:$C$214,R41,$D$5:$D$214,">0") | U41: =IFERROR(AVERAGEIFS($D$5:$D$214,$A$5:$A$214,Q41,$C$5:$C$214,R41),"—") | V41: =IFERROR(AVERAGEIFS($H$5:$H$214,$A$5:$A$214,Q41,$C$5:$C$214,R41),"—") | W41: =IFERROR(AVERAGEIFS($I$5:$I$214,$A$5:$A$214,Q41,$C$5:$C$214,R41),"—") | X41: =IFERROR(AVERAGEIFS($K$5:$K$214,$A$5:$A$214,Q41,$C$5:$C$214,R41),"—") | Y41: 2 | Z41: =IF(T41=0,"NOT LISTED on Bridg",IF(NOT(ISNUMBER(X41)),"No direct quote",IF(ABS(X41)<=Y41,"Match (net of Bridg fee)",IF(ABS(W41)<=Y41,"Match (Bridg fee not applied)",IF(X41<0,"Bridg LOWER than venue","Bridg HIGHER than venue")))))
A42: SOL → ETH | B42: 2 | C42: Symbiosis | D42: 96.67081 | F42: 96.3787 | H42: =IF(ISNUMBER(F42),F42-N(G42),"") | I42: =IF(AND(ISNUMBER(D42),ISNUMBER(H42)),(D42-H42)/100*10000,"") | J42: 0.15 | K42: =IF(ISNUMBER(I42),I42+N(J42)/100*10000,"") | L42: 0.001 | N42: 2026-09-23T14:22:28.648Z | O42: 2026-09-23T14:22:28.649Z | Q42: BSC → SOL | R42: LI.FI (Jumper) | S42: =COUNTIFS($A$5:$A$214,Q42,$C$5:$C$214,R42) | T42: =COUNTIFS($A$5:$A$214,Q42,$C$5:$C$214,R42,$D$5:$D$214,">0") | U42: =IFERROR(AVERAGEIFS($D$5:$D$214,$A$5:$A$214,Q42,$C$5:$C$214,R42),"—") | V42: =IFERROR(AVERAGEIFS($H$5:$H$214,$A$5:$A$214,Q42,$C$5:$C$214,R42),"—") | W42: =IFERROR(AVERAGEIFS($I$5:$I$214,$A$5:$A$214,Q42,$C$5:$C$214,R42),"—") | X42: =IFERROR(AVERAGEIFS($K$5:$K$214,$A$5:$A$214,Q42,$C$5:$C$214,R42),"—") | Y42: 2 | Z42: =IF(T42=0,"NOT LISTED on Bridg",IF(NOT(ISNUMBER(X42)),"No direct quote",IF(ABS(X42)<=Y42,"Match (net of Bridg fee)",IF(ABS(W42)<=Y42,"Match (Bridg fee not applied)",IF(X42<0,"Bridg LOWER than venue","Bridg HIGHER than venue")))))
A43: SOL → ETH | B43: 3 | C43: Symbiosis | D43: 96.510498 | F43: 96.510498 | H43: =IF(ISNUMBER(F43),F43-N(G43),"") | I43: =IF(AND(ISNUMBER(D43),ISNUMBER(H43)),(D43-H43)/100*10000,"") | J43: 0.15 | K43: =IF(ISNUMBER(I43),I43+N(J43)/100*10000,"") | L43: 0 | N43: 2026-09-23T14:26:54.591Z | O43: 2026-09-23T14:26:54.591Z | Q43: BSC → SOL | R43: Across | S43: =COUNTIFS($A$5:$A$214,Q43,$C$5:$C$214,R43) | T43: =COUNTIFS($A$5:$A$214,Q43,$C$5:$C$214,R43,$D$5:$D$214,">0") | U43: =IFERROR(AVERAGEIFS($D$5:$D$214,$A$5:$A$214,Q43,$C$5:$C$214,R43),"—") | V43: =IFERROR(AVERAGEIFS($H$5:$H$214,$A$5:$A$214,Q43,$C$5:$C$214,R43),"—") | W43: =IFERROR(AVERAGEIFS($I$5:$I$214,$A$5:$A$214,Q43,$C$5:$C$214,R43),"—") | X43: =IFERROR(AVERAGEIFS($K$5:$K$214,$A$5:$A$214,Q43,$C$5:$C$214,R43),"—") | Y43: 2 | Z43: =IF(T43=0,"NOT LISTED on Bridg",IF(NOT(ISNUMBER(X43)),"No direct quote",IF(ABS(X43)<=Y43,"Match (net of Bridg fee)",IF(ABS(W43)<=Y43,"Match (Bridg fee not applied)",IF(X43<0,"Bridg LOWER than venue","Bridg HIGHER than venue")))))
A44: ETH → SOL | B44: 1 | C44: Relay | D44: 99.696013 | F44: 99.945703 | H44: =IF(ISNUMBER(F44),F44-N(G44),"") | I44: =IF(AND(ISNUMBER(D44),ISNUMBER(H44)),(D44-H44)/100*10000,"") | J44: 0.05 | K44: =IF(ISNUMBER(I44),I44+N(J44)/100*10000,"") | L44: 0.001 | N44: 2026-09-23T14:19:28.697Z | O44: 2026-09-23T14:19:28.698Z | Q44: BSC → SOL | R44: Mayan | S44: =COUNTIFS($A$5:$A$214,Q44,$C$5:$C$214,R44) | T44: =COUNTIFS($A$5:$A$214,Q44,$C$5:$C$214,R44,$D$5:$D$214,">0") | U44: =IFERROR(AVERAGEIFS($D$5:$D$214,$A$5:$A$214,Q44,$C$5:$C$214,R44),"—") | V44: =IFERROR(AVERAGEIFS($H$5:$H$214,$A$5:$A$214,Q44,$C$5:$C$214,R44),"—") | W44: =IFERROR(AVERAGEIFS($I$5:$I$214,$A$5:$A$214,Q44,$C$5:$C$214,R44),"—") | X44: =IFERROR(AVERAGEIFS($K$5:$K$214,$A$5:$A$214,Q44,$C$5:$C$214,R44),"—") | Y44: 4 | Z44: =IF(T44=0,"NOT LISTED on Bridg",IF(NOT(ISNUMBER(X44)),"No direct quote",IF(ABS(X44)<=Y44,"Match (net of Bridg fee)",IF(ABS(W44)<=Y44,"Match (Bridg fee not applied)",IF(X44<0,"Bridg LOWER than venue","Bridg HIGHER than venue")))))
A45: ETH → SOL | B45: 2 | C45: Relay | D45: 99.696651 | F45: 99.945717 | H45: =IF(ISNUMBER(F45),F45-N(G45),"") | I45: =IF(AND(ISNUMBER(D45),ISNUMBER(H45)),(D45-H45)/100*10000,"") | J45: 0.05 | K45: =IF(ISNUMBER(I45),I45+N(J45)/100*10000,"") | L45: 0.003 | N45: 2026-09-23T14:23:47.144Z | O45: 2026-09-23T14:23:47.141Z | Q45: BSC → SOL | R45: Husher | S45: =COUNTIFS($A$5:$A$214,Q45,$C$5:$C$214,R45) | T45: =COUNTIFS($A$5:$A$214,Q45,$C$5:$C$214,R45,$D$5:$D$214,">0") | U45: =IFERROR(AVERAGEIFS($D$5:$D$214,$A$5:$A$214,Q45,$C$5:$C$214,R45),"—") | V45: =IFERROR(AVERAGEIFS($H$5:$H$214,$A$5:$A$214,Q45,$C$5:$C$214,R45),"—") | W45: =IFERROR(AVERAGEIFS($I$5:$I$214,$A$5:$A$214,Q45,$C$5:$C$214,R45),"—") | X45: =IFERROR(AVERAGEIFS($K$5:$K$214,$A$5:$A$214,Q45,$C$5:$C$214,R45),"—") | Y45: 2 | Z45: =IF(T45=0,"NOT LISTED on Bridg",IF(NOT(ISNUMBER(X45)),"No direct quote",IF(ABS(X45)<=Y45,"Match (net of Bridg fee)",IF(ABS(W45)<=Y45,"Match (Bridg fee not applied)",IF(X45<0,"Bridg LOWER than venue","Bridg HIGHER than venue")))))
A46: ETH → SOL | B46: 3 | C46: Relay | D46: 99.696812 | F46: 99.945713 | H46: =IF(ISNUMBER(F46),F46-N(G46),"") | I46: =IF(AND(ISNUMBER(D46),ISNUMBER(H46)),(D46-H46)/100*10000,"") | J46: 0.05 | K46: =IF(ISNUMBER(I46),I46+N(J46)/100*10000,"") | L46: 0.001 | N46: 2026-09-23T14:27:28.356Z | O46: 2026-09-23T14:27:28.355Z | Q46: BSC → SOL | R46: Layerswap | S46: =COUNTIFS($A$5:$A$214,Q46,$C$5:$C$214,R46) | T46: =COUNTIFS($A$5:$A$214,Q46,$C$5:$C$214,R46,$D$5:$D$214,">0") | U46: =IFERROR(AVERAGEIFS($D$5:$D$214,$A$5:$A$214,Q46,$C$5:$C$214,R46),"—") | V46: =IFERROR(AVERAGEIFS($H$5:$H$214,$A$5:$A$214,Q46,$C$5:$C$214,R46),"—") | W46: =IFERROR(AVERAGEIFS($I$5:$I$214,$A$5:$A$214,Q46,$C$5:$C$214,R46),"—") | X46: =IFERROR(AVERAGEIFS($K$5:$K$214,$A$5:$A$214,Q46,$C$5:$C$214,R46),"—") | Y46: 2 | Z46: =IF(T46=0,"NOT LISTED on Bridg",IF(NOT(ISNUMBER(X46)),"No direct quote",IF(ABS(X46)<=Y46,"Match (net of Bridg fee)",IF(ABS(W46)<=Y46,"Match (Bridg fee not applied)",IF(X46<0,"Bridg LOWER than venue","Bridg HIGHER than venue")))))
A47: ETH → SOL | B47: 1 | C47: deBridge | D47: 97.956546 | F47: 99.920018 | G47: 1.965 | H47: =IF(ISNUMBER(F47),F47-N(G47),"") | I47: =IF(AND(ISNUMBER(D47),ISNUMBER(H47)),(D47-H47)/100*10000,"") | J47: 0.05 | K47: =IF(ISNUMBER(I47),I47+N(J47)/100*10000,"") | L47: 0.001 | M47: +1.965 USDC charged on top of 100 input (subtracted) | N47: 2026-09-23T14:19:28.697Z | O47: 2026-09-23T14:19:28.698Z | Q47: BSC → SOL | R47: Meson | S47: =COUNTIFS($A$5:$A$214,Q47,$C$5:$C$214,R47) | T47: =COUNTIFS($A$5:$A$214,Q47,$C$5:$C$214,R47,$D$5:$D$214,">0") | U47: =IFERROR(AVERAGEIFS($D$5:$D$214,$A$5:$A$214,Q47,$C$5:$C$214,R47),"—") | V47: =IFERROR(AVERAGEIFS($H$5:$H$214,$A$5:$A$214,Q47,$C$5:$C$214,R47),"—") | W47: =IFERROR(AVERAGEIFS($I$5:$I$214,$A$5:$A$214,Q47,$C$5:$C$214,R47),"—") | X47: =IFERROR(AVERAGEIFS($K$5:$K$214,$A$5:$A$214,Q47,$C$5:$C$214,R47),"—") | Y47: 2 | Z47: =IF(T47=0,"NOT LISTED on Bridg",IF(NOT(ISNUMBER(X47)),"No direct quote",IF(ABS(X47)<=Y47,"Match (net of Bridg fee)",IF(ABS(W47)<=Y47,"Match (Bridg fee not applied)",IF(X47<0,"Bridg LOWER than venue","Bridg HIGHER than venue")))))
A48: ETH → SOL | B48: 2 | C48: deBridge | D48: 97.8387 | F48: 99.920018 | G48: 2.0844 | H48: =IF(ISNUMBER(F48),F48-N(G48),"") | I48: =IF(AND(ISNUMBER(D48),ISNUMBER(H48)),(D48-H48)/100*10000,"") | J48: 0.05 | K48: =IF(ISNUMBER(I48),I48+N(J48)/100*10000,"") | L48: 0.004 | M48: +2.0844 USDC charged on top of 100 input (subtracted) | N48: 2026-09-23T14:23:47.144Z | O48: 2026-09-23T14:23:47.140Z | Q48: BSC → SOL | R48: SimpleSwap | S48: =COUNTIFS($A$5:$A$214,Q48,$C$5:$C$214,R48) | T48: =COUNTIFS($A$5:$A$214,Q48,$C$5:$C$214,R48,$D$5:$D$214,">0") | U48: =IFERROR(AVERAGEIFS($D$5:$D$214,$A$5:$A$214,Q48,$C$5:$C$214,R48),"—") | V48: =IFERROR(AVERAGEIFS($H$5:$H$214,$A$5:$A$214,Q48,$C$5:$C$214,R48),"—") | W48: =IFERROR(AVERAGEIFS($I$5:$I$214,$A$5:$A$214,Q48,$C$5:$C$214,R48),"—") | X48: =IFERROR(AVERAGEIFS($K$5:$K$214,$A$5:$A$214,Q48,$C$5:$C$214,R48),"—") | Y48: 2 | Z48: =IF(T48=0,"NOT LISTED on Bridg",IF(NOT(ISNUMBER(X48)),"No direct quote",IF(ABS(X48)<=Y48,"Match (net of Bridg fee)",IF(ABS(W48)<=Y48,"Match (Bridg fee not applied)",IF(X48<0,"Bridg LOWER than venue","Bridg HIGHER than venue")))))
A49: ETH → SOL | B49: 3 | C49: deBridge | D49: 98.077794 | F49: 99.880035 | G49: 6.6166 | H49: =IF(ISNUMBER(F49),F49-N(G49),"") | I49: =IF(AND(ISNUMBER(D49),ISNUMBER(H49)),(D49-H49)/100*10000,"") | J49: 0.05 | K49: =IF(ISNUMBER(I49),I49+N(J49)/100*10000,"") | L49: 0.001 | M49: +6.6166 USDC charged on top of 100 input (subtracted) | N49: 2026-09-23T14:27:28.356Z | O49: 2026-09-23T14:27:28.355Z | Q49: BSC → SOL | R49: Symbiosis | S49: =COUNTIFS($A$5:$A$214,Q49,$C$5:$C$214,R49) | T49: =COUNTIFS($A$5:$A$214,Q49,$C$5:$C$214,R49,$D$5:$D$214,">0") | U49: =IFERROR(AVERAGEIFS($D$5:$D$214,$A$5:$A$214,Q49,$C$5:$C$214,R49),"—") | V49: =IFERROR(AVERAGEIFS($H$5:$H$214,$A$5:$A$214,Q49,$C$5:$C$214,R49),"—") | W49: =IFERROR(AVERAGEIFS($I$5:$I$214,$A$5:$A$214,Q49,$C$5:$C$214,R49),"—") | X49: =IFERROR(AVERAGEIFS($K$5:$K$214,$A$5:$A$214,Q49,$C$5:$C$214,R49),"—") | Y49: 2 | Z49: =IF(T49=0,"NOT LISTED on Bridg",IF(NOT(ISNUMBER(X49)),"No direct quote",IF(ABS(X49)<=Y49,"Match (net of Bridg fee)",IF(ABS(W49)<=Y49,"Match (Bridg fee not applied)",IF(X49<0,"Bridg LOWER than venue","Bridg HIGHER than venue")))))
A50: ETH → SOL | B50: 1 | C50: LI.FI (Jumper) | D50: 98.994462 | F50: 99.945703 | H50: =IF(ISNUMBER(F50),F50-N(G50),"") | I50: =IF(AND(ISNUMBER(D50),ISNUMBER(H50)),(D50-H50)/100*10000,"") | J50: 0.05 | K50: =IF(ISNUMBER(I50),I50+N(J50)/100*10000,"") | L50: 0.001 | M50: Jumper Best Return via Relay; max route 100.0 | N50: 2026-09-23T14:19:28.697Z | O50: 2026-09-23T14:19:28.698Z | Q50: SOL → Base | R50: Relay | S50: =COUNTIFS($A$5:$A$214,Q50,$C$5:$C$214,R50) | T50: =COUNTIFS($A$5:$A$214,Q50,$C$5:$C$214,R50,$D$5:$D$214,">0") | U50: =IFERROR(AVERAGEIFS($D$5:$D$214,$A$5:$A$214,Q50,$C$5:$C$214,R50),"—") | V50: =IFERROR(AVERAGEIFS($H$5:$H$214,$A$5:$A$214,Q50,$C$5:$C$214,R50),"—") | W50: =IFERROR(AVERAGEIFS($I$5:$I$214,$A$5:$A$214,Q50,$C$5:$C$214,R50),"—") | X50: =IFERROR(AVERAGEIFS($K$5:$K$214,$A$5:$A$214,Q50,$C$5:$C$214,R50),"—") | Y50: 2 | Z50: =IF(T50=0,"NOT LISTED on Bridg",IF(NOT(ISNUMBER(X50)),"No direct quote",IF(ABS(X50)<=Y50,"Match (net of Bridg fee)",IF(ABS(W50)<=Y50,"Match (Bridg fee not applied)",IF(X50<0,"Bridg LOWER than venue","Bridg HIGHER than venue")))))
A51: ETH → SOL | B51: 2 | C51: LI.FI (Jumper) | D51: 98.995817 | F51: 99.945717 | H51: =IF(ISNUMBER(F51),F51-N(G51),"") | I51: =IF(AND(ISNUMBER(D51),ISNUMBER(H51)),(D51-H51)/100*10000,"") | J51: 0.05 | K51: =IF(ISNUMBER(I51),I51+N(J51)/100*10000,"") | L51: 0.002 | M51: Jumper Best Return via Relay; max route 100.0 | N51: 2026-09-23T14:23:47.144Z | O51: 2026-09-23T14:23:47.142Z | Q51: SOL → Base | R51: deBridge | S51: =COUNTIFS($A$5:$A$214,Q51,$C$5:$C$214,R51) | T51: =COUNTIFS($A$5:$A$214,Q51,$C$5:$C$214,R51,$D$5:$D$214,">0") | U51: =IFERROR(AVERAGEIFS($D$5:$D$214,$A$5:$A$214,Q51,$C$5:$C$214,R51),"—") | V51: =IFERROR(AVERAGEIFS($H$5:$H$214,$A$5:$A$214,Q51,$C$5:$C$214,R51),"—") | W51: =IFERROR(AVERAGEIFS($I$5:$I$214,$A$5:$A$214,Q51,$C$5:$C$214,R51),"—") | X51: =IFERROR(AVERAGEIFS($K$5:$K$214,$A$5:$A$214,Q51,$C$5:$C$214,R51),"—") | Y51: 2 | Z51: =IF(T51=0,"NOT LISTED on Bridg",IF(NOT(ISNUMBER(X51)),"No direct quote",IF(ABS(X51)<=Y51,"Match (net of Bridg fee)",IF(ABS(W51)<=Y51,"Match (Bridg fee not applied)",IF(X51<0,"Bridg LOWER than venue","Bridg HIGHER than venue")))))
A52: ETH → SOL | B52: 3 | C52: LI.FI (Jumper) | D52: 98.99596 | F52: 99.945713 | H52: =IF(ISNUMBER(F52),F52-N(G52),"") | I52: =IF(AND(ISNUMBER(D52),ISNUMBER(H52)),(D52-H52)/100*10000,"") | J52: 0.05 | K52: =IF(ISNUMBER(I52),I52+N(J52)/100*10000,"") | L52: 0 | M52: Jumper Best Return via Relay; max route 100.0 | N52: 2026-09-23T14:27:28.356Z | O52: 2026-09-23T14:27:28.356Z | Q52: SOL → Base | R52: LI.FI (Jumper) | S52: =COUNTIFS($A$5:$A$214,Q52,$C$5:$C$214,R52) | T52: =COUNTIFS($A$5:$A$214,Q52,$C$5:$C$214,R52,$D$5:$D$214,">0") | U52: =IFERROR(AVERAGEIFS($D$5:$D$214,$A$5:$A$214,Q52,$C$5:$C$214,R52),"—") | V52: =IFERROR(AVERAGEIFS($H$5:$H$214,$A$5:$A$214,Q52,$C$5:$C$214,R52),"—") | W52: =IFERROR(AVERAGEIFS($I$5:$I$214,$A$5:$A$214,Q52,$C$5:$C$214,R52),"—") | X52: =IFERROR(AVERAGEIFS($K$5:$K$214,$A$5:$A$214,Q52,$C$5:$C$214,R52),"—") | Y52: 2 | Z52: =IF(T52=0,"NOT LISTED on Bridg",IF(NOT(ISNUMBER(X52)),"No direct quote",IF(ABS(X52)<=Y52,"Match (net of Bridg fee)",IF(ABS(W52)<=Y52,"Match (Bridg fee not applied)",IF(X52<0,"Bridg LOWER than venue","Bridg HIGHER than venue")))))
A53: ETH → SOL | B53: 1 | C53: Across | D53: not listed | F53: 99.99 | H53: =IF(ISNUMBER(F53),F53-N(G53),"") | I53: =IF(AND(ISNUMBER(D53),ISNUMBER(H53)),(D53-H53)/100*10000,"") | J53: 0.05 | K53: =IF(ISNUMBER(I53),I53+N(J53)/100*10000,"") | L53: 0 | N53: 2026-09-23T14:19:28.697Z | O53: 2026-09-23T14:19:28.697Z | Q53: SOL → Base | R53: Across | S53: =COUNTIFS($A$5:$A$214,Q53,$C$5:$C$214,R53) | T53: =COUNTIFS($A$5:$A$214,Q53,$C$5:$C$214,R53,$D$5:$D$214,">0") | U53: =IFERROR(AVERAGEIFS($D$5:$D$214,$A$5:$A$214,Q53,$C$5:$C$214,R53),"—") | V53: =IFERROR(AVERAGEIFS($H$5:$H$214,$A$5:$A$214,Q53,$C$5:$C$214,R53),"—") | W53: =IFERROR(AVERAGEIFS($I$5:$I$214,$A$5:$A$214,Q53,$C$5:$C$214,R53),"—") | X53: =IFERROR(AVERAGEIFS($K$5:$K$214,$A$5:$A$214,Q53,$C$5:$C$214,R53),"—") | Y53: 2 | Z53: =IF(T53=0,"NOT LISTED on Bridg",IF(NOT(ISNUMBER(X53)),"No direct quote",IF(ABS(X53)<=Y53,"Match (net of Bridg fee)",IF(ABS(W53)<=Y53,"Match (Bridg fee not applied)",IF(X53<0,"Bridg LOWER than venue","Bridg HIGHER than venue")))))
A54: ETH → SOL | B54: 2 | C54: Across | D54: not listed | F54: 99.99 | H54: =IF(ISNUMBER(F54),F54-N(G54),"") | I54: =IF(AND(ISNUMBER(D54),ISNUMBER(H54)),(D54-H54)/100*10000,"") | J54: 0.05 | K54: =IF(ISNUMBER(I54),I54+N(J54)/100*10000,"") | L54: 0.005 | N54: 2026-09-23T14:23:47.144Z | O54: 2026-09-23T14:23:47.139Z | Q54: SOL → Base | R54: Mayan | S54: =COUNTIFS($A$5:$A$214,Q54,$C$5:$C$214,R54) | T54: =COUNTIFS($A$5:$A$214,Q54,$C$5:$C$214,R54,$D$5:$D$214,">0") | U54: =IFERROR(AVERAGEIFS($D$5:$D$214,$A$5:$A$214,Q54,$C$5:$C$214,R54),"—") | V54: =IFERROR(AVERAGEIFS($H$5:$H$214,$A$5:$A$214,Q54,$C$5:$C$214,R54),"—") | W54: =IFERROR(AVERAGEIFS($I$5:$I$214,$A$5:$A$214,Q54,$C$5:$C$214,R54),"—") | X54: =IFERROR(AVERAGEIFS($K$5:$K$214,$A$5:$A$214,Q54,$C$5:$C$214,R54),"—") | Y54: 4 | Z54: =IF(T54=0,"NOT LISTED on Bridg",IF(NOT(ISNUMBER(X54)),"No direct quote",IF(ABS(X54)<=Y54,"Match (net of Bridg fee)",IF(ABS(W54)<=Y54,"Match (Bridg fee not applied)",IF(X54<0,"Bridg LOWER than venue","Bridg HIGHER than venue")))))
A55: ETH → SOL | B55: 3 | C55: Across | D55: not listed | F55: 99.99 | H55: =IF(ISNUMBER(F55),F55-N(G55),"") | I55: =IF(AND(ISNUMBER(D55),ISNUMBER(H55)),(D55-H55)/100*10000,"") | J55: 0.05 | K55: =IF(ISNUMBER(I55),I55+N(J55)/100*10000,"") | L55: 0.001 | N55: 2026-09-23T14:27:28.356Z | O55: 2026-09-23T14:27:28.355Z | Q55: SOL → Base | R55: Allbridge Core | S55: =COUNTIFS($A$5:$A$214,Q55,$C$5:$C$214,R55) | T55: =COUNTIFS($A$5:$A$214,Q55,$C$5:$C$214,R55,$D$5:$D$214,">0") | U55: =IFERROR(AVERAGEIFS($D$5:$D$214,$A$5:$A$214,Q55,$C$5:$C$214,R55),"—") | V55: =IFERROR(AVERAGEIFS($H$5:$H$214,$A$5:$A$214,Q55,$C$5:$C$214,R55),"—") | W55: =IFERROR(AVERAGEIFS($I$5:$I$214,$A$5:$A$214,Q55,$C$5:$C$214,R55),"—") | X55: =IFERROR(AVERAGEIFS($K$5:$K$214,$A$5:$A$214,Q55,$C$5:$C$214,R55),"—") | Y55: 2 | Z55: =IF(T55=0,"NOT LISTED on Bridg",IF(NOT(ISNUMBER(X55)),"No direct quote",IF(ABS(X55)<=Y55,"Match (net of Bridg fee)",IF(ABS(W55)<=Y55,"Match (Bridg fee not applied)",IF(X55<0,"Bridg LOWER than venue","Bridg HIGHER than venue")))))
A56: ETH → SOL | B56: 1 | C56: Mayan | D56: 99.012777 | F56: 99.0127 | H56: =IF(ISNUMBER(F56),F56-N(G56),"") | I56: =IF(AND(ISNUMBER(D56),ISNUMBER(H56)),(D56-H56)/100*10000,"") | J56: 0.05 | K56: =IF(ISNUMBER(I56),I56+N(J56)/100*10000,"") | L56: 0.001 | M56: Swift v2; UI shows 4 dp | N56: 2026-09-23T14:19:28.697Z | O56: 2026-09-23T14:19:28.698Z | Q56: SOL → Base | R56: CCTP (via Portal) | S56: =COUNTIFS($A$5:$A$214,Q56,$C$5:$C$214,R56) | T56: =COUNTIFS($A$5:$A$214,Q56,$C$5:$C$214,R56,$D$5:$D$214,">0") | U56: =IFERROR(AVERAGEIFS($D$5:$D$214,$A$5:$A$214,Q56,$C$5:$C$214,R56),"—") | V56: =IFERROR(AVERAGEIFS($H$5:$H$214,$A$5:$A$214,Q56,$C$5:$C$214,R56),"—") | W56: =IFERROR(AVERAGEIFS($I$5:$I$214,$A$5:$A$214,Q56,$C$5:$C$214,R56),"—") | X56: =IFERROR(AVERAGEIFS($K$5:$K$214,$A$5:$A$214,Q56,$C$5:$C$214,R56),"—") | Y56: 2 | Z56: =IF(T56=0,"NOT LISTED on Bridg",IF(NOT(ISNUMBER(X56)),"No direct quote",IF(ABS(X56)<=Y56,"Match (net of Bridg fee)",IF(ABS(W56)<=Y56,"Match (Bridg fee not applied)",IF(X56<0,"Bridg LOWER than venue","Bridg HIGHER than venue")))))
A57: ETH → SOL | B57: 2 | C57: Mayan | D57: 98.970404 | F57: 98.9619 | H57: =IF(ISNUMBER(F57),F57-N(G57),"") | I57: =IF(AND(ISNUMBER(D57),ISNUMBER(H57)),(D57-H57)/100*10000,"") | J57: 0.05 | K57: =IF(ISNUMBER(I57),I57+N(J57)/100*10000,"") | L57: 0.004 | M57: Swift v2; UI shows 4 dp | N57: 2026-09-23T14:23:47.144Z | O57: 2026-09-23T14:23:47.140Z | Q57: SOL → Base | R57: Husher | S57: =COUNTIFS($A$5:$A$214,Q57,$C$5:$C$214,R57) | T57: =COUNTIFS($A$5:$A$214,Q57,$C$5:$C$214,R57,$D$5:$D$214,">0") | U57: =IFERROR(AVERAGEIFS($D$5:$D$214,$A$5:$A$214,Q57,$C$5:$C$214,R57),"—") | V57: =IFERROR(AVERAGEIFS($H$5:$H$214,$A$5:$A$214,Q57,$C$5:$C$214,R57),"—") | W57: =IFERROR(AVERAGEIFS($I$5:$I$214,$A$5:$A$214,Q57,$C$5:$C$214,R57),"—") | X57: =IFERROR(AVERAGEIFS($K$5:$K$214,$A$5:$A$214,Q57,$C$5:$C$214,R57),"—") | Y57: 2 | Z57: =IF(T57=0,"NOT LISTED on Bridg",IF(NOT(ISNUMBER(X57)),"No direct quote",IF(ABS(X57)<=Y57,"Match (net of Bridg fee)",IF(ABS(W57)<=Y57,"Match (Bridg fee not applied)",IF(X57<0,"Bridg LOWER than venue","Bridg HIGHER than venue")))))
A58: ETH → SOL | B58: 3 | C58: Mayan | D58: 99.028479 | F58: 99.0287 | H58: =IF(ISNUMBER(F58),F58-N(G58),"") | I58: =IF(AND(ISNUMBER(D58),ISNUMBER(H58)),(D58-H58)/100*10000,"") | J58: 0.05 | K58: =IF(ISNUMBER(I58),I58+N(J58)/100*10000,"") | L58: 0.002 | M58: Swift v2; UI shows 4 dp | N58: 2026-09-23T14:27:28.356Z | O58: 2026-09-23T14:27:28.354Z | Q58: SOL → Base | R58: Layerswap | S58: =COUNTIFS($A$5:$A$214,Q58,$C$5:$C$214,R58) | T58: =COUNTIFS($A$5:$A$214,Q58,$C$5:$C$214,R58,$D$5:$D$214,">0") | U58: =IFERROR(AVERAGEIFS($D$5:$D$214,$A$5:$A$214,Q58,$C$5:$C$214,R58),"—") | V58: =IFERROR(AVERAGEIFS($H$5:$H$214,$A$5:$A$214,Q58,$C$5:$C$214,R58),"—") | W58: =IFERROR(AVERAGEIFS($I$5:$I$214,$A$5:$A$214,Q58,$C$5:$C$214,R58),"—") | X58: =IFERROR(AVERAGEIFS($K$5:$K$214,$A$5:$A$214,Q58,$C$5:$C$214,R58),"—") | Y58: 2 | Z58: =IF(T58=0,"NOT LISTED on Bridg",IF(NOT(ISNUMBER(X58)),"No direct quote",IF(ABS(X58)<=Y58,"Match (net of Bridg fee)",IF(ABS(W58)<=Y58,"Match (Bridg fee not applied)",IF(X58<0,"Bridg LOWER than venue","Bridg HIGHER than venue")))))
A59: ETH → SOL | B59: 1 | C59: Allbridge Core | D59: 99.85005 | F59: 99.9 | H59: =IF(ISNUMBER(F59),F59-N(G59),"") | I59: =IF(AND(ISNUMBER(D59),ISNUMBER(H59)),(D59-H59)/100*10000,"") | J59: 0.05 | K59: =IF(ISNUMBER(I59),I59+N(J59)/100*10000,"") | L59: 0 | M59: +0.000137 ETH (relayer fee, fee=native) charged on top of 100 input (not converted) | N59: 2026-09-23T14:19:28.697Z | O59: 2026-09-23T14:19:28.697Z | Q59: SOL → Base | R59: Meson | S59: =COUNTIFS($A$5:$A$214,Q59,$C$5:$C$214,R59) | T59: =COUNTIFS($A$5:$A$214,Q59,$C$5:$C$214,R59,$D$5:$D$214,">0") | U59: =IFERROR(AVERAGEIFS($D$5:$D$214,$A$5:$A$214,Q59,$C$5:$C$214,R59),"—") | V59: =IFERROR(AVERAGEIFS($H$5:$H$214,$A$5:$A$214,Q59,$C$5:$C$214,R59),"—") | W59: =IFERROR(AVERAGEIFS($I$5:$I$214,$A$5:$A$214,Q59,$C$5:$C$214,R59),"—") | X59: =IFERROR(AVERAGEIFS($K$5:$K$214,$A$5:$A$214,Q59,$C$5:$C$214,R59),"—") | Y59: 2 | Z59: =IF(T59=0,"NOT LISTED on Bridg",IF(NOT(ISNUMBER(X59)),"No direct quote",IF(ABS(X59)<=Y59,"Match (net of Bridg fee)",IF(ABS(W59)<=Y59,"Match (Bridg fee not applied)",IF(X59<0,"Bridg LOWER than venue","Bridg HIGHER than venue")))))
A60: ETH → SOL | B60: 2 | C60: Allbridge Core | D60: 99.85005 | F60: 99.9 | H60: =IF(ISNUMBER(F60),F60-N(G60),"") | I60: =IF(AND(ISNUMBER(D60),ISNUMBER(H60)),(D60-H60)/100*10000,"") | J60: 0.05 | K60: =IF(ISNUMBER(I60),I60+N(J60)/100*10000,"") | L60: 0.005 | M60: +0.000137 ETH (relayer fee, fee=native) charged on top of 100 input (not converted) | N60: 2026-09-23T14:23:47.144Z | O60: 2026-09-23T14:23:47.139Z | Q60: SOL → Base | R60: SimpleSwap | S60: =COUNTIFS($A$5:$A$214,Q60,$C$5:$C$214,R60) | T60: =COUNTIFS($A$5:$A$214,Q60,$C$5:$C$214,R60,$D$5:$D$214,">0") | U60: =IFERROR(AVERAGEIFS($D$5:$D$214,$A$5:$A$214,Q60,$C$5:$C$214,R60),"—") | V60: =IFERROR(AVERAGEIFS($H$5:$H$214,$A$5:$A$214,Q60,$C$5:$C$214,R60),"—") | W60: =IFERROR(AVERAGEIFS($I$5:$I$214,$A$5:$A$214,Q60,$C$5:$C$214,R60),"—") | X60: =IFERROR(AVERAGEIFS($K$5:$K$214,$A$5:$A$214,Q60,$C$5:$C$214,R60),"—") | Y60: 2 | Z60: =IF(T60=0,"NOT LISTED on Bridg",IF(NOT(ISNUMBER(X60)),"No direct quote",IF(ABS(X60)<=Y60,"Match (net of Bridg fee)",IF(ABS(W60)<=Y60,"Match (Bridg fee not applied)",IF(X60<0,"Bridg LOWER than venue","Bridg HIGHER than venue")))))
A61: ETH → SOL | B61: 3 | C61: Allbridge Core | D61: 99.85005 | F61: 99.9 | H61: =IF(ISNUMBER(F61),F61-N(G61),"") | I61: =IF(AND(ISNUMBER(D61),ISNUMBER(H61)),(D61-H61)/100*10000,"") | J61: 0.05 | K61: =IF(ISNUMBER(I61),I61+N(J61)/100*10000,"") | L61: 0.002 | M61: +0.000137 ETH (relayer fee, fee=native) charged on top of 100 input (not converted) | N61: 2026-09-23T14:27:28.356Z | O61: 2026-09-23T14:27:28.354Z | Q61: SOL → Base | R61: Skip Go | S61: =COUNTIFS($A$5:$A$214,Q61,$C$5:$C$214,R61) | T61: =COUNTIFS($A$5:$A$214,Q61,$C$5:$C$214,R61,$D$5:$D$214,">0") | U61: =IFERROR(AVERAGEIFS($D$5:$D$214,$A$5:$A$214,Q61,$C$5:$C$214,R61),"—") | V61: =IFERROR(AVERAGEIFS($H$5:$H$214,$A$5:$A$214,Q61,$C$5:$C$214,R61),"—") | W61: =IFERROR(AVERAGEIFS($I$5:$I$214,$A$5:$A$214,Q61,$C$5:$C$214,R61),"—") | X61: =IFERROR(AVERAGEIFS($K$5:$K$214,$A$5:$A$214,Q61,$C$5:$C$214,R61),"—") | Y61: 2 | Z61: =IF(T61=0,"NOT LISTED on Bridg",IF(NOT(ISNUMBER(X61)),"No direct quote",IF(ABS(X61)<=Y61,"Match (net of Bridg fee)",IF(ABS(W61)<=Y61,"Match (Bridg fee not applied)",IF(X61<0,"Bridg LOWER than venue","Bridg HIGHER than venue")))))
A62: ETH → SOL | B62: 1 | C62: CCTP (via Portal) | D62: 99.781658 | F62: 99.980001 | H62: =IF(ISNUMBER(F62),F62-N(G62),"") | I62: =IF(AND(ISNUMBER(D62),ISNUMBER(H62)),(D62-H62)/100*10000,"") | J62: 0.05 | K62: =IF(ISNUMBER(I62),I62+N(J62)/100*10000,"") | L62: 0.001 | M62: via Portal (CCTPv2FastExecutorRoute); executor fee hidden until wallet connect | N62: 2026-09-23T14:19:28.697Z | O62: 2026-09-23T14:19:28.696Z | Q62: Base → SOL | R62: Relay | S62: =COUNTIFS($A$5:$A$214,Q62,$C$5:$C$214,R62) | T62: =COUNTIFS($A$5:$A$214,Q62,$C$5:$C$214,R62,$D$5:$D$214,">0") | U62: =IFERROR(AVERAGEIFS($D$5:$D$214,$A$5:$A$214,Q62,$C$5:$C$214,R62),"—") | V62: =IFERROR(AVERAGEIFS($H$5:$H$214,$A$5:$A$214,Q62,$C$5:$C$214,R62),"—") | W62: =IFERROR(AVERAGEIFS($I$5:$I$214,$A$5:$A$214,Q62,$C$5:$C$214,R62),"—") | X62: =IFERROR(AVERAGEIFS($K$5:$K$214,$A$5:$A$214,Q62,$C$5:$C$214,R62),"—") | Y62: 2 | Z62: =IF(T62=0,"NOT LISTED on Bridg",IF(NOT(ISNUMBER(X62)),"No direct quote",IF(ABS(X62)<=Y62,"Match (net of Bridg fee)",IF(ABS(W62)<=Y62,"Match (Bridg fee not applied)",IF(X62<0,"Bridg LOWER than venue","Bridg HIGHER than venue")))))
A63: ETH → SOL | B63: 2 | C63: CCTP (via Portal) | D63: 99.781658 | F63: 99.980001 | H63: =IF(ISNUMBER(F63),F63-N(G63),"") | I63: =IF(AND(ISNUMBER(D63),ISNUMBER(H63)),(D63-H63)/100*10000,"") | J63: 0.05 | K63: =IF(ISNUMBER(I63),I63+N(J63)/100*10000,"") | L63: 0.001 | M63: via Portal (CCTPv2FastExecutorRoute); executor fee hidden until wallet connect | N63: 2026-09-23T14:23:47.144Z | O63: 2026-09-23T14:23:47.145Z | Q63: Base → SOL | R63: deBridge | S63: =COUNTIFS($A$5:$A$214,Q63,$C$5:$C$214,R63) | T63: =COUNTIFS($A$5:$A$214,Q63,$C$5:$C$214,R63,$D$5:$D$214,">0") | U63: =IFERROR(AVERAGEIFS($D$5:$D$214,$A$5:$A$214,Q63,$C$5:$C$214,R63),"—") | V63: =IFERROR(AVERAGEIFS($H$5:$H$214,$A$5:$A$214,Q63,$C$5:$C$214,R63),"—") | W63: =IFERROR(AVERAGEIFS($I$5:$I$214,$A$5:$A$214,Q63,$C$5:$C$214,R63),"—") | X63: =IFERROR(AVERAGEIFS($K$5:$K$214,$A$5:$A$214,Q63,$C$5:$C$214,R63),"—") | Y63: 2 | Z63: =IF(T63=0,"NOT LISTED on Bridg",IF(NOT(ISNUMBER(X63)),"No direct quote",IF(ABS(X63)<=Y63,"Match (net of Bridg fee)",IF(ABS(W63)<=Y63,"Match (Bridg fee not applied)",IF(X63<0,"Bridg LOWER than venue","Bridg HIGHER than venue")))))
A64: ETH → SOL | B64: 3 | C64: CCTP (via Portal) | D64: 99.78301 | F64: 99.980001 | H64: =IF(ISNUMBER(F64),F64-N(G64),"") | I64: =IF(AND(ISNUMBER(D64),ISNUMBER(H64)),(D64-H64)/100*10000,"") | J64: 0.05 | K64: =IF(ISNUMBER(I64),I64+N(J64)/100*10000,"") | L64: 0.003 | M64: via Portal (CCTPv2FastExecutorRoute); executor fee hidden until wallet connect | N64: 2026-09-23T14:27:28.356Z | O64: 2026-09-23T14:27:28.353Z | Q64: Base → SOL | R64: LI.FI (Jumper) | S64: =COUNTIFS($A$5:$A$214,Q64,$C$5:$C$214,R64) | T64: =COUNTIFS($A$5:$A$214,Q64,$C$5:$C$214,R64,$D$5:$D$214,">0") | U64: =IFERROR(AVERAGEIFS($D$5:$D$214,$A$5:$A$214,Q64,$C$5:$C$214,R64),"—") | V64: =IFERROR(AVERAGEIFS($H$5:$H$214,$A$5:$A$214,Q64,$C$5:$C$214,R64),"—") | W64: =IFERROR(AVERAGEIFS($I$5:$I$214,$A$5:$A$214,Q64,$C$5:$C$214,R64),"—") | X64: =IFERROR(AVERAGEIFS($K$5:$K$214,$A$5:$A$214,Q64,$C$5:$C$214,R64),"—") | Y64: 2 | Z64: =IF(T64=0,"NOT LISTED on Bridg",IF(NOT(ISNUMBER(X64)),"No direct quote",IF(ABS(X64)<=Y64,"Match (net of Bridg fee)",IF(ABS(W64)<=Y64,"Match (Bridg fee not applied)",IF(X64<0,"Bridg LOWER than venue","Bridg HIGHER than venue")))))
A65: ETH → SOL | B65: 1 | C65: Husher | D65: 99.45025 | F65: 99.35 | H65: =IF(ISNUMBER(F65),F65-N(G65),"") | I65: =IF(AND(ISNUMBER(D65),ISNUMBER(H65)),(D65-H65)/100*10000,"") | J65: 0.05 | K65: =IF(ISNUMBER(I65),I65+N(J65)/100*10000,"") | L65: 0.001 | N65: 2026-09-23T14:19:28.697Z | O65: 2026-09-23T14:19:28.696Z | Q65: Base → SOL | R65: Across | S65: =COUNTIFS($A$5:$A$214,Q65,$C$5:$C$214,R65) | T65: =COUNTIFS($A$5:$A$214,Q65,$C$5:$C$214,R65,$D$5:$D$214,">0") | U65: =IFERROR(AVERAGEIFS($D$5:$D$214,$A$5:$A$214,Q65,$C$5:$C$214,R65),"—") | V65: =IFERROR(AVERAGEIFS($H$5:$H$214,$A$5:$A$214,Q65,$C$5:$C$214,R65),"—") | W65: =IFERROR(AVERAGEIFS($I$5:$I$214,$A$5:$A$214,Q65,$C$5:$C$214,R65),"—") | X65: =IFERROR(AVERAGEIFS($K$5:$K$214,$A$5:$A$214,Q65,$C$5:$C$214,R65),"—") | Y65: 2 | Z65: =IF(T65=0,"NOT LISTED on Bridg",IF(NOT(ISNUMBER(X65)),"No direct quote",IF(ABS(X65)<=Y65,"Match (net of Bridg fee)",IF(ABS(W65)<=Y65,"Match (Bridg fee not applied)",IF(X65<0,"Bridg LOWER than venue","Bridg HIGHER than venue")))))
A66: ETH → SOL | B66: 2 | C66: Husher | D66: 99.45025 | F66: 99.35 | H66: =IF(ISNUMBER(F66),F66-N(G66),"") | I66: =IF(AND(ISNUMBER(D66),ISNUMBER(H66)),(D66-H66)/100*10000,"") | J66: 0.05 | K66: =IF(ISNUMBER(I66),I66+N(J66)/100*10000,"") | L66: 0.004 | N66: 2026-09-23T14:23:47.144Z | O66: 2026-09-23T14:23:47.140Z | Q66: Base → SOL | R66: Mayan | S66: =COUNTIFS($A$5:$A$214,Q66,$C$5:$C$214,R66) | T66: =COUNTIFS($A$5:$A$214,Q66,$C$5:$C$214,R66,$D$5:$D$214,">0") | U66: =IFERROR(AVERAGEIFS($D$5:$D$214,$A$5:$A$214,Q66,$C$5:$C$214,R66),"—") | V66: =IFERROR(AVERAGEIFS($H$5:$H$214,$A$5:$A$214,Q66,$C$5:$C$214,R66),"—") | W66: =IFERROR(AVERAGEIFS($I$5:$I$214,$A$5:$A$214,Q66,$C$5:$C$214,R66),"—") | X66: =IFERROR(AVERAGEIFS($K$5:$K$214,$A$5:$A$214,Q66,$C$5:$C$214,R66),"—") | Y66: 4 | Z66: =IF(T66=0,"NOT LISTED on Bridg",IF(NOT(ISNUMBER(X66)),"No direct quote",IF(ABS(X66)<=Y66,"Match (net of Bridg fee)",IF(ABS(W66)<=Y66,"Match (Bridg fee not applied)",IF(X66<0,"Bridg LOWER than venue","Bridg HIGHER than venue")))))
A67: ETH → SOL | B67: 3 | C67: Husher | D67: 99.45025 | F67: 99.35 | H67: =IF(ISNUMBER(F67),F67-N(G67),"") | I67: =IF(AND(ISNUMBER(D67),ISNUMBER(H67)),(D67-H67)/100*10000,"") | J67: 0.05 | K67: =IF(ISNUMBER(I67),I67+N(J67)/100*10000,"") | L67: 0.002 | N67: 2026-09-23T14:27:28.356Z | O67: 2026-09-23T14:27:28.354Z | Q67: Base → SOL | R67: Allbridge Core | S67: =COUNTIFS($A$5:$A$214,Q67,$C$5:$C$214,R67) | T67: =COUNTIFS($A$5:$A$214,Q67,$C$5:$C$214,R67,$D$5:$D$214,">0") | U67: =IFERROR(AVERAGEIFS($D$5:$D$214,$A$5:$A$214,Q67,$C$5:$C$214,R67),"—") | V67: =IFERROR(AVERAGEIFS($H$5:$H$214,$A$5:$A$214,Q67,$C$5:$C$214,R67),"—") | W67: =IFERROR(AVERAGEIFS($I$5:$I$214,$A$5:$A$214,Q67,$C$5:$C$214,R67),"—") | X67: =IFERROR(AVERAGEIFS($K$5:$K$214,$A$5:$A$214,Q67,$C$5:$C$214,R67),"—") | Y67: 2 | Z67: =IF(T67=0,"NOT LISTED on Bridg",IF(NOT(ISNUMBER(X67)),"No direct quote",IF(ABS(X67)<=Y67,"Match (net of Bridg fee)",IF(ABS(W67)<=Y67,"Match (Bridg fee not applied)",IF(X67<0,"Bridg LOWER than venue","Bridg HIGHER than venue")))))
A68: ETH → SOL | B68: 1 | C68: Layerswap | D68: 99.599588 | F68: 99.681249 | H68: =IF(ISNUMBER(F68),F68-N(G68),"") | I68: =IF(AND(ISNUMBER(D68),ISNUMBER(H68)),(D68-H68)/100*10000,"") | J68: 0.05 | K68: =IF(ISNUMBER(I68),I68+N(J68)/100*10000,"") | L68: 0.002 | N68: 2026-09-23T14:19:28.697Z | O68: 2026-09-23T14:19:28.699Z | Q68: Base → SOL | R68: CCTP (via Portal) | S68: =COUNTIFS($A$5:$A$214,Q68,$C$5:$C$214,R68) | T68: =COUNTIFS($A$5:$A$214,Q68,$C$5:$C$214,R68,$D$5:$D$214,">0") | U68: =IFERROR(AVERAGEIFS($D$5:$D$214,$A$5:$A$214,Q68,$C$5:$C$214,R68),"—") | V68: =IFERROR(AVERAGEIFS($H$5:$H$214,$A$5:$A$214,Q68,$C$5:$C$214,R68),"—") | W68: =IFERROR(AVERAGEIFS($I$5:$I$214,$A$5:$A$214,Q68,$C$5:$C$214,R68),"—") | X68: =IFERROR(AVERAGEIFS($K$5:$K$214,$A$5:$A$214,Q68,$C$5:$C$214,R68),"—") | Y68: 2 | Z68: =IF(T68=0,"NOT LISTED on Bridg",IF(NOT(ISNUMBER(X68)),"No direct quote",IF(ABS(X68)<=Y68,"Match (net of Bridg fee)",IF(ABS(W68)<=Y68,"Match (Bridg fee not applied)",IF(X68<0,"Bridg LOWER than venue","Bridg HIGHER than venue")))))
A69: ETH → SOL | B69: 2 | C69: Layerswap | D69: 99.601114 | F69: 99.682776 | H69: =IF(ISNUMBER(F69),F69-N(G69),"") | I69: =IF(AND(ISNUMBER(D69),ISNUMBER(H69)),(D69-H69)/100*10000,"") | J69: 0.05 | K69: =IF(ISNUMBER(I69),I69+N(J69)/100*10000,"") | L69: 0.001 | N69: 2026-09-23T14:23:47.144Z | O69: 2026-09-23T14:23:47.143Z | Q69: Base → SOL | R69: Husher | S69: =COUNTIFS($A$5:$A$214,Q69,$C$5:$C$214,R69) | T69: =COUNTIFS($A$5:$A$214,Q69,$C$5:$C$214,R69,$D$5:$D$214,">0") | U69: =IFERROR(AVERAGEIFS($D$5:$D$214,$A$5:$A$214,Q69,$C$5:$C$214,R69),"—") | V69: =IFERROR(AVERAGEIFS($H$5:$H$214,$A$5:$A$214,Q69,$C$5:$C$214,R69),"—") | W69: =IFERROR(AVERAGEIFS($I$5:$I$214,$A$5:$A$214,Q69,$C$5:$C$214,R69),"—") | X69: =IFERROR(AVERAGEIFS($K$5:$K$214,$A$5:$A$214,Q69,$C$5:$C$214,R69),"—") | Y69: 2 | Z69: =IF(T69=0,"NOT LISTED on Bridg",IF(NOT(ISNUMBER(X69)),"No direct quote",IF(ABS(X69)<=Y69,"Match (net of Bridg fee)",IF(ABS(W69)<=Y69,"Match (Bridg fee not applied)",IF(X69<0,"Bridg LOWER than venue","Bridg HIGHER than venue")))))
A70: ETH → SOL | B70: 3 | C70: Layerswap | D70: 99.601095 | F70: 99.682757 | H70: =IF(ISNUMBER(F70),F70-N(G70),"") | I70: =IF(AND(ISNUMBER(D70),ISNUMBER(H70)),(D70-H70)/100*10000,"") | J70: 0.05 | K70: =IF(ISNUMBER(I70),I70+N(J70)/100*10000,"") | L70: 0 | N70: 2026-09-23T14:27:28.356Z | O70: 2026-09-23T14:27:28.356Z | Q70: Base → SOL | R70: Layerswap | S70: =COUNTIFS($A$5:$A$214,Q70,$C$5:$C$214,R70) | T70: =COUNTIFS($A$5:$A$214,Q70,$C$5:$C$214,R70,$D$5:$D$214,">0") | U70: =IFERROR(AVERAGEIFS($D$5:$D$214,$A$5:$A$214,Q70,$C$5:$C$214,R70),"—") | V70: =IFERROR(AVERAGEIFS($H$5:$H$214,$A$5:$A$214,Q70,$C$5:$C$214,R70),"—") | W70: =IFERROR(AVERAGEIFS($I$5:$I$214,$A$5:$A$214,Q70,$C$5:$C$214,R70),"—") | X70: =IFERROR(AVERAGEIFS($K$5:$K$214,$A$5:$A$214,Q70,$C$5:$C$214,R70),"—") | Y70: 2 | Z70: =IF(T70=0,"NOT LISTED on Bridg",IF(NOT(ISNUMBER(X70)),"No direct quote",IF(ABS(X70)<=Y70,"Match (net of Bridg fee)",IF(ABS(W70)<=Y70,"Match (Bridg fee not applied)",IF(X70<0,"Bridg LOWER than venue","Bridg HIGHER than venue")))))
A71: ETH → SOL | B71: 1 | C71: Meson | D71: 99.45025 | F71: 99.1 | H71: =IF(ISNUMBER(F71),F71-N(G71),"") | I71: =IF(AND(ISNUMBER(D71),ISNUMBER(H71)),(D71-H71)/100*10000,"") | J71: 0.05 | K71: =IF(ISNUMBER(I71),I71+N(J71)/100*10000,"") | L71: 0.001 | N71: 2026-09-23T14:19:28.697Z | O71: 2026-09-23T14:19:28.696Z | Q71: Base → SOL | R71: Meson | S71: =COUNTIFS($A$5:$A$214,Q71,$C$5:$C$214,R71) | T71: =COUNTIFS($A$5:$A$214,Q71,$C$5:$C$214,R71,$D$5:$D$214,">0") | U71: =IFERROR(AVERAGEIFS($D$5:$D$214,$A$5:$A$214,Q71,$C$5:$C$214,R71),"—") | V71: =IFERROR(AVERAGEIFS($H$5:$H$214,$A$5:$A$214,Q71,$C$5:$C$214,R71),"—") | W71: =IFERROR(AVERAGEIFS($I$5:$I$214,$A$5:$A$214,Q71,$C$5:$C$214,R71),"—") | X71: =IFERROR(AVERAGEIFS($K$5:$K$214,$A$5:$A$214,Q71,$C$5:$C$214,R71),"—") | Y71: 2 | Z71: =IF(T71=0,"NOT LISTED on Bridg",IF(NOT(ISNUMBER(X71)),"No direct quote",IF(ABS(X71)<=Y71,"Match (net of Bridg fee)",IF(ABS(W71)<=Y71,"Match (Bridg fee not applied)",IF(X71<0,"Bridg LOWER than venue","Bridg HIGHER than venue")))))
A72: ETH → SOL | B72: 2 | C72: Meson | D72: 99.45025 | F72: 99.1 | H72: =IF(ISNUMBER(F72),F72-N(G72),"") | I72: =IF(AND(ISNUMBER(D72),ISNUMBER(H72)),(D72-H72)/100*10000,"") | J72: 0.05 | K72: =IF(ISNUMBER(I72),I72+N(J72)/100*10000,"") | L72: 0.007 | N72: 2026-09-23T14:23:47.144Z | O72: 2026-09-23T14:23:47.137Z | Q72: Base → SOL | R72: SimpleSwap | S72: =COUNTIFS($A$5:$A$214,Q72,$C$5:$C$214,R72) | T72: =COUNTIFS($A$5:$A$214,Q72,$C$5:$C$214,R72,$D$5:$D$214,">0") | U72: =IFERROR(AVERAGEIFS($D$5:$D$214,$A$5:$A$214,Q72,$C$5:$C$214,R72),"—") | V72: =IFERROR(AVERAGEIFS($H$5:$H$214,$A$5:$A$214,Q72,$C$5:$C$214,R72),"—") | W72: =IFERROR(AVERAGEIFS($I$5:$I$214,$A$5:$A$214,Q72,$C$5:$C$214,R72),"—") | X72: =IFERROR(AVERAGEIFS($K$5:$K$214,$A$5:$A$214,Q72,$C$5:$C$214,R72),"—") | Y72: 2 | Z72: =IF(T72=0,"NOT LISTED on Bridg",IF(NOT(ISNUMBER(X72)),"No direct quote",IF(ABS(X72)<=Y72,"Match (net of Bridg fee)",IF(ABS(W72)<=Y72,"Match (Bridg fee not applied)",IF(X72<0,"Bridg LOWER than venue","Bridg HIGHER than venue")))))
A73: ETH → SOL | B73: 3 | C73: Meson | D73: 99.45025 | F73: 99.1 | H73: =IF(ISNUMBER(F73),F73-N(G73),"") | I73: =IF(AND(ISNUMBER(D73),ISNUMBER(H73)),(D73-H73)/100*10000,"") | J73: 0.05 | K73: =IF(ISNUMBER(I73),I73+N(J73)/100*10000,"") | L73: 0.002 | N73: 2026-09-23T14:27:28.356Z | O73: 2026-09-23T14:27:28.354Z | Q73: Base → SOL | R73: Skip Go | S73: =COUNTIFS($A$5:$A$214,Q73,$C$5:$C$214,R73) | T73: =COUNTIFS($A$5:$A$214,Q73,$C$5:$C$214,R73,$D$5:$D$214,">0") | U73: =IFERROR(AVERAGEIFS($D$5:$D$214,$A$5:$A$214,Q73,$C$5:$C$214,R73),"—") | V73: =IFERROR(AVERAGEIFS($H$5:$H$214,$A$5:$A$214,Q73,$C$5:$C$214,R73),"—") | W73: =IFERROR(AVERAGEIFS($I$5:$I$214,$A$5:$A$214,Q73,$C$5:$C$214,R73),"—") | X73: =IFERROR(AVERAGEIFS($K$5:$K$214,$A$5:$A$214,Q73,$C$5:$C$214,R73),"—") | Y73: 2 | Z73: =IF(T73=0,"NOT LISTED on Bridg",IF(NOT(ISNUMBER(X73)),"No direct quote",IF(ABS(X73)<=Y73,"Match (net of Bridg fee)",IF(ABS(W73)<=Y73,"Match (Bridg fee not applied)",IF(X73<0,"Bridg LOWER than venue","Bridg HIGHER than venue")))))
A74: ETH → SOL | B74: 1 | C74: SimpleSwap | D74: 95.715087 | F74: 98.482157 | H74: =IF(ISNUMBER(F74),F74-N(G74),"") | I74: =IF(AND(ISNUMBER(D74),ISNUMBER(H74)),(D74-H74)/100*10000,"") | J74: 0.05 | K74: =IF(ISNUMBER(I74),I74+N(J74)/100*10000,"") | L74: 0.005 | M74: selected card: Best rate / Decentralized; best card 98.482157 | N74: 2026-09-23T14:19:28.697Z | O74: 2026-09-23T14:19:28.702Z | Q74: Base → SOL | R74: Symbiosis | S74: =COUNTIFS($A$5:$A$214,Q74,$C$5:$C$214,R74) | T74: =COUNTIFS($A$5:$A$214,Q74,$C$5:$C$214,R74,$D$5:$D$214,">0") | U74: =IFERROR(AVERAGEIFS($D$5:$D$214,$A$5:$A$214,Q74,$C$5:$C$214,R74),"—") | V74: =IFERROR(AVERAGEIFS($H$5:$H$214,$A$5:$A$214,Q74,$C$5:$C$214,R74),"—") | W74: =IFERROR(AVERAGEIFS($I$5:$I$214,$A$5:$A$214,Q74,$C$5:$C$214,R74),"—") | X74: =IFERROR(AVERAGEIFS($K$5:$K$214,$A$5:$A$214,Q74,$C$5:$C$214,R74),"—") | Y74: 2 | Z74: =IF(T74=0,"NOT LISTED on Bridg",IF(NOT(ISNUMBER(X74)),"No direct quote",IF(ABS(X74)<=Y74,"Match (net of Bridg fee)",IF(ABS(W74)<=Y74,"Match (Bridg fee not applied)",IF(X74<0,"Bridg LOWER than venue","Bridg HIGHER than venue")))))
A75: ETH → SOL | B75: 2 | C75: SimpleSwap | D75: 95.326357 | H75: =IF(ISNUMBER(F75),F75-N(G75),"") | I75: =IF(AND(ISNUMBER(D75),ISNUMBER(H75)),(D75-H75)/100*10000,"") | J75: 0.05 | K75: =IF(ISNUMBER(I75),I75+N(J75)/100*10000,"") | L75: 0.007 | M75: selected card: None; best card None | N75: 2026-09-23T14:23:47.144Z | O75: 2026-09-23T14:23:47.137Z
A76: ETH → SOL | B76: 3 | C76: SimpleSwap | D76: 95.704517 | F76: 98.479738 | H76: =IF(ISNUMBER(F76),F76-N(G76),"") | I76: =IF(AND(ISNUMBER(D76),ISNUMBER(H76)),(D76-H76)/100*10000,"") | J76: 0.05 | K76: =IF(ISNUMBER(I76),I76+N(J76)/100*10000,"") | L76: 0.001 | M76: selected card: Best rate / Decentralized; best card 98.479738 | N76: 2026-09-23T14:27:28.356Z | O76: 2026-09-23T14:27:28.357Z | Q76: Tolerance: ±2 bps (±4 for Mayan: Dutch-auction pricing and 2–4 dp display). Assumption set by the analyst.
A77: ETH → SOL | B77: 1 | C77: Skip Go | D77: 99.68794 | F77: 99.72581 | H77: =IF(ISNUMBER(F77),F77-N(G77),"") | I77: =IF(AND(ISNUMBER(D77),ISNUMBER(H77)),(D77-H77)/100*10000,"") | J77: 0.05 | K77: =IF(ISNUMBER(I77),I77+N(J77)/100*10000,"") | L77: 0.002 | N77: 2026-09-23T14:19:28.697Z | O77: 2026-09-23T14:19:28.699Z
A78: ETH → SOL | B78: 2 | C78: Skip Go | D78: 99.68794 | F78: 99.72581 | H78: =IF(ISNUMBER(F78),F78-N(G78),"") | I78: =IF(AND(ISNUMBER(D78),ISNUMBER(H78)),(D78-H78)/100*10000,"") | J78: 0.05 | K78: =IF(ISNUMBER(I78),I78+N(J78)/100*10000,"") | L78: 0.001 | N78: 2026-09-23T14:23:47.144Z | O78: 2026-09-23T14:23:47.145Z
A79: ETH → SOL | B79: 3 | C79: Skip Go | D79: 99.69 | F79: 99.72787 | H79: =IF(ISNUMBER(F79),F79-N(G79),"") | I79: =IF(AND(ISNUMBER(D79),ISNUMBER(H79)),(D79-H79)/100*10000,"") | J79: 0.05 | K79: =IF(ISNUMBER(I79),I79+N(J79)/100*10000,"") | L79: 0.001 | N79: 2026-09-23T14:27:28.356Z | O79: 2026-09-23T14:27:28.357Z
A80: ETH → SOL | B80: 1 | C80: Symbiosis | D80: 98.950473 | F80: 98.950473 | H80: =IF(ISNUMBER(F80),F80-N(G80),"") | I80: =IF(AND(ISNUMBER(D80),ISNUMBER(H80)),(D80-H80)/100*10000,"") | J80: 0.05 | K80: =IF(ISNUMBER(I80),I80+N(J80)/100*10000,"") | L80: 0.003 | N80: 2026-09-23T14:19:28.697Z | O80: 2026-09-23T14:19:28.700Z
A81: ETH → SOL | B81: 2 | C81: Symbiosis | D81: 98.951612 | F81: 98.951612 | H81: =IF(ISNUMBER(F81),F81-N(G81),"") | I81: =IF(AND(ISNUMBER(D81),ISNUMBER(H81)),(D81-H81)/100*10000,"") | J81: 0.05 | K81: =IF(ISNUMBER(I81),I81+N(J81)/100*10000,"") | L81: 0 | N81: 2026-09-23T14:23:47.144Z | O81: 2026-09-23T14:23:47.144Z
A82: ETH → SOL | B82: 3 | C82: Symbiosis | D82: 98.95137 | F82: 98.95137 | H82: =IF(ISNUMBER(F82),F82-N(G82),"") | I82: =IF(AND(ISNUMBER(D82),ISNUMBER(H82)),(D82-H82)/100*10000,"") | J82: 0.05 | K82: =IF(ISNUMBER(I82),I82+N(J82)/100*10000,"") | L82: 0.001 | N82: 2026-09-23T14:27:28.356Z | O82: 2026-09-23T14:27:28.357Z
A83: SOL → BSC | B83: 1 | C83: Relay | D83: 99.598071 | F83: 99.651304 | H83: =IF(ISNUMBER(F83),F83-N(G83),"") | I83: =IF(AND(ISNUMBER(D83),ISNUMBER(H83)),(D83-H83)/100*10000,"") | J83: 0.05 | K83: =IF(ISNUMBER(I83),I83+N(J83)/100*10000,"") | L83: 0.001 | N83: 2026-09-23T14:19:58.625Z | O83: 2026-09-23T14:19:58.626Z
A84: SOL → BSC | B84: 2 | C84: Relay | D84: 99.58515 | F84: 99.640814 | H84: =IF(ISNUMBER(F84),F84-N(G84),"") | I84: =IF(AND(ISNUMBER(D84),ISNUMBER(H84)),(D84-H84)/100*10000,"") | J84: 0.05 | K84: =IF(ISNUMBER(I84),I84+N(J84)/100*10000,"") | L84: 0.001 | N84: 2026-09-23T14:24:42.081Z | O84: 2026-09-23T14:24:42.080Z
A85: SOL → BSC | B85: 3 | C85: Relay | D85: 99.589005 | F85: 99.63692 | H85: =IF(ISNUMBER(F85),F85-N(G85),"") | I85: =IF(AND(ISNUMBER(D85),ISNUMBER(H85)),(D85-H85)/100*10000,"") | J85: 0.05 | K85: =IF(ISNUMBER(I85),I85+N(J85)/100*10000,"") | L85: 0.001 | N85: 2026-09-23T14:28:40.088Z | O85: 2026-09-23T14:28:40.087Z
A86: SOL → BSC | B86: 1 | C86: deBridge | D86: 98.675519 | F86: 99.920015 | G86: 1.2455 | H86: =IF(ISNUMBER(F86),F86-N(G86),"") | I86: =IF(AND(ISNUMBER(D86),ISNUMBER(H86)),(D86-H86)/100*10000,"") | J86: 0.05 | K86: =IF(ISNUMBER(I86),I86+N(J86)/100*10000,"") | L86: 0.001 | M86: +1.2455 USDC charged on top of 100 input (subtracted) | N86: 2026-09-23T14:19:58.625Z | O86: 2026-09-23T14:19:58.626Z
A87: SOL → BSC | B87: 2 | C87: deBridge | D87: 98.685318 | F87: 99.920015 | G87: 1.2357 | H87: =IF(ISNUMBER(F87),F87-N(G87),"") | I87: =IF(AND(ISNUMBER(D87),ISNUMBER(H87)),(D87-H87)/100*10000,"") | J87: 0.05 | K87: =IF(ISNUMBER(I87),I87+N(J87)/100*10000,"") | L87: 0.001 | M87: +1.2357 USDC charged on top of 100 input (subtracted) | N87: 2026-09-23T14:24:42.081Z | O87: 2026-09-23T14:24:42.080Z
A88: SOL → BSC | B88: 3 | C88: deBridge | D88: 98.683938 | F88: 99.920016 | G88: 1.2371 | H88: =IF(ISNUMBER(F88),F88-N(G88),"") | I88: =IF(AND(ISNUMBER(D88),ISNUMBER(H88)),(D88-H88)/100*10000,"") | J88: 0.05 | K88: =IF(ISNUMBER(I88),I88+N(J88)/100*10000,"") | L88: 0.002 | M88: +1.2371 USDC charged on top of 100 input (subtracted) | N88: 2026-09-23T14:28:40.088Z | O88: 2026-09-23T14:28:40.086Z
A89: SOL → BSC | B89: 1 | C89: LI.FI (Jumper) | D89: 99.178482 | F89: 99.93159 | H89: =IF(ISNUMBER(F89),F89-N(G89),"") | I89: =IF(AND(ISNUMBER(D89),ISNUMBER(H89)),(D89-H89)/100*10000,"") | J89: 0.05 | K89: =IF(ISNUMBER(I89),I89+N(J89)/100*10000,"") | L89: 0.002 | M89: Jumper Best Return via Mayan (Swift); max route 99.93159 | N89: 2026-09-23T14:19:58.625Z | O89: 2026-09-23T14:19:58.623Z
A90: SOL → BSC | B90: 2 | C90: LI.FI (Jumper) | D90: 99.178502 | F90: 99.93159 | H90: =IF(ISNUMBER(F90),F90-N(G90),"") | I90: =IF(AND(ISNUMBER(D90),ISNUMBER(H90)),(D90-H90)/100*10000,"") | J90: 0.05 | K90: =IF(ISNUMBER(I90),I90+N(J90)/100*10000,"") | L90: 0.004 | M90: Jumper Best Return via Mayan (Swift); max route 99.93159 | N90: 2026-09-23T14:24:42.081Z | O90: 2026-09-23T14:24:42.077Z
A91: SOL → BSC | B91: 3 | C91: LI.FI (Jumper) | D91: 99.228124 | F91: 99.931599 | H91: =IF(ISNUMBER(F91),F91-N(G91),"") | I91: =IF(AND(ISNUMBER(D91),ISNUMBER(H91)),(D91-H91)/100*10000,"") | J91: 0.05 | K91: =IF(ISNUMBER(I91),I91+N(J91)/100*10000,"") | L91: 0.003 | M91: Jumper Best Return via Mayan (Swift); max route 99.931599 | N91: 2026-09-23T14:28:40.088Z | O91: 2026-09-23T14:28:40.091Z
A92: SOL → BSC | B92: 1 | C92: Across | D92: not listed | F92: 99.981745 | H92: =IF(ISNUMBER(F92),F92-N(G92),"") | I92: =IF(AND(ISNUMBER(D92),ISNUMBER(H92)),(D92-H92)/100*10000,"") | J92: 0.05 | K92: =IF(ISNUMBER(I92),I92+N(J92)/100*10000,"") | L92: 0.001 | N92: 2026-09-23T14:19:58.625Z | O92: 2026-09-23T14:19:58.624Z
A93: SOL → BSC | B93: 2 | C93: Across | D93: not listed | F93: 99.982214 | H93: =IF(ISNUMBER(F93),F93-N(G93),"") | I93: =IF(AND(ISNUMBER(D93),ISNUMBER(H93)),(D93-H93)/100*10000,"") | J93: 0.05 | K93: =IF(ISNUMBER(I93),I93+N(J93)/100*10000,"") | L93: 0.002 | N93: 2026-09-23T14:24:42.081Z | O93: 2026-09-23T14:24:42.079Z
A94: SOL → BSC | B94: 3 | C94: Across | D94: not listed | F94: 99.972498 | H94: =IF(ISNUMBER(F94),F94-N(G94),"") | I94: =IF(AND(ISNUMBER(D94),ISNUMBER(H94)),(D94-H94)/100*10000,"") | J94: 0.05 | K94: =IF(ISNUMBER(I94),I94+N(J94)/100*10000,"") | L94: 0.003 | N94: 2026-09-23T14:28:40.088Z | O94: 2026-09-23T14:28:40.085Z
A95: SOL → BSC | B95: 1 | C95: Mayan | D95: 99.881626 | E95: yes | F95: 99.931 | H95: =IF(ISNUMBER(F95),F95-N(G95),"") | I95: =IF(AND(ISNUMBER(D95),ISNUMBER(H95)),(D95-H95)/100*10000,"") | J95: 0.05 | K95: =IF(ISNUMBER(I95),I95+N(J95)/100*10000,"") | L95: 0.001 | M95: Swift v2; UI shows 3 dp | N95: 2026-09-23T14:19:58.625Z | O95: 2026-09-23T14:19:58.624Z
A96: SOL → BSC | B96: 2 | C96: Mayan | D96: 99.881595 | E96: yes | F96: 99.931 | H96: =IF(ISNUMBER(F96),F96-N(G96),"") | I96: =IF(AND(ISNUMBER(D96),ISNUMBER(H96)),(D96-H96)/100*10000,"") | J96: 0.05 | K96: =IF(ISNUMBER(I96),I96+N(J96)/100*10000,"") | L96: 0.002 | M96: Swift v2; UI shows 3 dp | N96: 2026-09-23T14:24:42.081Z | O96: 2026-09-23T14:24:42.079Z
A97: SOL → BSC | B97: 3 | C97: Mayan | D97: 99.881629 | E97: yes | F97: 99.931 | H97: =IF(ISNUMBER(F97),F97-N(G97),"") | I97: =IF(AND(ISNUMBER(D97),ISNUMBER(H97)),(D97-H97)/100*10000,"") | J97: 0.05 | K97: =IF(ISNUMBER(I97),I97+N(J97)/100*10000,"") | L97: 0.004 | M97: Swift v2; UI shows 3 dp | N97: 2026-09-23T14:28:40.088Z | O97: 2026-09-23T14:28:40.084Z
A98: SOL → BSC | B98: 1 | C98: Husher | D98: 99.7501 | F98: 99.65 | H98: =IF(ISNUMBER(F98),F98-N(G98),"") | I98: =IF(AND(ISNUMBER(D98),ISNUMBER(H98)),(D98-H98)/100*10000,"") | J98: 0.05 | K98: =IF(ISNUMBER(I98),I98+N(J98)/100*10000,"") | L98: 0.001 | N98: 2026-09-23T14:19:58.625Z | O98: 2026-09-23T14:19:58.624Z
A99: SOL → BSC | B99: 2 | C99: Husher | D99: 99.7501 | F99: 99.65 | H99: =IF(ISNUMBER(F99),F99-N(G99),"") | I99: =IF(AND(ISNUMBER(D99),ISNUMBER(H99)),(D99-H99)/100*10000,"") | J99: 0.05 | K99: =IF(ISNUMBER(I99),I99+N(J99)/100*10000,"") | L99: 0.003 | N99: 2026-09-23T14:24:42.081Z | O99: 2026-09-23T14:24:42.078Z
A100: SOL → BSC | B100: 3 | C100: Husher | D100: 99.7501 | F100: 99.65 | H100: =IF(ISNUMBER(F100),F100-N(G100),"") | I100: =IF(AND(ISNUMBER(D100),ISNUMBER(H100)),(D100-H100)/100*10000,"") | J100: 0.05 | K100: =IF(ISNUMBER(I100),I100+N(J100)/100*10000,"") | L100: 0.004 | N100: 2026-09-23T14:28:40.088Z | O100: 2026-09-23T14:28:40.084Z
A101: SOL → BSC | B101: 1 | C101: Layerswap | D101: 99.678465 | F101: 99.863113 | H101: =IF(ISNUMBER(F101),F101-N(G101),"") | I101: =IF(AND(ISNUMBER(D101),ISNUMBER(H101)),(D101-H101)/100*10000,"") | J101: 0.05 | K101: =IF(ISNUMBER(I101),I101+N(J101)/100*10000,"") | L101: 0.001 | N101: 2026-09-23T14:19:58.625Z | O101: 2026-09-23T14:19:58.626Z
...

Sheet Receipts
A1: Route | B1: Sample | C1: Site | D1: requestStart (UTC) | E1: quoteVisible (UTC) | F1: screenshotAt (UTC) | G1: Δ vs Bridg (s) | H1: Out (USDC) | I1: Crop screenshot | J1: Crop SHA-256 | K1: Full-page screenshot | L1: Full SHA-256 | M1: Value read at (UTC)
A2: SOL → ETH | B2: 1 | C2: Bridg | D2: 2026-09-23T14:18:34.538Z | E2: 2026-09-23T14:18:36.899Z | F2: 2026-09-23T14:18:55.437Z | H2: 99.840015 | I2: open | J2: 1c04bb2637b883df092fb8fc0bf21f8b2a417a4fe6cb1c35cf57dd41b1674ed1 | K2: open | L2: b8e886031f8e7dc0f7e271c0c4b995766415903eb560758b5cd86542849b6846 | M2: 2026-09-23T14:18:55.406Z
A3: SOL → ETH | B3: 1 | C3: OpenSea | D3: 2026-09-23T14:18:34.664Z | E3: 2026-09-23T14:18:39.130Z | F3: 2026-09-23T14:18:55.428Z | G3: 0.001 | H3: 98.9896 | I3: open | J3: 028c8eb236afdab32cdb8aa7e24d1d94502b317224c98d1c5d45d720823592c5 | K3: open | L3: f56b169b989a9e1278d82d4554310faeb7f05fa13208f92f38b42777524ba54e | M3: 2026-09-23T14:18:55.405Z
A4: SOL → ETH | B4: 1 | C4: Relay | D4: 2026-09-23T14:18:34.535Z | E4: 2026-09-23T14:18:38.436Z | F4: 2026-09-23T14:18:55.426Z | G4: 0.002 | H4: 99.193956 | I4: open | J4: 4e21b33b73f8b1aab58f58e6dce4ab15b3ca51e2b198f34e0f4a279bf159e7ea | K4: open | L4: 92e185a087b1d7b159c9b84b4055fa8cdb2cc27016ca2d970dfe2aba93525df3 | M4: 2026-09-23T14:18:55.404Z
A5: SOL → ETH | B5: 1 | C5: deBridge | D5: 2026-09-23T14:18:34.531Z | E5: 2026-09-23T14:18:37.964Z | F5: 2026-09-23T14:18:55.424Z | G5: 0.004 | H5: 99.920018 | I5: open | J5: bfac4526c6b3207aea9ede8ae50f4229f4a38194f73bad7e33a73662af8e727c | K5: open | L5: c4050321f2ca32ae8bc24515ec7dee4854c16b1b50cef568c0aa399e4bf9b4c9 | M5: 2026-09-23T14:18:55.402Z
A6: SOL → ETH | B6: 1 | C6: LI.FI (Jumper) | D6: 2026-09-23T14:18:34.668Z | E6: 2026-09-23T14:18:53.254Z | F6: 2026-09-23T14:18:55.407Z | G6: 0.006 | H6: 99.193956 | I6: open | J6: 3804d3737b919ec5594495a1f2eef99fd0bf181c1409fa89343d15a5c0a30571 | K6: open | L6: 8970de8e1b4d10819a38835351c31f14cdb97dbfd66726521d990e1bdc6ebb0c | M6: 2026-09-23T14:18:55.400Z
A7: SOL → ETH | B7: 1 | C7: Across | D7: 2026-09-23T14:18:34.512Z | E7: 2026-09-23T14:18:37.143Z | F7: 2026-09-23T14:18:55.411Z | G7: 0.006 | H7: 99.99 | I7: open | J7: 079f39c069db892cefb93c29aebe39e0961e23ea3c1801ef3a897f0ec7659aaf | K7: open | L7: 3f37293ed5439a5f7989a54594638125ea670606664a9d9bd7d89a83c567f68b | M7: 2026-09-23T14:18:55.400Z
A8: SOL → ETH | B8: 1 | C8: Mayan | D8: 2026-09-23T14:18:34.511Z | E8: 2026-09-23T14:18:37.365Z | F8: 2026-09-23T14:18:55.411Z | G8: 0.006 | H8: 96.6446 | I8: open | J8: 808f897bc406d06b4abb5b7a7082546abef1a7a73e30895a48679aeadb4f8466 | K8: open | L8: 23e15ba35c0540aa3e78383986b37a39e3fbe05b29ebe25c22069313a258f0af | M8: 2026-09-23T14:18:55.400Z
A9: SOL → ETH | B9: 1 | C9: Allbridge Core | D9: 2026-09-23T14:18:34.659Z | E9: 2026-09-23T14:18:37.676Z | F9: 2026-09-23T14:18:55.590Z | G9: 0.005 | H9: 99.9 | I9: open | J9: 7dd0abcdc33a99af2e60dedf2abc525ed94624d098c017a65111c43c52984f7d | K9: open | L9: 1f2bce1774b7cdd8519193cafc0485c52a828ed097cc9fea52ab292f5010f655 | M9: 2026-09-23T14:18:55.401Z
A10: SOL → ETH | B10: 1 | C10: CCTP (via Portal) | D10: 2026-09-23T14:18:34.656Z | E10: 2026-09-23T14:18:40.048Z | F10: 2026-09-23T14:18:55.437Z | G10: 0 | H10: 99.99 | I10: open | J10: 07a9954726fefe67ad94114f248a413a02f6a2d4639a74c0f9a1a773d2c7d9ff | K10: open | L10: 6a2c09e5a9da8130387feb21e17f656d147cf22da31c26e113b978406ff20908 | M10: 2026-09-23T14:18:55.406Z
A11: SOL → ETH | B11: 1 | C11: Husher | D11: 2026-09-23T14:18:34.669Z | E11: 2026-09-23T14:18:37.420Z | F11: 2026-09-23T14:18:55.425Z | G11: 0.005 | H11: 99.05 | I11: open | J11: 04b61ebaad3eb4aec183f4c45f9c54147bac53e6b3e642d21ce227c340559133 | K11: open | L11: 131dbc7318300afe669b3f31f6f3ea3f5fa3f6be5c2012c6819a9dfbaebc288e | M11: 2026-09-23T14:18:55.401Z
A12: SOL → ETH | B12: 1 | C12: Layerswap | D12: 2026-09-23T14:18:34.512Z | E12: 2026-09-23T14:18:38.407Z | F12: 2026-09-23T14:18:55.429Z | G12: 0.004 | H12: 99.716863 | I12: open | J12: db055a5e08d9f00ab1ddd26dbb0d5c9b47f77c4e19d0440ca7a52b30a66cd734 | K12: open | L12: 1c1b347da052b2608118a5ea989d55aaa1e6e2f3659a9d14278a89a5b0f8e63a | M12: 2026-09-23T14:18:55.402Z
A13: SOL → ETH | B13: 1 | C13: Meson | D13: 2026-09-23T14:18:34.698Z | E13: 2026-09-23T14:18:36.601Z | F13: 2026-09-23T14:18:55.413Z | G13: 0.006 | H13: 98.65 | I13: open | J13: fef2afd1f0c7e51e942fe3e75622f415d2310c1dd2458ffa07eb0392070ca505 | K13: open | L13: 10865867f536ddb309c441413187d93fd0c22f1ebbb4e50d5548171140aaf7d7 | M13: 2026-09-23T14:18:55.400Z
A14: SOL → ETH | B14: 1 | C14: SimpleSwap | D14: 2026-09-23T14:18:34.669Z | E14: 2026-09-23T14:18:39.168Z | F14: 2026-09-23T14:18:55.490Z | G14: 0.001 | H14: 98.206302 | I14: open | J14: dd386279bf1eadaeedf5c9f8289bcd72c2d988fb7aa06f225e5c52617855105d | K14: open | L14: 0b4e15a485095d01a8f2daede3a6dc94cc9678d1794f98094c007913a87b2dfe | M14: 2026-09-23T14:18:55.405Z
... A16: SOL → ETH | B16: 1 | C16: Symbiosis | D16: 2026-09-23T14:18:34.533Z | E16: 2026-09-23T14:18:39.114Z | F16: 2026-09-23T14:18:55.435Z | G16: 0.002 | H16: 96.860997 | I16: open | J16: ceb5d9f2785e1e2868ce3c0df2854429eac0fe84062ae63650e426de2323c7a0 | K16: open | L16: 5098301347b8364a41c4d2c9ddf3258879dd751ff1754774cb64450920167419 | M16: 2026-09-23T14:18:55.404Z
A17: SOL → ETH | B17: 2 | C17: Bridg | D17: 2026-09-23T14:22:16.319Z | E17: 2026-09-23T14:22:17.847Z | F17: 2026-09-23T14:22:28.676Z | H17: 99.840015 | I17: open | J17: fed74dd93bb0785a62f6414ae7b71d7abdc3d67548ff7687d0ce46245ae8edc5 | K17: open | L17: ca62bdce3fbce4bb645f1c51ce9aa7329f7c6e0794b135be87e922394f252765 | M17: 2026-09-23T14:22:28.648Z
A18: SOL → ETH | B18: 2 | C18: OpenSea | D18: 2026-09-23T14:22:16.319Z | E18: 2026-09-23T14:22:22.327Z | F18: 2026-09-23T14:22:31.668Z | G18: 0.008 | H18: 98.7874 | I18: open | J18: ec2b239c0651cce2c3ffe8d3d5e0052118203848c52a4f564164d2dc65e6b58d | K18: open | L18: 5ff8a5a3761b2eacb3924219a7ce9031a90d4e4c4d274fd7d13265cb651b2a25 | M18: 2026-09-23T14:22:28.640Z
A19: SOL → ETH | B19: 2 | C19: Relay | D19: 2026-09-23T14:22:16.318Z | E19: 2026-09-23T14:22:18.601Z | F19: 2026-09-23T14:22:28.670Z | G19: 0.003 | H19: 99.087326 | I19: open | J19: 8f6a01719b30adcf84d7ff6ffe129566e9a71b1bff53cd821dfb7e8a714469f6 | K19: open | L19: 1ef094fe5f9d70d57be2cec9dfa220503ed3872de9ee9cbb6ec588884f5755e8 | M19: 2026-09-23T14:22:28.645Z
A20: SOL → ETH | B20: 2 | C20: deBridge | D20: 2026-09-23T14:22:16.317Z | E20: 2026-09-23T14:22:18.511Z | F20: 2026-09-23T14:22:28.671Z | G20: 0.002 | H20: 99.920018 | I20: open | J20: c56b67440a971294f8e8005eae8dff1d25ecdf02d978737bb03d6417230d2148 | K20: open | L20: 257d4304bc290620a334e8025e85ba2504c365f3c0a6625ef7bedd7e9ebb9428 | M20: 2026-09-23T14:22:28.646Z
A21: SOL → ETH | B21: 2 | C21: LI.FI (Jumper) | D21: 2026-09-23T14:22:16.319Z | E21: 2026-09-23T14:22:20.712Z | F21: 2026-09-23T14:22:28.663Z | G21: 0.002 | H21: 99.087326 | I21: open | J21: ec90fbfd86c6a6bccaab1f1daf97f9f0fc0afb094e8b60167d2f90304fb825ca | K21: open | L21: 48563c281d35b94effcea0906f3e383b8c0a444f62329bfbf366f6e68e29825d | M21: 2026-09-23T14:22:28.650Z
A22: SOL → ETH | B22: 2 | C22: Across | D22: 2026-09-23T14:22:16.318Z | E22: 2026-09-23T14:22:18.203Z | F22: 2026-09-23T14:22:28.652Z | G22: 0.004 | H22: 99.99 | I22: open | J22: e6f06d5292a44e04191cf1a6faf1383ff60916079761425e4577a51dbe35feb5 | K22: open | L22: f9d6a4b054ca69515d6b77ed37042575d320a376181efa0e00165c10f40afe4c | M22: 2026-09-23T14:22:28.644Z
A23: SOL → ETH | B23: 2 | C23: Mayan | D23: 2026-09-23T14:22:16.315Z | E23: 2026-09-23T14:22:17.685Z | F23: 2026-09-23T14:22:28.652Z | G23: 0.005 | H23: 96.6844 | I23: open | J23: 77552eae0d731101f37d0873967d4509f810c1b7e6c6a512147e5d3a1f232a6d | K23: open | L23: 3d8b84640ae50f6da62b85381531125aff1f727896375fa467c75746dff6da8f | M23: 2026-09-23T14:22:28.643Z
A24: SOL → ETH | B24: 2 | C24: Allbridge Core | D24: 2026-09-23T14:22:16.319Z | E24: 2026-09-23T14:22:18.086Z | F24: 2026-09-23T14:22:28.838Z | G24: 0.004 | H24: 99.9 | I24: open | J24: 8ee3605d7e6a0cdcf169082dbd3f4307819b525b862ea32969ab905f1344218a | K24: open | L24: 6181e3bc8e8e33ca1e6e2b9d92e9c5d9c687f3c51dd11583e985bf75007decd4 | M24: 2026-09-23T14:22:28.644Z
A25: SOL → ETH | B25: 2 | C25: CCTP (via Portal) | D25: 2026-09-23T14:22:16.318Z | E25: 2026-09-23T14:22:20.102Z | F25: 2026-09-23T14:22:28.681Z | G25: 0.001 | H25: 99.99 | I25: open | J25: 07a9954726fefe67ad94114f248a413a02f6a2d4639a74c0f9a1a773d2c7d9ff | K25: open | L25: bfa8e8753c333b98df11083c9013a1b9a53dc4a8072d7eb3b4ca75443296d7f8 | M25: 2026-09-23T14:22:28.649Z
A26: SOL → ETH | B26: 2 | C26: Husher | D26: 2026-09-23T14:22:16.320Z | E26: 2026-09-23T14:22:18.196Z | F26: 2026-09-23T14:22:28.667Z | G26: 0.005 | H26: 99.05 | I26: open | J26: 31acc4593baef971c8f99b51f95ee767bc94c47d932ff784a3e43fa8fe227b04 | K26: open | L26: c33f2f03f701674d43eb7497f660b2435e5c31e9a03130764d01babc91caa008 | M26: 2026-09-23T14:22:28.643Z
A27: SOL → ETH | B27: 2 | C27: Layerswap | D27: 2026-09-23T14:22:16.316Z | E27: 2026-09-23T14:22:18.642Z | F27: 2026-09-23T14:22:28.675Z | G27: 0.002 | H27: 99.717755 | I27: open | J27: abcb60421a2977358508d9f7ae32f1b80f639ce3073d3b9baac8120367d45e50 | K27: open | L27: 0fb602fcf565abbfda7f02949d99dcb5c3ad4822c820139f4554de1c02776805 | M27: 2026-09-23T14:22:28.646Z
A28: SOL → ETH | B28: 2 | C28: Meson | D28: 2026-09-23T14:22:16.320Z | E28: 2026-09-23T14:22:17.212Z | F28: 2026-09-23T14:22:28.653Z | G28: 0.006 | H28: 98.37 | I28: open | J28: cd372226edd5d1ba5c7f71f5bc4982ef67717e59939e13e6d6f299f2b1ae155c | K28: open | L28: c0a73d09d6913ec6c9e6a082dbe4ed00f848e7044a4ebdce7040a5ae56abd515 | M28: 2026-09-23T14:22:28.642Z
A29: SOL → ETH | B29: 2 | C29: SimpleSwap | D29: 2026-09-23T14:22:16.320Z | E29: 2026-09-23T14:22:19.635Z | F29: 2026-09-23T14:22:28.754Z | G29: 0.002 | H29: 98.205703 | I29: open | J29: ad1c37cbf51f469710896708bed00164509b9ffc854f23a48b0953eb7fff01fd | K29: open | L29: 245e0301ec87bba8d8b764b98f2e30dc22c67514767484f2b513d85e03f494ce | M29: 2026-09-23T14:22:28.646Z
... A31: SOL → ETH | B31: 2 | C31: Symbiosis | D31: 2026-09-23T14:22:16.317Z | E31: 2026-09-23T14:22:20.005Z | F31: 2026-09-23T14:22:28.679Z | G31: 0.001 | H31: 96.3787 | I31: open | J31: b47cd864a0ea1839dbe3490a7fc328b80d48efd62152c39ea3d9483bca7c472b | K31: open | L31: 32ef70e035351f2df5a08164028789eef79e073594305be59574859ba8c66b97 | M31: 2026-09-23T14:22:28.649Z
A32: SOL → ETH | B32: 3 | C32: Bridg | D32: 2026-09-23T14:26:48.253Z | E32: 2026-09-23T14:26:49.452Z | F32: 2026-09-23T14:26:54.615Z | H32: 99.840015 | I32: open | J32: d4854fb7708c2c4a2010a189bc40fffee8609f6ed40d444335fde928c5b30ddb | K32: open | L32: cd2e6190a8db44b83732e08b2824e5db51050794d9f0dec331f1d6ee99bb6335 | M32: 2026-09-23T14:26:54.591Z
A33: SOL → ETH | B33: 3 | C33: OpenSea | D33: 2026-09-23T14:26:48.252Z | E33: 2026-09-23T14:26:51.825Z | F33: 2026-09-23T14:26:54.622Z | G33: 0.002 | H33: 99.067 | I33: open | J33: b4d9dba9cf7528b9d4c4655d77ca541a690d920da635c903c186451aa85f3321 | K33: open | L33: 2cd03342c38ad7583ac5ba80c29b12b38057abb158e1124d81335e7797b70ffe | M33: 2026-09-23T14:26:54.593Z
A34: SOL → ETH | B34: 3 | C34: Relay | D34: 2026-09-23T14:26:48.252Z | E34: 2026-09-23T14:26:50.584Z | F34: 2026-09-23T14:26:54.609Z | G34: 0.002 | H34: 99.260036 | I34: open | J34: f37a115b11e80ed858bca6ed342ff2254f5694989bfa5fa59e9e813db3112c1b | K34: open | L34: ecbe1d753dbbd230309fe34054d4e523190909ff7a916b841b750a76481ad8d7 | M34: 2026-09-23T14:26:54.589Z
A35: SOL → ETH | B35: 3 | C35: deBridge | D35: 2026-09-23T14:26:48.253Z | E35: 2026-09-23T14:26:51.726Z | F35: 2026-09-23T14:26:54.621Z | G35: 0.002 | H35: 99.880033 | I35: open | J35: 83ca3c668a8d529265819fe1c2ea5a527cb3e0f9151c66963ed2cc42a5bc9253 | K35: open | L35: 7b8936b0a4688dcd49d821aab22fbc7d4f658c8e3c7a87764f19d58fc8001619 | M35: 2026-09-23T14:26:54.593Z
A36: SOL → ETH | B36: 3 | C36: LI.FI (Jumper) | D36: 2026-09-23T14:26:48.255Z | E36: 2026-09-23T14:26:51.678Z | F36: 2026-09-23T14:26:54.601Z | G36: 0 | H36: 99.260036 | I36: open | J36: 748f5117527e40427a24c4e3c197f851537058afa1e554a77cc0edd67ed2a431 | K36: open | L36: 07f40469404a634369fc988df5e607f42c79f833e82ec4a3b7b89857d7ceb136 | M36: 2026-09-23T14:26:54.591Z
A37: SOL → ETH | B37: 3 | C37: Across | D37: 2026-09-23T14:26:48.251Z | E37: 2026-09-23T14:26:50.556Z | F37: 2026-09-23T14:26:54.597Z | G37: 0.002 | H37: 99.99 | I37: open | J37: e6f06d5292a44e04191cf1a6faf1383ff60916079761425e4577a51dbe35feb5 | K37: open | L37: 3dbecb6a92714a6c80bf3798ae85a5a228d0ce5507a9f5b41d38ec40766ceb7a | M37: 2026-09-23T14:26:54.589Z
A38: SOL → ETH | B38: 3 | C38: Mayan | D38: 2026-09-23T14:26:48.251Z | E38: 2026-09-23T14:26:50.100Z | F38: 2026-09-23T14:26:54.596Z | G38: 0.003 | H38: 96.851 | I38: open | J38: 0813d60ce949293ebec8e5cadbecc82c982269fd84b91d4619b9ed32556cb738 | K38: open | L38: 9c6cf7523b4d72db5213cb377f6692a0ba2156734f21087510ea97b207629b6f | M38: 2026-09-23T14:26:54.588Z
A39: SOL → ETH | B39: 3 | C39: Allbridge Core | D39: 2026-09-23T14:26:48.257Z | E39: 2026-09-23T14:26:50.605Z | F39: 2026-09-23T14:26:55.854Z | G39: 0.001 | H39: 99.9 | I39: open | J39: 3fef2fb5b9fa2b66b14c58a263e56c006477bbb4d921bc2a413f7c5235a6d9d4 | K39: open | L39: bbc3eca5c0fe72164b4386e01b00d246545ca7ca0e43ca26abef9dd9a07d7a59 | M39: 2026-09-23T14:26:54.590Z
A40: SOL → ETH | B40: 3 | C40: CCTP (via Portal) | D40: 2026-09-23T14:26:48.253Z | E40: 2026-09-23T14:26:52.395Z | F40: 2026-09-23T14:26:54.607Z | G40: 0.003 | H40: 99.99 | I40: open | J40: 78e6b63937d00b725526d32b329e55207054bd599a82b3329323131d0f374add | K40: open | L40: 6c35669244ebe0201a5199bf8de14c630ae32d169a537f5b4dfee102c66c9c33 | M40: 2026-09-23T14:26:54.588Z
A41: SOL → ETH | B41: 3 | C41: Husher | D41: 2026-09-23T14:26:48.257Z | E41: 2026-09-23T14:26:50.583Z | F41: 2026-09-23T14:26:54.611Z | G41: 0.002 | H41: 99.05 | I41: open | J41: 24fb42eb90878b6f211cf1fc7f771a6eeb3699b076f5a30014219d11d804c936 | K41: open | L41: 0e27ac955165cfa897b7ef6b3b154c6d62c21b07e057f5950e1bf95a4ea57137 | M41: 2026-09-23T14:26:54.589Z
A42: SOL → ETH | B42: 3 | C42: Layerswap | D42: 2026-09-23T14:26:48.251Z | E42: 2026-09-23T14:26:51.705Z | F42: 2026-09-23T14:26:54.617Z | G42: 0.001 | H42: 99.706546 | I42: open | J42: 71445f71ea3fa83fad29b0ad4e2df73d18491d56512325efa106fd988a214caf | K42: open | L42: 382ca622bd0a1bd69000e9fdc6337bdf6c7b0973e4749440c33b756889b17987 | M42: 2026-09-23T14:26:54.592Z
A43: SOL → ETH | B43: 3 | C43: Meson | D43: 2026-09-23T14:26:48.257Z | E43: 2026-09-23T14:26:49.692Z | F43: 2026-09-23T14:26:54.595Z | G43: 0.003 | H43: 98.67 | I43: open | J43: 3a9de99e2623870060ff167ce4c7923f441280040ff306184e5a88f40140d5a3 | K43: open | L43: a85d452d583c3004a344c31ef9167965558861be6cee9ca352114d4a369fbd80 | M43: 2026-09-23T14:26:54.588Z
A44: SOL → ETH | B44: 3 | C44: SimpleSwap | D44: 2026-09-23T14:26:48.258Z | E44: 2026-09-23T14:26:52.307Z | F44: 2026-09-23T14:26:54.797Z | G44: 0.003 | H44: 98.205814 | I44: open | J44: 6d66195801b1eaae19341607756738bb85593fb6b2253a73bcd588b6d06efc24 | K44: open | L44: c0b63a8b68080e4d5818d90d2b5243058a84e8bb8338b589b64133002c26d8cd | M44: 2026-09-23T14:26:54.594Z
... A46: SOL → ETH | B46: 3 | C46: Symbiosis | D46: 2026-09-23T14:26:48.252Z | E46: 2026-09-23T14:26:51.709Z | F46: 2026-09-23T14:26:54.619Z | G46: 0 | H46: 96.510498 | I46: open | J46: bb812be023a43cca40cb153a0bb65c52fb895530e977a8c30084d08c24dadc25 | K46: open | L46: f985797a1ff30bdc9642641aa10b4f27735b041d5127ed4fca11f49c45af8952 | M46: 2026-09-23T14:26:54.591Z
A47: ETH → SOL | B47: 1 | C47: Bridg | D47: 2026-09-23T14:19:22.123Z | E47: 2026-09-23T14:19:23.634Z | F47: 2026-09-23T14:19:28.723Z | H47: 99.85005 | I47: open | J47: dcb530ba9a3ac4f519ff6ce5de81c27b289d192081a99f13e3aa4fb4b886be87 | K47: open | L47: df4eae8e94fbf12df53c2469199aa05fd1e29c0db0501950df1579215f73ebdd | M47: 2026-09-23T14:19:28.697Z
A48: ETH → SOL | B48: 1 | C48: OpenSea | D48: 2026-09-23T14:19:22.118Z | E48: 2026-09-23T14:19:25.252Z | F48: 2026-09-23T14:19:28.744Z | G48: 0.004 | H48: 99.7459 | I48: open | J48: 45fe5e0bc24ec949ca2b99fa2bc3a334fed15f75ed2fde5350872ab01c120753 | K48: open | L48: 929d8e03860056bbf334fa8991944ac32c8988002d466b288f67616f7f40dcc4 | M48: 2026-09-23T14:19:28.701Z
A49: ETH → SOL | B49: 1 | C49: Relay | D49: 2026-09-23T14:19:22.117Z | E49: 2026-09-23T14:19:24.093Z | F49: 2026-09-23T14:19:28.731Z | G49: 0.001 | H49: 99.945703 | I49: open | J49: b75a59d963bc05cdf2fa22e4477a4bfbff5581b3dac96e86fc6970df8e89eec2 | K49: open | L49: 7612fc6bffd8ca61cbbde8900581affbb2df318c4f5db788eb2e685ba8e52054 | M49: 2026-09-23T14:19:28.698Z
A50: ETH → SOL | B50: 1 | C50: deBridge | D50: 2026-09-23T14:19:22.120Z | E50: 2026-09-23T14:19:24.092Z | F50: 2026-09-23T14:19:28.731Z | G50: 0.001 | H50: 99.920018 | I50: open | J50: 25b3e9ec03cd3ef3697581fc28d2cad0efb5e4959945c3602c5f593bba2b9960 | K50: open | L50: 92727bd7c0c08bc352be06936e8830b74987489865331e4626433f0a8541f3a7 | M50: 2026-09-23T14:19:28.698Z
A51: ETH → SOL | B51: 1 | C51: LI.FI (Jumper) | D51: 2026-09-23T14:19:22.121Z | E51: 2026-09-23T14:19:24.437Z | F51: 2026-09-23T14:19:28.709Z | G51: 0.001 | H51: 99.945703 | I51: open | J51: 7151b45e72e3d7010af0b7dd9d7de30e7d2605f46a0f180f65d66183535927d2 | K51: open | L51: bbf79df2968f98b1868104fde3fd0c20130ff6d7c1a41fe79059dfcb0fd05cfa | M51: 2026-09-23T14:19:28.698Z
A52: ETH → SOL | B52: 1 | C52: Across | D52: 2026-09-23T14:19:22.117Z | E52: 2026-09-23T14:19:23.610Z | F52: 2026-09-23T14:19:28.705Z | G52: 0 | H52: 99.99 | I52: open | J52: 5c222636d245f05df7db78ce841b96079b9465c4ecd24e04168f55e76c12feb7 | K52: open | L52: aaeef70dc3c9c3be6b5a28a085a7f612ac747cddf83c32f74047344c0a4e48be | M52: 2026-09-23T14:19:28.697Z
A53: ETH → SOL | B53: 1 | C53: Mayan | D53: 2026-09-23T14:19:22.116Z | E53: 2026-09-23T14:19:23.870Z | F53: 2026-09-23T14:19:28.706Z | G53: 0.001 | H53: 99.0127 | I53: open | J53: 87f999fc629c39fdee114d730f644f084a431dc2731968c63a58af0596752d8c | K53: open | L53: 258492e94e1735ffe95a45026a1cac08e6bda861072cf87c6d23aaa2185893ea | M53: 2026-09-23T14:19:28.698Z
A54: ETH → SOL | B54: 1 | C54: Allbridge Core | D54: 2026-09-23T14:19:22.124Z | E54: 2026-09-23T14:19:23.598Z | F54: 2026-09-23T14:19:29.622Z | G54: 0 | H54: 99.9 | I54: open | J54: de0eba51e97690902c2383bcb28be6625a0ef6a0cf325dfd4f00947cc4000e97 | K54: open | L54: 50f0df2fc68990ff676e46f804967e345113e05a5cb67521210acf874ffa2c14 | M54: 2026-09-23T14:19:28.697Z
A55: ETH → SOL | B55: 1 | C55: CCTP (via Portal) | D55: 2026-09-23T14:19:22.124Z | E55: 2026-09-23T14:19:26.548Z | F55: 2026-09-23T14:19:28.714Z | G55: 0.001 | H55: 99.980001 | I55: open | J55: 43fc6f8aea5a0c478ff9c7e9f5cbe5a82b05fe7d4ce00546c77021994b9753a2 | K55: open | L55: 113fae78c6bf6f4efde50d1317eaec151c76cc78ca158b35d63636927247461e | M55: 2026-09-23T14:19:28.696Z
A56: ETH → SOL | B56: 1 | C56: Husher | D56: 2026-09-23T14:19:22.125Z | E56: 2026-09-23T14:19:23.515Z | F56: 2026-09-23T14:19:28.725Z | G56: 0.001 | H56: 99.35 | I56: open | J56: 30af934d5d36245f4d925f7e848ec40c62bf58f10ae7a3500563bcaf6f1b579b | K56: open | L56: 21a941857b83ffcb5cff936c47aa6eb22a9771f7a1cb7e8d3e6e38c4befcfb19 | M56: 2026-09-23T14:19:28.696Z
A57: ETH → SOL | B57: 1 | C57: Layerswap | D57: 2026-09-23T14:19:22.120Z | E57: 2026-09-23T14:19:24.571Z | F57: 2026-09-23T14:19:28.732Z | G57: 0.002 | H57: 99.681249 | I57: open | J57: c6dc1e888e5e17216016391f6ffac2365f2994525986bf74616585c8bbf47629 | K57: open | L57: dd95edf1d0682d0342a7d0076da5ead9db2fe94ad4e746faa0b8cbb45fef405e | M57: 2026-09-23T14:19:28.699Z
A58: ETH → SOL | B58: 1 | C58: Meson | D58: 2026-09-23T14:19:22.126Z | E58: 2026-09-23T14:19:22.766Z | F58: 2026-09-23T14:19:28.703Z | G58: 0.001 | H58: 99.1 | I58: open | J58: a8a32326d59c3d46f7fed55a3b4f39afd50c8a5e4c223a57b96e865e4185afcd | K58: open | L58: 86933ba30fc7eb25e9209c447ef1f9b764aab9698a037bb0b320efa737042eea | M58: 2026-09-23T14:19:28.696Z
A59: ETH → SOL | B59: 1 | C59: SimpleSwap | D59: 2026-09-23T14:19:22.126Z | E59: 2026-09-23T14:19:25.340Z | F59: 2026-09-23T14:19:28.872Z | G59: 0.005 | H59: 98.482157 | I59: open | J59: 31a289425ea9b8c02f7279976c7468d016c481b16fbfea61a450eeb213f726d0 | K59: open | L59: 828ef18ab70495437cccc10243a9b1a194f59e2ee3193001c812211a9d9b1fef | M59: 2026-09-23T14:19:28.702Z
... A61: ETH → SOL | B61: 1 | C61: Symbiosis | D61: 2026-09-23T14:19:22.119Z | E61: 2026-09-23T14:19:24.972Z | F61: 2026-09-23T14:19:28.738Z | G61: 0.003 | H61: 98.950473 | I61: open | J61: 46f1a0e0771cc03120f0692c61b5d1e2838d02f67ae81d62b9b444f47f09c97c | K61: open | L61: 078ec2ec8eec2c265964e65a7d790bb9786317357aed104a70e2864ef4e40dfa | M61: 2026-09-23T14:19:28.700Z
A62: ETH → SOL | B62: 2 | C62: Bridg | D62: 2026-09-23T14:23:01.562Z | E62: 2026-09-23T14:23:02.870Z | F62: 2026-09-23T14:23:47.173Z | H62: 99.85005 | I62: open | J62: 4419ae39e018bfc2ca92e1a83eefc6bb129d6d47ed201de4ee74edf5d4896031 | K62: open | L62: efaa8e90c9679981e6c7d97e1d3fe0fdb3ee26db9548d900a627c36bd74561db | M62: 2026-09-23T14:23:47.144Z
A63: ETH → SOL | B63: 2 | C63: OpenSea | D63: 2026-09-23T14:23:01.547Z | E63: 2026-09-23T14:23:04.895Z | F63: 2026-09-23T14:23:47.181Z | G63: 0.001 | H63: 99.7453 | I63: open | J63: 1a1489f5d0f95746f13cc458381e1dce24c2f9a4e65f4acb8d58a5d17b5f54e9 | K63: open | L63: 5b2dae5744dcee88cf717cafcf2caa631d31ad62fe51ef7052acb5a501238bc0 | M63: 2026-09-23T14:23:47.145Z
A64: ETH → SOL | B64: 2 | C64: Relay | D64: 2026-09-23T14:23:01.546Z | E64: 2026-09-23T14:23:03.598Z | F64: 2026-09-23T14:23:47.171Z | G64: 0.003 | H64: 99.945717 | I64: open | J64: e63ba230095881f9dd16152cc33c18484a4592273816a3a192b0bb534559be3c | K64: open | L64: 58da3db66f563a3610290780bf43c3ab57364e4ed4ecd19a3c973839108bf6a1 | M64: 2026-09-23T14:23:47.141Z
A65: ETH → SOL | B65: 2 | C65: deBridge | D65: 2026-09-23T14:23:01.551Z | E65: 2026-09-23T14:23:03.437Z | F65: 2026-09-23T14:23:47.165Z | G65: 0.004 | H65: 99.920018 | I65: open | J65: b2265aba761d7e3c62073bcd544a11999a2371098530decb8feb102dbd882f0e | K65: open | L65: 90c76abd2fc33bf030b7e6924bc7791e8053ee2cd00f062065f6ccfea4db29dc | M65: 2026-09-23T14:23:47.140Z
A66: ETH → SOL | B66: 2 | C66: LI.FI (Jumper) | D66: 2026-09-23T14:23:01.552Z | E66: 2026-09-23T14:23:04.129Z | F66: 2026-09-23T14:23:47.151Z | G66: 0.002 | H66: 99.945717 | I66: open | J66: a172a09f48d1648ac7b588426230c6886f72388ce9ea1a21d80290dd16aff0e2 | K66: open | L66: c8b6d48ce9c499398b39970383916108ce6147accf8ff218a9dffd2539ce447a | M66: 2026-09-23T14:23:47.142Z
A67: ETH → SOL | B67: 2 | C67: Across | D67: 2026-09-23T14:23:01.550Z | E67: 2026-09-23T14:23:02.967Z | F67: 2026-09-23T14:23:47.148Z | G67: 0.005 | H67: 99.99 | I67: open | J67: 5c222636d245f05df7db78ce841b96079b9465c4ecd24e04168f55e76c12feb7 | K67: open | L67: 26342dcf524325ebf00348fba56d32c89be32fc7c562654b0ef0adc127659e59 | M67: 2026-09-23T14:23:47.139Z
A68: ETH → SOL | B68: 2 | C68: Mayan | D68: 2026-09-23T14:23:01.545Z | E68: 2026-09-23T14:23:03.274Z | F68: 2026-09-23T14:23:47.149Z | G68: 0.004 | H68: 98.9619 | I68: open | J68: 421d48e99ff4688ab8b1cf5eb082b46dbe91a471f55c89fac37a9b25a6f1feda | K68: open | L68: c24c774107206c2102bd0dbf7280a3518f600a47d4e83c95b6b0aa43f45a29d9 | M68: 2026-09-23T14:23:47.140Z
A69: ETH → SOL | B69: 2 | C69: Allbridge Core | D69: 2026-09-23T14:23:01.563Z | E69: 2026-09-23T14:23:03.041Z | F69: 2026-09-23T14:23:47.479Z | G69: 0.005 | H69: 99.9 | I69: open | J69: c1f05579ce2e5528b55bc4bbc25c3e094638b9b6b19f684294028a6171c95e46 | K69: open | L69: 17de22f4f95f88f59385e2301081935f35201bae9cc2626443ed98c98b78b5c9 | M69: 2026-09-23T14:23:47.139Z
A70: ETH → SOL | B70: 2 | C70: CCTP (via Portal) | D70: 2026-09-23T14:23:01.554Z | E70: 2026-09-23T14:23:05.119Z | F70: 2026-09-23T14:23:47.185Z | G70: 0.001 | H70: 99.980001 | I70: open | J70: ed9044e3568d944a9c2bf84985bf3b2e265fadde331919d2005aa07ca18f783d | K70: open | L70: 5b947dc1e822f318d6521fc7a351a8d7ecfedbc95565b0a40a69428f70fd5cef | M70: 2026-09-23T14:23:47.145Z
A71: ETH → SOL | B71: 2 | C71: Husher | D71: 2026-09-23T14:23:01.579Z | E71: 2026-09-23T14:23:03.193Z | F71: 2026-09-23T14:23:47.168Z | G71: 0.004 | H71: 99.35 | I71: open | J71: 765f5ac5dca17f357cccc9b963c984b474cbd3b9d00078cb4b902cce1219273a | K71: open | L71: 1f586ddfcecebc8faa052ab4958fd5a4bf814ae0a75635d295efb72ce3068ce7 | M71: 2026-09-23T14:23:47.140Z
A72: ETH → SOL | B72: 2 | C72: Layerswap | D72: 2026-09-23T14:23:01.546Z | E72: 2026-09-23T14:23:04.153Z | F72: 2026-09-23T14:23:47.175Z | G72: 0.001 | H72: 99.682776 | I72: open | J72: 964feb36ada0b45dbba5a3886496e1a39d9c5a3d7a2e560b84d8810b8f284154 | K72: open | L72: 2ec87a5083912e3ed94ddddfafd4c2648d7d652b3033306118aa523cf1926523 | M72: 2026-09-23T14:23:47.143Z
A73: ETH → SOL | B73: 2 | C73: Meson | D73: 2026-09-23T14:23:01.580Z | E73: 2026-09-23T14:23:02.198Z | F73: 2026-09-23T14:23:47.147Z | G73: 0.007 | H73: 99.1 | I73: open | J73: a8a32326d59c3d46f7fed55a3b4f39afd50c8a5e4c223a57b96e865e4185afcd | K73: open | L73: 8d5d51d937c09707409b79aefcb6483776994aacc694b95aa0e4dc1f6d54c810 | M73: 2026-09-23T14:23:47.137Z
A74: ETH → SOL | B74: 2 | C74: Skip Go | D74: 2026-09-23T14:23:01.562Z | E74: 2026-09-23T14:23:04.496Z | F74: 2026-09-23T14:23:47.179Z | G74: 0.001 | H74: 99.72581 | I74: open | J74: 7d45544e66fa666339e3f38cc80257c374c931721cdcbe8254cc533ddff18587 | K74: open | L74: b0398e05dfa7ec89acbea3fc65c4ff69b5a441b3f5be83555ec3cdafe8c8382c | M74: 2026-09-23T14:23:47.145Z
A75: ETH → SOL | B75: 2 | C75: Symbiosis | D75: 2026-09-23T14:23:01.548Z | E75: 2026-09-23T14:23:04.395Z | F75: 2026-09-23T14:23:47.176Z | G75: 0 | H75: 98.951612 | I75: open | J75: f4760ebaa1832f6d670196e5c49185c9b71301b7b893a0cb703a4466d83f7b1c | K75: open | L75: 809df74457cd544641254ca1d389beef0e61414114179d9ae6dff103c392375b | M75: 2026-09-23T14:23:47.144Z
A76: ETH → SOL | B76: 3 | C76: Bridg | D76: 2026-09-23T14:27:21.676Z | E76: 2026-09-23T14:27:23.278Z | F76: 2026-09-23T14:27:28.368Z | H76: 99.85005 | I76: open | J76: 82be149797285aff27fff5f5ea7aba657f6b6cc2939892f5424df8fc07d0c91d | K76: open | L76: 146c26e0ee6f67bc8a6cd6a5f9cc041be1ee8fee420e7cf5a7cbc1a20085255c | M76: 2026-09-23T14:27:28.356Z
A77: ETH → SOL | B77: 3 | C77: OpenSea | D77: 2026-09-23T14:27:21.679Z | E77: 2026-09-23T14:27:25.109Z | F77: 2026-09-23T14:27:28.369Z | G77: 0.001 | H77: 99.7466 | I77: open | J77: 97bcda1c63bd381fd4da04ddfc40918dd4b0cdb6727efd6b9f9b436f80adf5d3 | K77: open | L77: a8df877af35cbe026f8fafd5492fe5b327f957850c282910adf46bb78ab9e31d | M77: 2026-09-23T14:27:28.357Z
A78: ETH → SOL | B78: 3 | C78: Relay | D78: 2026-09-23T14:27:21.671Z | E78: 2026-09-23T14:27:24.111Z | F78: 2026-09-23T14:27:28.366Z | G78: 0.001 | H78: 99.945713 | I78: open | J78: 678aa4da80c58c302f5fe3f0068b893f46d96ea8646c1800f5bd0fe5a80e3b04 | K78: open | L78: edcacc1291cc31ffe61b57298609a45e61d00d2d8755f7d6dcd8e3ddb34c1cd5 | M78: 2026-09-23T14:27:28.355Z
A79: ETH → SOL | B79: 3 | C79: deBridge | D79: 2026-09-23T14:27:21.675Z | E79: 2026-09-23T14:27:24.092Z | F79: 2026-09-23T14:27:28.365Z | G79: 0.001 | H79: 99.880035 | I79: open | J79: 6a252a9b0fd37aa9905cce2e7d5d956b781eb36dce073ee0d578edd104ef4857 | K79: open | L79: 3475c76c0939648dd5456a4b3e60686ed17ff637cff9b961bf2323d2de4a106a | M79: 2026-09-23T14:27:28.355Z
A80: ETH → SOL | B80: 3 | C80: LI.FI (Jumper) | D80: 2026-09-23T14:27:21.678Z | E80: 2026-09-23T14:27:24.934Z | F80: 2026-09-23T14:27:28.362Z | G80: 0 | H80: 99.945713 | I80: open | J80: 7b3d9a7cd7ca3ede67bca6f3cba365aca96cf323d611bf568f6d81a7d3adb8f5 | K80: open | L80: dc9346b86ffeb05534c2c3861d363d6b65b0a788ef5a7048afeb13f7fe7a1f70 | M80: 2026-09-23T14:27:28.356Z
A81: ETH → SOL | B81: 3 | C81: Across | D81: 2026-09-23T14:27:21.670Z | E81: 2026-09-23T14:27:23.874Z | F81: 2026-09-23T14:27:28.360Z | G81: 0.001 | H81: 99.99 | I81: open | J81: 5c222636d245f05df7db78ce841b96079b9465c4ecd24e04168f55e76c12feb7 | K81: open | L81: 3eb483c94f671a03d09491001b4efb9a955548574d8180859e075f2959990ce1 | M81: 2026-09-23T14:27:28.355Z
A82: ETH → SOL | B82: 3 | C82: Mayan | D82: 2026-09-23T14:27:21.669Z | E82: 2026-09-23T14:27:23.500Z | F82: 2026-09-23T14:27:28.359Z | G82: 0.002 | H82: 99.0287 | I82: open | J82: efcc8c99d88a890ff2d35f0c9d91a064c2950d796712b8719e4ae98fdd6b7033 | K82: open | L82: 276763f41b5e0c201c5a5da17a5d431cea31230f9fcb23fa7e4d677b8058f63c | M82: 2026-09-23T14:27:28.354Z
A83: ETH → SOL | B83: 3 | C83: Allbridge Core | D83: 2026-09-23T14:27:21.679Z | E83: 2026-09-23T14:27:23.493Z | F83: 2026-09-23T14:27:30.006Z | G83: 0.002 | H83: 99.9 | I83: open | J83: 8ac77333b6e1ff89e9ca320ac77b173dda095a0a34ec37abf1c78bb4478f1114 | K83: open | L83: 50f0df2fc68990ff676e46f804967e345113e05a5cb67521210acf874ffa2c14 | M83: 2026-09-23T14:27:28.354Z
A84: ETH → SOL | B84: 3 | C84: CCTP (via Portal) | D84: 2026-09-23T14:27:21.679Z | E84: 2026-09-23T14:27:26.203Z | F84: 2026-09-23T14:27:28.363Z | G84: 0.003 | H84: 99.980001 | I84: open | J84: 962db000d2f512bfada3e26b1305ca22101492cf5970591eb8c9c3c52801587d | K84: open | L84: 6b7ee13f1ecef1f380733ae892028ce62d45c15095a9c49f4dbe1593b695b46e | M84: 2026-09-23T14:27:28.353Z
A85: ETH → SOL | B85: 3 | C85: Husher | D85: 2026-09-23T14:27:21.680Z | E85: 2026-09-23T14:27:23.502Z | F85: 2026-09-23T14:27:28.365Z | G85: 0.002 | H85: 99.35 | I85: open | J85: 30af934d5d36245f4d925f7e848ec40c62bf58f10ae7a3500563bcaf6f1b579b | K85: open | L85: cad886b514f2dc020f2cc08f9c2e9ea87a22368e108cd96bc8fcb67bb3b0ddc8 | M85: 2026-09-23T14:27:28.354Z
A86: ETH → SOL | B86: 3 | C86: Layerswap | D86: 2026-09-23T14:27:21.670Z | E86: 2026-09-23T14:27:24.282Z | F86: 2026-09-23T14:27:28.367Z | G86: 0 | H86: 99.682757 | I86: open | J86: e5e6e23490e2a2f2ef17db653ebdab78345791cda1f49cf660dd8bf15c557d53 | K86: open | L86: 231de017f0fd940164401c7b02525eca50c8b039faa8293b7c646e4a781c7454 | M86: 2026-09-23T14:27:28.356Z
A87: ETH → SOL | B87: 3 | C87: Meson | D87: 2026-09-23T14:27:21.681Z | E87: 2026-09-23T14:27:22.613Z | F87: 2026-09-23T14:27:28.361Z | G87: 0.002 | H87: 99.1 | I87: open | J87: a8a32326d59c3d46f7fed55a3b4f39afd50c8a5e4c223a57b96e865e4185afcd | K87: open | L87: 4ad31bc9baca25c8644afbb682c654dedd20c0f9cf10012928785dc196c58f4d | M87: 2026-09-23T14:27:28.354Z
A88: ETH → SOL | B88: 3 | C88: SimpleSwap | D88: 2026-09-23T14:27:21.681Z | E88: 2026-09-23T14:27:25.024Z | F88: 2026-09-23T14:27:29.298Z | G88: 0.001 | H88: 98.479738 | I88: open | J88: cbda08164ac53fe55905ad466c56e1f1d53cd7ceb92ac0008942e57e78fe6afe | K88: open | L88: 408c4f6b031b985c4404bdb2b85c037147bc1350696a1f0aff081e512803bf8d | M88: 2026-09-23T14:27:28.357Z
... A90: ETH → SOL | B90: 3 | C90: Symbiosis | D90: 2026-09-23T14:27:21.673Z | E90: 2026-09-23T14:27:25.245Z | F90: 2026-09-23T14:27:28.369Z | G90: 0.001 | H90: 98.95137 | I90: open | J90: 72422bdd7711b4aed096816090572985a70389bb3ab29a05182e3be2189a078e | K90: open | L90: 72a5faf5cbf02934b0ae5daf05a379ab8a047b4adfd5063ac1902aecf1fcf219 | M90: 2026-09-23T14:27:28.357Z
A91: SOL → BSC | B91: 1 | C91: Bridg | D91: 2026-09-23T14:19:52.315Z | E91: 2026-09-23T14:19:53.709Z | F91: 2026-09-23T14:19:58.640Z | H91: 99.870038 | I91: open | J91: 443699e32845732bfb5c3e881ce24d7842aaa255363223d6733214554965fb69 | K91: open | L91: a34486116077f6ff8244090aa3f5cecced5c9c966213eff136f458a26a8f29a3 | M91: 2026-09-23T14:19:58.625Z
A92: SOL → BSC | B92: 1 | C92: Relay | D92: 2026-09-23T14:19:52.315Z | E92: 2026-09-23T14:19:54.827Z | F92: 2026-09-23T14:19:58.662Z | G92: 0.001 | H92: 99.651304 | I92: open | J92: cade892914de594a9cb7cd55b920ae3400c4e3c0530cc788906ea5fbdb8cc1bb | K92: open | L92: 5b70d3ad3fc2f6a5c0699014100b4a0512930fcbfa9ffc7b53ebae614528c16b | M92: 2026-09-23T14:19:58.626Z
A93: SOL → BSC | B93: 1 | C93: deBridge | D93: 2026-09-23T14:19:52.317Z | E93: 2026-09-23T14:19:54.790Z | F93: 2026-09-23T14:19:58.661Z | G93: 0.001 | H93: 99.920015 | I93: open | J93: 16befa75c3508c1dc5e3e1efcbbf2e051fac3fb62ab0ea5448704765316a643f | K93: open | L93: bb956886bcd39854d9f1e69687fa31e9d26396936cbf4cb723cebbbcd9393538 | M93: 2026-09-23T14:19:58.626Z
A94: SOL → BSC | B94: 1 | C94: LI.FI (Jumper) | D94: 2026-09-23T14:19:52.317Z | E94: 2026-09-23T14:19:56.484Z | F94: 2026-09-23T14:19:58.628Z | G94: 0.002 | H94: 99.93159 | I94: open | J94: 2f3e465a250f2cfc76f8f84185d5dfbd0ecb3414bda7fda134620f25467965a7 | K94: open | L94: fc2a48de6cadcf22f7b3640fb710d193a1f4af6e8da2a01bb3f32abc2f41fcc9 | M94: 2026-09-23T14:19:58.623Z
A95: SOL → BSC | B95: 1 | C95: Across | D95: 2026-09-23T14:19:52.315Z | E95: 2026-09-23T14:19:54.082Z | F95: 2026-09-23T14:19:58.633Z | G95: 0.001 | H95: 99.981745 | I95: open | J95: 53ca27848a7b35479cefecdf2bee060b51362ebf36b6d5211356412de7b8491a | K95: open | L95: ef99166794839d59862d98b764be85baa99a7858a2f38a22d44f41bdd1cba0f8 | M95: 2026-09-23T14:19:58.624Z
A96: SOL → BSC | B96: 1 | C96: Mayan | D96: 2026-09-23T14:19:52.314Z | E96: 2026-09-23T14:19:53.910Z | F96: 2026-09-23T14:19:58.632Z | G96: 0.001 | H96: 99.931 | I96: open | J96: a02c86867b29c19e85582e3723303f2f85ebedee30624eeab7b598938e3ef5de | K96: open | L96: 41a698e2cce0c2a548460145b34a3ceda74cd34370bd9ec54691479cb21e1c52 | M96: 2026-09-23T14:19:58.624Z
A97: SOL → BSC | B97: 1 | C97: Husher | D97: 2026-09-23T14:19:52.323Z | E97: 2026-09-23T14:19:54.091Z | F97: 2026-09-23T14:19:58.660Z | G97: 0.001 | H97: 99.65 | I97: open | J97: 7417df4424d648bae07263c8594d657f364584399915f8d763a24782dd3d4f4b | K97: open | L97: 1ab9edec93155b7daf6d19fc9c9feacb7f76d9f365f933507a5172ea1e4d7b56 | M97: 2026-09-23T14:19:58.624Z
A98: SOL → BSC | B98: 1 | C98: Layerswap | D98: 2026-09-23T14:19:52.316Z | E98: 2026-09-23T14:19:55.032Z | F98: 2026-09-23T14:19:58.663Z | G98: 0.001 | H98: 99.863113 | I98: open | J98: 634c2f607c76a0f68b119157a7566dab2d365331c1680438e2f497258eaafeaf | K98: open | L98: a4e156dbe7e10fa1e8cd46da5a649a8a13817df34ab8ea3ebf7388ead621fb6e | M98: 2026-09-23T14:19:58.626Z
A99: SOL → BSC | B99: 1 | C99: Meson | D99: 2026-09-23T14:19:52.320Z | E99: 2026-09-23T14:19:52.804Z | F99: 2026-09-23T14:19:58.635Z | G99: 0.002 | H99: 99.88 | I99: open | J99: f3c5717ceaddc72822b0bcd0fb927b2f6c141b811ef19d6d95f6fae4543c8073 | K99: open | L99: 12ffb1738ee3f6064842997839e2b2e04ce5a8fc13cbb73a50a0aca80759ef29 | M99: 2026-09-23T14:19:58.623Z
A100: SOL → BSC | B100: 1 | C100: SimpleSwap | D100: 2026-09-23T14:19:52.325Z | E100: 2026-09-23T14:19:55.429Z | F100: 2026-09-23T14:19:58.707Z | G100: 0.002 | H100: 98.139 | I100: open | J100: d7cb8ee9cb5635b15fc09e9bbba38cc7c663de360e8ef56e5f72dfe8ede47324 | K100: open | L100: aa14b892df70495e05cb5b4dd946860e78677e3f7d172b506748b558ec6abbf5 | M100: 2026-09-23T14:19:58.627Z
A101: SOL → BSC | B101: 2 | C101: Bridg | D101: 2026-09-23T14:24:12.906Z | E101: 2026-09-23T14:24:13.884Z | F101: 2026-09-23T14:24:42.100Z | H101: 99.870038 | I101: open | J101: e6ea3ffafdeecaf3537b16804db0d920bc1b9025939b1b3aecfc325eee6f4cc0 | K101: open | L101: 0d4a954c3822742c23d2cd956a0e2bb773d0c77fbc1918294401df6dcb6cd6fe | M101: 2026-09-23T14:24:42.081Z
A102: SOL → BSC | B102: 2 | C102: Relay | D102: 2026-09-23T14:24:12.907Z | E102: 2026-09-23T14:24:15.029Z | F102: 2026-09-23T14:24:42.096Z | G102: 0.001 | H102: 99.640814 | I102: open | J102: 069586ecaf959f4178e337e49a67f1b7395ed77fa13cb2b11283809e92584722 | K102: open | L102: f94deb23f0b18bf6adf4251dabccce3afa83fc9d49c2942040e0caa24b49b1e0 | M102: 2026-09-23T14:24:42.080Z
A103: SOL → BSC | B103: 2 | C103: deBridge | D103: 2026-09-23T14:24:12.906Z | E103: 2026-09-23T14:24:15.031Z | F103: 2026-09-23T14:24:42.097Z | G103: 0.001 | H103: 99.920015 | I103: open | J103: cbcb0920d8e9d3f04619581d6b67a67a8cc5c1f23291b900bc5b9b66f25d7cca | K103: open | L103: 1d4b1a631a706edf37527b4384648b1e26c5b0c68ff446391aadb1d6c0ec08a8 | M103: 2026-09-23T14:24:42.080Z
A104: SOL → BSC | B104: 2 | C104: LI.FI (Jumper) | D104: 2026-09-23T14:24:12.910Z | E104: 2026-09-23T14:24:39.934Z | F104: 2026-09-23T14:24:42.083Z | G104: 0.004 | H104: 99.93159 | I104: open | J104: 7e6212299e84a35d3f0d816d4d921d6a5c44bad5da5f458217869b32fef26d27 | K104: open | L104: ee35d09cec6725e9f8d656923266415aa3e5ad0841e2cd6efb36471be7f98077 | M104: 2026-09-23T14:24:42.077Z
A105: SOL → BSC | B105: 2 | C105: Across | D105: 2026-09-23T14:24:12.906Z | E105: 2026-09-23T14:24:14.756Z | F105: 2026-09-23T14:24:42.085Z | G105: 0.002 | H105: 99.982214 | I105: open | J105: 58f0e2c212a37bd746d8686cf0d56fb8200a035ded2b813d39fb703f92c77fe7 | K105: open | L105: ec469d4451c4ad04c5614f091f8bc47850078ef2adcf542a549efedbe2ad09dc | M105: 2026-09-23T14:24:42.079Z
...

Sheet Platform Registry
A1: Name | B1: Kind | C1: Status | D1: Routes quoted (own UI) | E1: Bridg venue id | F1: URL / method | G1: Reason / notes | H1: Checked
A2: Bridg | B2: subject | C2: WORKING | D2: all 6 | F2: https://bridg.now/swap/ | G2: Per-venue live-quote board + best/fastest fee breakdown; no wallet needed
A3: Relay | B3: venue | C3: WORKING | D3: all 6 | E3: relay | F3: https://relay.link
A4: deBridge | B4: venue | C4: WORKING | D4: all 6 | E4: debridge | F4: https://app.debridge.finance
A5: LI.FI (Jumper) | B5: venue | C5: WORKING | D5: all 6 | E5: lifi | F5: https://jumper.exchange
A6: Across | B6: venue | C6: WORKING | D6: all 6 | E6: across | F6: https://app.across.to
A7: Mayan | B7: venue | C7: WORKING | D7: all 6 | E7: mayan | F7: https://swap.mayan.finance
A8: Allbridge Core | B8: venue | C8: PARTIAL | D8: SOL → ETH, ETH → SOL, SOL → Base, Base → SOL | E8: allbridge-core
A9: CCTP (via Portal) | B9: venue | C9: PARTIAL | D9: SOL → ETH, ETH → SOL, SOL → Base, Base → SOL | E9: cctp
A10: Husher | B10: venue | C10: WORKING | D10: all 6 | E10: husher
A11: Layerswap | B11: venue | C11: WORKING | D11: all 6 | E11: layerswap
A12: Meson | B12: venue | C12: WORKING | D12: all 6 | E12: meson
A13: OpenSea | B13: platform | C13: PARTIAL | D13: SOL → ETH, ETH → SOL, SOL → Base, Base → SOL
A14: SimpleSwap | B14: venue | C14: WORKING | D14: all 6 | E14: simpleswap
A15: Skip Go | B15: venue | C15: PARTIAL | D15: SOL → ETH, ETH → SOL, SOL → Base, Base → SOL | E15: skip-go
A16: Symbiosis | B16: venue | C16: PARTIAL | D16: SOL → ETH, ETH → SOL, BSC → SOL, Base → SOL | E16: symbiosis
A17: Axiom | B17: platform | C17: BLOCKED | D17: none | F17: https://axiom.trade/ | G17: PARTIAL — no 100 USDC quote without funds. Signed-in check (user logged in; built-in browser, 2026-09-23): Axiom 'Exchange' has a cross-chain Convert (e.g. 'Swap USDC on Solana for USDC on Ethereum', indicative 1 USDC = 1.0000 USDC) but the amount field clamps to the wallet balance (0), so 100 can't be priced. Deposit auto-bridges EVM→Solana and shows fees only at its minimum: ETH→SOL USDC ($3 min) ~26s, impact −0.388%, fees ~$0.27 (gas $0.27, routing/liquidity <$0.01); BSC→SOL ($2 min) ~26s, impact −8.357%, fees ~$0.21 (gas); Base→SOL ($2 min) ~26s, impact −0.455%, fees ~$0.02. Indicative only — not comparable to a 100 USDC quote. | H17: 2026-09-23T14:07:33Z
A18: Eco | B18: venue | C18: BLOCKED | D18: none | E18: eco | F18: https://portal.eco.com/ | G18: Eco Portal (portal.eco.com, Eco's official transfer UI) does not offer Solana or BNB Chain as origin or destination (chains: Arbitrum, Base, Celo, Ethereum, Ink, Optimism, Plasma, Polygon, Sonic, Unichain), so no SOL<->ETH/BSC/Base USDC route can be quoted there. The UI itself quotes without a wallet for supported chains (e.g. Base->Ethereum 100 USDC -> 100 USDC). | H18: 2026-09-23T09:27:00Z
A19: FOMO | B19: platform | C19: BLOCKED | D19: none | F19: https://fomo.family/ | G19: BLOCKED — signed-in check (user logged in): deposits accept USDC from Solana, Base, BNB Chain, Monad, Robinhood Chain, Arc, Ethereum into one USD cash balance; no fee/quote is shown at deposit and moving funds out needs a balance. No chain-to-chain quote. | H19: 2026-09-23T14:07:33Z
A20: GMGN | B20: platform | C20: BLOCKED | D20: none | F20: https://gmgn.ai/ | G20: BLOCKED — signed-in check (user logged in): wallet menu has Convert, but it requires binding 2FA (a security-setting change the user must make) and then a 3-hour lock before Convert works. Deposit accepts SOL/USDT/USDC/USD1 on the Solana network only. | H20: 2026-09-23T14:07:33Z
A21: NEAR Intents | B21: venue | C21: BLOCKED | D21: none | E21: near-intents | F21: https://near.com/swap | G21: Official NEAR Intents app (app.near-intents.org) is decommissioned and just points to near.com; near.com's swap requires signing in / creating an account (passkey or wallet). The public landing-page demo swap has no chain selector (one unified USDC = Ethereum USDC), so no SOL<->EVM USDC route can be quoted. | H21: 2026-09-23T09:27:00Z
A22: Pump.fun | B22: platform | C22: BLOCKED | D22: none | F22: https://pump.fun/ | G22: BLOCKED — signed-in check (user logged in): web Deposit is Solana-only ('Only send assets on the Solana network', min 0.01 SOL). No cross-chain quote on web; the MoonPay cross-chain deposit reported in news may be mobile-only. | H22: 2026-09-23T14:07:33Z
A23: Rhino.fi | B23: venue | C23: BLOCKED | D23: none | E23: rhino | F23: https://app.rhino.fi/bridge?token=USDC&chainIn=SOLANA&chainOut=ETHEREUM | G23: No public web UI: app.rhino.fi redirects to rhino.fi/b2c-app-deprecation (retail app deprecated Aug 2026; B2B/Console only, requires an account) | H23: 2026-09-23T09:22:44Z

Sheet Raw Quotes
A1: Run ID | B1: Route | C1: Sample | D1: Site | E1: Kind | F1: Status | G1: requestStart (UTC) | H1: quoteVisible (UTC) | I1: screenshotAt (UTC) | J1: Δ read vs Bridg (s) | K1: Out (USDC) | L1: Fee on top | M1: Fee token | N1: Detail | O1: Page URL | P1: Campaign | Q1: Value read at (UTC) | R1: Settled at (UTC) | S1: Run read spread (s)
A2: 4c97f29bcfca | B2: SOL->ETH | C2: 1 | D2: Bridg | E2: bridg | F2: OK | G2: 2026-09-23T14:18:34.538Z | H2: 2026-09-23T14:18:36.899Z | I2: 2026-09-23T14:18:55.437Z | K2: 99.840015 | N2: best via Across; 16 venues priced; fees [['Across fee', 0.009985], ['Bridg fee', 0.15]] | O2: https://bridg.now/swap/ | P2: 20260923T141817Z | Q2: 2026-09-23T14:18:55.406Z | R2: 2026-09-23T14:18:41.639Z | S2: 0.006
A3: 4c97f29bcfca | B3: SOL->ETH | C3: 1 | D3: Relay | E3: venue | F3: OK | G3: 2026-09-23T14:18:34.535Z | H3: 2026-09-23T14:18:38.436Z | I3: 2026-09-23T14:18:55.426Z | J3: 0.002 | K3: 99.193956 | N3: rate=0.9919 | O3: https://relay.link/bridge/ethereum?fromChainId=792703809&fromCurrency=EPjFWdd5AufqSSqeM2qN1xzybapC8G4wEGGkZwyTDt1v&toCurrency=0xa0b86991c6218b36c1d19d4a2e9eb0ce3606eb48 | P3: 20260923T141817Z | Q3: 2026-09-23T14:18:55.404Z | R3: 2026-09-23T14:18:40.718Z | S3: 0.006
A4: 4c97f29bcfca | B4: SOL->ETH | C4: 1 | D4: deBridge | E4: venue | F4: OK | G4: 2026-09-23T14:18:34.531Z | H4: 2026-09-23T14:18:37.964Z | I4: 2026-09-23T14:18:55.424Z | J4: 0.004 | K4: 99.920018 | L4: 2.9354 | M4: USDC | N4: fixed_fee_on_top=2.9354; fixed_fee_token=USDC | O4: https://app.debridge.com/?inputChain=7565164&outputChain=1&inputCurrency=EPjFWdd5AufqSSqeM2qN1xzybapC8G4wEGGkZwyTDt1v&outputCurrency=0xa0b86991c6218b36c1d19d4a2e9eb0ce3606eb48&dlnMode=simple | P4: 20260923T141817Z | Q4: 2026-09-23T14:18:55.402Z | R4: 2026-09-23T14:18:40.142Z | S4: 0.006
A5: 4c97f29bcfca | B5: SOL->ETH | C5: 1 | D5: LI.FI (Jumper) | E5: venue | F5: OK | G5: 2026-09-23T14:18:34.668Z | H5: 2026-09-23T14:18:53.254Z | I5: 2026-09-23T14:18:55.407Z | J5: 0.006 | K5: 99.193956 | N5: best_return_venue=Relay; max_out=99.99 | O5: https://jumper.xyz/?fromChain=1151111081099710&fromToken=EPjFWdd5AufqSSqeM2qN1xzybapC8G4wEGGkZwyTDt1v&toChain=1&toToken=0xa0b86991c6218b36c1d19d4a2e9eb0ce3606eb48 | P5: 20260923T141817Z | Q5: 2026-09-23T14:18:55.400Z | R5: 2026-09-23T14:18:55.399Z | S5: 0.006
A6: 4c97f29bcfca | B6: SOL->ETH | C6: 1 | D6: Across | E6: venue | F6: OK | G6: 2026-09-23T14:18:34.512Z | H6: 2026-09-23T14:18:37.143Z | I6: 2026-09-23T14:18:55.411Z | J6: 0.006 | K6: 99.99 | O6: https://across.to/?from=solana&to=ethereum&inputToken=USDC&outputToken=USDC | P6: 20260923T141817Z | Q6: 2026-09-23T14:18:55.400Z | R6: 2026-09-23T14:18:39.457Z | S6: 0.006
A7: 4c97f29bcfca | B7: SOL->ETH | C7: 1 | D7: Mayan | E7: venue | F7: OK | G7: 2026-09-23T14:18:34.511Z | H7: 2026-09-23T14:18:37.365Z | I7: 2026-09-23T14:18:55.411Z | J7: 0.006 | K7: 96.6446 | N7: mode=Swift v2; eta=3s; display_decimals=4 | O7: https://swap.mayan.finance/ | P7: 20260923T141817Z | Q7: 2026-09-23T14:18:55.400Z | R7: 2026-09-23T14:18:39.450Z | S7: 0.006
A8: 4c97f29bcfca | B8: SOL->ETH | C8: 1 | D8: Allbridge Core | E8: venue | F8: OK | G8: 2026-09-23T14:18:34.659Z | H8: 2026-09-23T14:18:37.676Z | I8: 2026-09-23T14:18:55.590Z | J8: 0.005 | K8: 99.9 | L8: 0.014082 | M8: SOL (relayer fee, fee=native) | N8: out_input_box=99.9; out_details_2dp=99.9; fixed_fee_on_top=0.014082; fixed_fee_token=SOL (relayer fee, fee=native); transfer_fee=0.10 USDC; messenger=CCTP; eta=~2 min; display_decimals=1; picked=['USDC from Solana', 'USDC to Ethereum'] | O8: https://core.allbridge.io/?fee=native&ft=USDC&tt=USDC&f=SOL&t=ETH | P8: 20260923T141817Z | Q8: 2026-09-23T14:18:55.401Z | R8: 2026-09-23T14:18:39.982Z | S8: 0.006
A9: 4c97f29bcfca | B9: SOL->ETH | C9: 1 | D9: CCTP (via Portal) | E9: venue | F9: OK | G9: 2026-09-23T14:18:34.656Z | H9: 2026-09-23T14:18:40.048Z | I9: 2026-09-23T14:18:55.437Z | J9: 0 | K9: 99.99 | N9: venue_ui=CCTP via Portal (portalbridge.com/usdc-bridge); messenger=Circle CCTP; route_type=CCTPv2StandardExecutorRoute; eta=14 sec; usd_value=99.99; price_impact=-0.01%; fixed_fee_note=executor/relayer fee not shown without a wallet; display_decimals=2 | O9: https://portalbridge.com/usdc-bridge?fromChain=Solana&fromToken=USDC&toChain=Ethereum&toToken=USDC | P9: 20260923T141817Z | Q9: 2026-09-23T14:18:55.406Z | R9: 2026-09-23T14:18:42.192Z | S9: 0.006
A10: 4c97f29bcfca | B10: SOL->ETH | C10: 1 | D10: Husher | E10: venue | F10: OK | G10: 2026-09-23T14:18:34.669Z | H10: 2026-09-23T14:18:37.420Z | I10: 2026-09-23T14:18:55.425Z | J10: 0.005 | K10: 99.05 | N10: out_usd=$99.07; provider=Husher (Best Rate); rate_type=floating; fee_deducted=0.35; network_fee_deducted=0.6; api_receive=99.05000000; eta_s=40; display_decimals=2 | O10: https://www.husher.io/ | P10: 20260923T141817Z | Q10: 2026-09-23T14:18:55.401Z | R10: 2026-09-23T14:18:39.490Z | S10: 0.006
A11: 4c97f29bcfca | B11: SOL->ETH | C11: 1 | D11: Layerswap | E11: venue | F11: OK | G11: 2026-09-23T14:18:34.512Z | H11: 2026-09-23T14:18:38.407Z | I11: 2026-09-23T14:18:55.429Z | J11: 0.004 | K11: 99.716863 | N11: out_usd=$99.69; fee_usd=0.28; slippage=0.00%; eta=25 secs; to_token=USDC; to_chain=Ethereum; display_decimals=6 | O11: https://layerswap.io/app?from=SOLANA_MAINNET&to=ETHEREUM_MAINNET&fromAsset=USDC&toAsset=USDC | P11: 20260923T141817Z | Q11: 2026-09-23T14:18:55.402Z | R11: 2026-09-23T14:18:40.563Z | S11: 0.006
A12: 4c97f29bcfca | B12: SOL->ETH | C12: 1 | D12: Meson | E12: venue | F12: OK | G12: 2026-09-23T14:18:34.698Z | H12: 2026-09-23T14:18:36.601Z | I12: 2026-09-23T14:18:55.413Z | J12: 0.006 | K12: 98.65 | L12: 0 | N12: fees_deducted=[['Fee', 1.35, 'USDC']]; fee_total=1.35; fixed_fee_on_top=0.0; display_decimals=2 | O12: https://meson.fi/swap | P12: 20260923T141817Z | Q12: 2026-09-23T14:18:55.400Z | R12: 2026-09-23T14:18:38.645Z | S12: 0.006
A13: 4c97f29bcfca | B13: SOL->ETH | C13: 1 | D13: OpenSea | E13: platform | F13: OK | G13: 2026-09-23T14:18:34.664Z | H13: 2026-09-23T14:18:39.130Z | I13: 2026-09-23T14:18:55.428Z | J13: 0.001 | K13: 98.9896 | L13: 0.09 | M13: native (gas, USD shown) | N13: out_usd=$98.97; provider=Relay; fee_total_usd=1.09; provider_fee_usd=1.0; provider_fee_pct=1%; provider_fee_deducted=True; opensea_fee_usd=0.0; opensea_fee_pct=0%; gas_fee_usd=0.09; gas_fee_display=$0.09; fixed_fee_on_top=0.09; fixed_fee_token=native (gas, USD shown); price_impact=(-< $0.01) -0.01%; | O13: https://opensea.io/swap?fromChain=solana&fromAddress=EPjFWdd5AufqSSqeM2qN1xzybapC8G4wEGGkZwyTDt1v&toChain=ethereum&toAddress=0xa0b86991c6218b36c1d19d4a2e9eb0ce3606eb48 | P13: 20260923T141817Z | Q13: 2026-09-23T14:18:55.405Z | R13: 2026-09-23T14:18:41.454Z | S13: 0.006
A14: 4c97f29bcfca | B14: SOL->ETH | C14: 1 | D14: SimpleSwap | E14: venue | F14: OK | G14: 2026-09-23T14:18:34.669Z | H14: 2026-09-23T14:18:39.168Z | I14: 2026-09-23T14:18:55.490Z | J14: 0.001 | K14: 98.206302 | L14: 0 | M14: USDC | N14: best_card_out=98.206302; selected_card=Best rate / Decentralized; rate_type=floating; fixed_fee_on_top=0.0; fixed_fee_token=USDC; display_decimals=6; small_sum_warning=False | O14: https://simpleswap.io/?from=usdc-sol&to=usdc-eth | P14: 20260923T141817Z | Q14: 2026-09-23T14:18:55.405Z | R14: 2026-09-23T14:18:41.586Z | S14: 0.006
A15: 4c97f29bcfca | B15: SOL->ETH | C15: 1 | D15: Skip Go | E15: venue | F15: OK | G15: 2026-09-23T14:18:34.513Z | H15: 2026-09-23T14:18:39.607Z | I15: 2026-09-23T14:18:55.435Z | J15: 0 | K15: 96.94911 | N15: fees_usd_in_quote=3.05; eta=30 secs; usd_values=['99.98', '96.93']; display_decimals=5 | O15: https://go.skip.build/?src_chain=solana&src_asset=EPjFWdd5AufqSSqeM2qN1xzybapC8G4wEGGkZwyTDt1v&dest_chain=1&dest_asset=0xa0b86991c6218b36c1d19d4a2e9eb0ce3606eb48 | P15: 20260923T141817Z | Q15: 2026-09-23T14:18:55.406Z | R15: 2026-09-23T14:18:41.771Z | S15: 0.006
A16: 4c97f29bcfca | B16: SOL->ETH | C16: 1 | D16: Symbiosis | E16: venue | F16: OK | G16: 2026-09-23T14:18:34.533Z | H16: 2026-09-23T14:18:39.114Z | I16: 2026-09-23T14:18:55.435Z | J16: 0.002 | K16: 96.860997 | L16: 0 | N16: min_received=96.3766; fee_usd_deducted=3.14; eta=1 - 3 Min; price_impact=0%; slippage=2%; route=Bridge to Ethereum; fixed_fee_on_top=0.0; display_decimals=6 | O16: https://app.symbiosis.finance/swap?chainIn=Solana&chainOut=Ethereum&tokenIn=0x0000000000000000000000000000000000000003&tokenOut=0xa0b86991c6218b36c1d19d4a2e9eb0ce3606eb48 | P16: 20260923T141817Z | Q16: 2026-09-23T14:18:55.404Z | R16: 2026-09-23T14:18:41.393Z | S16: 0.006
A17: 1ce3ee3c699e | B17: ETH->SOL | C17: 1 | D17: Bridg | E17: bridg | F17: OK | G17: 2026-09-23T14:19:22.123Z | H17: 2026-09-23T14:19:23.634Z | I17: 2026-09-23T14:19:28.723Z | K17: 99.85005 | N17: best via Allbridge Core; 15 venues priced; fees [['Allbridge Core fee', 0.09995], ['Bridg fee', 0.05]] | O17: https://bridg.now/swap/ | P17: 20260923T141817Z | Q17: 2026-09-23T14:19:28.697Z | R17: 2026-09-23T14:19:25.849Z | S17: 0.006
A18: 1ce3ee3c699e | B18: ETH->SOL | C18: 1 | D18: Relay | E18: venue | F18: OK | G18: 2026-09-23T14:19:22.117Z | H18: 2026-09-23T14:19:24.093Z | I18: 2026-09-23T14:19:28.731Z | J18: 0.001 | K18: 99.945703 | N18: rate=0.9994 | O18: https://relay.link/bridge/solana?fromChainId=1&fromCurrency=0xa0b86991c6218b36c1d19d4a2e9eb0ce3606eb48&toCurrency=EPjFWdd5AufqSSqeM2qN1xzybapC8G4wEGGkZwyTDt1v | P18: 20260923T141817Z | Q18: 2026-09-23T14:19:28.698Z | R18: 2026-09-23T14:19:26.239Z | S18: 0.006
A19: 1ce3ee3c699e | B19: ETH->SOL | C19: 1 | D19: deBridge | E19: venue | F19: OK | G19: 2026-09-23T14:19:22.120Z | H19: 2026-09-23T14:19:24.092Z | I19: 2026-09-23T14:19:28.731Z | J19: 0.001 | K19: 99.920018 | L19: 1.965 | M19: USDC | N19: fixed_fee_on_top=1.965; fixed_fee_token=USDC | O19: https://app.debridge.com/?inputChain=1&outputChain=7565164&inputCurrency=0xa0b86991c6218b36c1d19d4a2e9eb0ce3606eb48&outputCurrency=EPjFWdd5AufqSSqeM2qN1xzybapC8G4wEGGkZwyTDt1v&dlnMode=simple | P19: 20260923T141817Z | Q19: 2026-09-23T14:19:28.698Z | R19: 2026-09-23T14:19:26.239Z | S19: 0.006
A20: 1ce3ee3c699e | B20: ETH->SOL | C20: 1 | D20: LI.FI (Jumper) | E20: venue | F20: OK | G20: 2026-09-23T14:19:22.121Z | H20: 2026-09-23T14:19:24.437Z | I20: 2026-09-23T14:19:28.709Z | J20: 0.001 | K20: 99.945703 | N20: best_return_venue=Relay; max_out=100.0 | O20: https://jumper.xyz/?fromChain=1&fromToken=0xa0b86991c6218b36c1d19d4a2e9eb0ce3606eb48&toChain=1151111081099710&toToken=EPjFWdd5AufqSSqeM2qN1xzybapC8G4wEGGkZwyTDt1v | P20: 20260923T141817Z | Q20: 2026-09-23T14:19:28.698Z | R20: 2026-09-23T14:19:26.567Z | S20: 0.006
A21: 1ce3ee3c699e | B21: ETH->SOL | C21: 1 | D21: Across | E21: venue | F21: OK | G21: 2026-09-23T14:19:22.117Z | H21: 2026-09-23T14:19:23.610Z | I21: 2026-09-23T14:19:28.705Z | J21: 0 | K21: 99.99 | O21: https://across.to/?from=ethereum&to=solana&inputToken=USDC&outputToken=USDC | P21: 20260923T141817Z | Q21: 2026-09-23T14:19:28.697Z | R21: 2026-09-23T14:19:25.744Z | S21: 0.006
A22: 1ce3ee3c699e | B22: ETH->SOL | C22: 1 | D22: Mayan | E22: venue | F22: OK | G22: 2026-09-23T14:19:22.116Z | H22: 2026-09-23T14:19:23.870Z | I22: 2026-09-23T14:19:28.706Z | J22: 0.001 | K22: 99.0127 | N22: mode=Swift v2; eta=3s; display_decimals=4 | O22: https://swap.mayan.finance/ | P22: 20260923T141817Z | Q22: 2026-09-23T14:19:28.698Z | R22: 2026-09-23T14:19:25.992Z | S22: 0.006
A23: 1ce3ee3c699e | B23: ETH->SOL | C23: 1 | D23: Allbridge Core | E23: venue | F23: OK | G23: 2026-09-23T14:19:22.124Z | H23: 2026-09-23T14:19:23.598Z | I23: 2026-09-23T14:19:29.622Z | J23: 0 | K23: 99.9 | L23: 0.000137 | M23: ETH (relayer fee, fee=native) | N23: out_input_box=99.9; out_details_2dp=99.9; fixed_fee_on_top=0.000137; fixed_fee_token=ETH (relayer fee, fee=native); transfer_fee=0.10 USDC; messenger=CCTP; eta=~18 min; display_decimals=1; picked=['USDC from Ethereum', 'USDC to Solana'] | O23: https://core.allbridge.io/?fee=native&ft=USDC&tt=USDC&f=ETH&t=SOL | P23: 20260923T141817Z | Q23: 2026-09-23T14:19:28.697Z | R23: 2026-09-23T14:19:25.936Z | S23: 0.006
A24: 1ce3ee3c699e | B24: ETH->SOL | C24: 1 | D24: CCTP (via Portal) | E24: venue | F24: OK | G24: 2026-09-23T14:19:22.124Z | H24: 2026-09-23T14:19:26.548Z | I24: 2026-09-23T14:19:28.714Z | J24: 0.001 | K24: 99.980001 | N24: venue_ui=CCTP via Portal (portalbridge.com/usdc-bridge); messenger=Circle CCTP; route_type=CCTPv2FastExecutorRoute; eta=20 sec; usd_value=99.98; price_impact=-0.02%; fixed_fee_note=executor/relayer fee not shown without a wallet; display_decimals=6 | O24: https://portalbridge.com/usdc-bridge?fromChain=Ethereum&fromToken=USDC&toChain=Solana&toToken=USDC | P24: 20260923T141817Z | Q24: 2026-09-23T14:19:28.696Z | R24: 2026-09-23T14:19:28.695Z | S24: 0.006
A25: 1ce3ee3c699e | B25: ETH->SOL | C25: 1 | D25: Husher | E25: venue | F25: OK | G25: 2026-09-23T14:19:22.125Z | H25: 2026-09-23T14:19:23.515Z | I25: 2026-09-23T14:19:28.725Z | J25: 0.001 | K25: 99.35 | N25: out_usd=$99.37; provider=Husher (Best Rate); rate_type=floating; fee_deducted=0.35; network_fee_deducted=0.3; api_receive=99.35000000; eta_s=40; display_decimals=2 | O25: https://www.husher.io/ | P25: 20260923T141817Z | Q25: 2026-09-23T14:19:28.696Z | R25: 2026-09-23T14:19:25.664Z | S25: 0.006
A26: 1ce3ee3c699e | B26: ETH->SOL | C26: 1 | D26: Layerswap | E26: venue | F26: OK | G26: 2026-09-23T14:19:22.120Z | H26: 2026-09-23T14:19:24.571Z | I26: 2026-09-23T14:19:28.732Z | J26: 0.002 | K26: 99.681249 | N26: out_usd=$99.66; fee_usd=0.32; slippage=0.00%; eta=22 secs; to_token=USDC; to_chain=Solana; display_decimals=6 | O26: https://layerswap.io/app?from=ETHEREUM_MAINNET&to=SOLANA_MAINNET&fromAsset=USDC&toAsset=USDC | P26: 20260923T141817Z | Q26: 2026-09-23T14:19:28.699Z | R26: 2026-09-23T14:19:26.736Z | S26: 0.006
A27: 1ce3ee3c699e | B27: ETH->SOL | C27: 1 | D27: Meson | E27: venue | F27: OK | G27: 2026-09-23T14:19:22.126Z | H27: 2026-09-23T14:19:22.766Z | I27: 2026-09-23T14:19:28.703Z | J27: 0.001 | K27: 99.1 | L27: 0 | N27: fees_deducted=[['Fee', 0.9, 'USDC']]; fee_total=0.9; fixed_fee_on_top=0.0; display_decimals=1 | O27: https://meson.fi/swap | P27: 20260923T141817Z | Q27: 2026-09-23T14:19:28.696Z | R27: 2026-09-23T14:19:24.937Z | S27: 0.006
A28: 1ce3ee3c699e | B28: ETH->SOL | C28: 1 | D28: OpenSea | E28: platform | F28: OK | G28: 2026-09-23T14:19:22.118Z | H28: 2026-09-23T14:19:25.252Z | I28: 2026-09-23T14:19:28.744Z | J28: 0.004 | K28: 99.7459 | L28: 0.94 | M28: native (gas, USD shown) | N28: out_usd=$99.72; provider=Relay; fee_total_usd=1.16; provider_fee_usd=0.22; provider_fee_pct=0.22%; provider_fee_deducted=True; opensea_fee_usd=0.0; opensea_fee_pct=0%; gas_fee_usd=0.94; gas_fee_display=$0.94; fixed_fee_on_top=0.94; fixed_fee_token=native (gas, USD shown); price_impact=(-$0.03) -0.03 | O28: https://opensea.io/swap?fromChain=ethereum&fromAddress=0xa0b86991c6218b36c1d19d4a2e9eb0ce3606eb48&toChain=solana&toAddress=EPjFWdd5AufqSSqeM2qN1xzybapC8G4wEGGkZwyTDt1v | P28: 20260923T141817Z | Q28: 2026-09-23T14:19:28.701Z | R28: 2026-09-23T14:19:27.409Z | S28: 0.006
A29: 1ce3ee3c699e | B29: ETH->SOL | C29: 1 | D29: SimpleSwap | E29: venue | F29: OK | G29: 2026-09-23T14:19:22.126Z | H29: 2026-09-23T14:19:25.340Z | I29: 2026-09-23T14:19:28.872Z | J29: 0.005 | K29: 98.482157 | L29: 0 | M29: USDC | N29: best_card_out=98.482157; selected_card=Best rate / Decentralized; rate_type=floating; fixed_fee_on_top=0.0; fixed_fee_token=USDC; display_decimals=6; small_sum_warning=False | O29: https://simpleswap.io/?from=usdc-eth&to=usdc-sol | P29: 20260923T141817Z | Q29: 2026-09-23T14:19:28.702Z | R29: 2026-09-23T14:19:27.561Z | S29: 0.006
A30: 1ce3ee3c699e | B30: ETH->SOL | C30: 1 | D30: Skip Go | E30: venue | F30: OK | G30: 2026-09-23T14:19:22.119Z | H30: 2026-09-23T14:19:24.784Z | I30: 2026-09-23T14:19:28.733Z | J30: 0.002 | K30: 99.72581 | N30: fees_usd_in_quote=0.27; eta=2 mins; usd_values=['99.98', '99.70']; display_decimals=5 | O30: https://go.skip.build/?src_chain=1&src_asset=0xa0b86991c6218b36c1d19d4a2e9eb0ce3606eb48&dest_chain=solana&dest_asset=EPjFWdd5AufqSSqeM2qN1xzybapC8G4wEGGkZwyTDt1v | P30: 20260923T141817Z | Q30: 2026-09-23T14:19:28.699Z | R30: 2026-09-23T14:19:26.921Z | S30: 0.006
A31: 1ce3ee3c699e | B31: ETH->SOL | C31: 1 | D31: Symbiosis | E31: venue | F31: OK | G31: 2026-09-23T14:19:22.119Z | H31: 2026-09-23T14:19:24.972Z | I31: 2026-09-23T14:19:28.738Z | J31: 0.003 | K31: 98.950473 | L31: 0 | N31: min_received=98.4557; fee_usd_deducted=1.02; eta=2 - 3 Min; price_impact=0%; slippage=2%; route=Bridge to Solana; fixed_fee_on_top=0.0; display_decimals=6 | O31: https://app.symbiosis.finance/swap?chainIn=Ethereum&chainOut=Solana&tokenIn=0xa0b86991c6218b36c1d19d4a2e9eb0ce3606eb48&tokenOut=0x0000000000000000000000000000000000000003 | P31: 20260923T141817Z | Q31: 2026-09-23T14:19:28.700Z | R31: 2026-09-23T14:19:27.140Z | S31: 0.006
A32: 18f661e80197 | B32: SOL->BSC | C32: 1 | D32: Bridg | E32: bridg | F32: OK | G32: 2026-09-23T14:19:52.315Z | H32: 2026-09-23T14:19:53.709Z | I32: 2026-09-23T14:19:58.640Z | K32: 99.870038 | N32: best via Rhino; 9 venues priced; fees [['Rhino fee', 0.079962], ['Bridg fee', 0.05]] | O32: https://bridg.now/swap/ | P32: 20260923T141817Z | Q32: 2026-09-23T14:19:58.625Z | R32: 2026-09-23T14:19:56.903Z | S32: 0.004
A33: 18f661e80197 | B33: SOL->BSC | C33: 1 | D33: Relay | E33: venue | F33: OK | G33: 2026-09-23T14:19:52.315Z | H33: 2026-09-23T14:19:54.827Z | I33: 2026-09-23T14:19:58.662Z | J33: 0.001 | K33: 99.651304 | N33: rate=0.9965 | O33: https://relay.link/bridge/bsc?fromChainId=792703809&fromCurrency=EPjFWdd5AufqSSqeM2qN1xzybapC8G4wEGGkZwyTDt1v&toCurrency=0x8ac76a51cc950d9822d68b83fe1ad97b32cd580d | P33: 20260923T141817Z | Q33: 2026-09-23T14:19:58.626Z | R33: 2026-09-23T14:19:56.961Z | S33: 0.004
A34: 18f661e80197 | B34: SOL->BSC | C34: 1 | D34: deBridge | E34: venue | F34: OK | G34: 2026-09-23T14:19:52.317Z | H34: 2026-09-23T14:19:54.790Z | I34: 2026-09-23T14:19:58.661Z | J34: 0.001 | K34: 99.920015 | L34: 1.2455 | M34: USDC | N34: fixed_fee_on_top=1.2455; fixed_fee_token=USDC | O34: https://app.debridge.com/?inputChain=7565164&outputChain=56&inputCurrency=EPjFWdd5AufqSSqeM2qN1xzybapC8G4wEGGkZwyTDt1v&outputCurrency=0x8ac76a51cc950d9822d68b83fe1ad97b32cd580d&dlnMode=simple | P34: 20260923T141817Z | Q34: 2026-09-23T14:19:58.626Z | R34: 2026-09-23T14:19:56.923Z | S34: 0.004
A35: 18f661e80197 | B35: SOL->BSC | C35: 1 | D35: LI.FI (Jumper) | E35: venue | F35: OK | G35: 2026-09-23T14:19:52.317Z | H35: 2026-09-23T14:19:56.484Z | I35: 2026-09-23T14:19:58.628Z | J35: 0.002 | K35: 99.93159 | N35: best_return_venue=Mayan (Swift); max_out=99.93159 | O35: https://jumper.xyz/?fromChain=1151111081099710&fromToken=EPjFWdd5AufqSSqeM2qN1xzybapC8G4wEGGkZwyTDt1v&toChain=56&toToken=0x8ac76a51cc950d9822d68b83fe1ad97b32cd580d | P35: 20260923T141817Z | Q35: 2026-09-23T14:19:58.623Z | R35: 2026-09-23T14:19:58.623Z | S35: 0.004
A36: 18f661e80197 | B36: SOL->BSC | C36: 1 | D36: Across | E36: venue | F36: OK | G36: 2026-09-23T14:19:52.315Z | H36: 2026-09-23T14:19:54.082Z | I36: 2026-09-23T14:19:58.633Z | J36: 0.001 | K36: 99.981745 | O36: https://across.to/?from=solana&to=bsc&inputToken=USDC&outputToken=USDC | P36: 20260923T141817Z | Q36: 2026-09-23T14:19:58.624Z | R36: 2026-09-23T14:19:56.274Z | S36: 0.004
A37: 18f661e80197 | B37: SOL->BSC | C37: 1 | D37: Mayan | E37: venue | F37: OK | G37: 2026-09-23T14:19:52.314Z | H37: 2026-09-23T14:19:53.910Z | I37: 2026-09-23T14:19:58.632Z | J37: 0.001 | K37: 99.931 | N37: mode=Swift v2; eta=3s; display_decimals=3 | O37: https://swap.mayan.finance/ | P37: 20260923T141817Z | Q37: 2026-09-23T14:19:58.624Z | R37: 2026-09-23T14:19:56.029Z | S37: 0.004
A38: 18f661e80197 | B38: SOL->BSC | C38: 1 | D38: Husher | E38: venue | F38: OK | G38: 2026-09-23T14:19:52.323Z | H38: 2026-09-23T14:19:54.091Z | I38: 2026-09-23T14:19:58.660Z | J38: 0.001 | K38: 99.65 | N38: out_usd=$99.67; provider=Husher (Best Rate); rate_type=floating; fee_deducted=0.35; network_fee_deducted=0.0; api_receive=99.65000000; eta_s=40; display_decimals=2 | O38: https://www.husher.io/ | P38: 20260923T141817Z | Q38: 2026-09-23T14:19:58.624Z | R38: 2026-09-23T14:19:56.293Z | S38: 0.004
A39: 18f661e80197 | B39: SOL->BSC | C39: 1 | D39: Layerswap | E39: venue | F39: OK | G39: 2026-09-23T14:19:52.316Z | H39: 2026-09-23T14:19:55.032Z | I39: 2026-09-23T14:19:58.663Z | J39: 0.001 | K39: 99.863113 | N39: out_usd=$99.84; fee_usd=0.14; slippage=0.00%; eta=3 secs; to_token=USDC; to_chain=BSC; display_decimals=6 | O39: https://layerswap.io/app?from=SOLANA_MAINNET&to=BSC_MAINNET&fromAsset=USDC&toAsset=USDC | P39: 20260923T141817Z | Q39: 2026-09-23T14:19:58.626Z | R39: 2026-09-23T14:19:57.205Z | S39: 0.004
A40: 18f661e80197 | B40: SOL->BSC | C40: 1 | D40: Meson | E40: venue | F40: OK | G40: 2026-09-23T14:19:52.320Z | H40: 2026-09-23T14:19:52.804Z | I40: 2026-09-23T14:19:58.635Z | J40: 0.002 | K40: 99.88 | L40: 0 | N40: fees_deducted=[['Fee', 0.12, 'USDC']]; fee_total=0.12; fixed_fee_on_top=0.0; display_decimals=2 | O40: https://meson.fi/swap | P40: 20260923T141817Z | Q40: 2026-09-23T14:19:58.623Z | R40: 2026-09-23T14:19:55.039Z | S40: 0.004
A41: 18f661e80197 | B41: SOL->BSC | C41: 1 | D41: SimpleSwap | E41: venue | F41: OK | G41: 2026-09-23T14:19:52.325Z | H41: 2026-09-23T14:19:55.429Z | I41: 2026-09-23T14:19:58.707Z | J41: 0.002 | K41: 98.139 | L41: 0 | M41: USDC | N41: best_card_out=98.139; selected_card=Best rate; rate_type=floating; fixed_fee_on_top=0.0; fixed_fee_token=USDC; display_decimals=3; small_sum_warning=False | O41: https://simpleswap.io/?from=usdc-sol&to=usdc-bsc | P41: 20260923T141817Z | Q41: 2026-09-23T14:19:58.627Z | R41: 2026-09-23T14:19:57.622Z | S41: 0.004
A42: fa8b4231fde3 | B42: BSC->SOL | C42: 1 | D42: Bridg | E42: bridg | F42: OK | G42: 2026-09-23T14:20:23.792Z | H42: 2026-09-23T14:20:25.034Z | I42: 2026-09-23T14:20:29.494Z | K42: 99.640471 | N42: best via Mayan; 10 venues priced; fees [['Mayan fee', 0.30953], ['Bridg fee', 0.05]] | O42: https://bridg.now/swap/ | P42: 20260923T141817Z | Q42: 2026-09-23T14:20:29.480Z | R42: 2026-09-23T14:20:27.195Z | S42: 0.004
A43: fa8b4231fde3 | B43: BSC->SOL | C43: 1 | D43: Relay | E43: venue | F43: OK | G43: 2026-09-23T14:20:23.791Z | H43: 2026-09-23T14:20:25.793Z | I43: 2026-09-23T14:20:29.496Z | J43: 0.002 | K43: 99.885705 | N43: rate=0.9988 | O43: https://relay.link/bridge/solana?fromChainId=56&fromCurrency=0x8ac76a51cc950d9822d68b83fe1ad97b32cd580d&toCurrency=EPjFWdd5AufqSSqeM2qN1xzybapC8G4wEGGkZwyTDt1v | P43: 20260923T141817Z | Q43: 2026-09-23T14:20:29.482Z | R43: 2026-09-23T14:20:27.933Z | S43: 0.004
A44: fa8b4231fde3 | B44: BSC->SOL | C44: 1 | D44: deBridge | E44: venue | F44: OK | G44: 2026-09-23T14:20:23.792Z | H44: 2026-09-23T14:20:26.058Z | I44: 2026-09-23T14:20:29.497Z | J44: 0.002 | K44: 99.920017 | L44: 1.0173 | M44: USDC | N44: fixed_fee_on_top=1.0173; fixed_fee_token=USDC | O44: https://app.debridge.com/?inputChain=56&outputChain=7565164&inputCurrency=0x8ac76a51cc950d9822d68b83fe1ad97b32cd580d&outputCurrency=EPjFWdd5AufqSSqeM2qN1xzybapC8G4wEGGkZwyTDt1v&dlnMode=simple | P44: 20260923T141817Z | Q44: 2026-09-23T14:20:29.482Z | R44: 2026-09-23T14:20:28.213Z | S44: 0.004
A45: fa8b4231fde3 | B45: BSC->SOL | C45: 1 | D45: LI.FI (Jumper) | E45: venue | F45: OK | G45: 2026-09-23T14:20:23.793Z | H45: 2026-09-23T14:20:26.598Z | I45: 2026-09-23T14:20:29.490Z | J45: 0.004 | K45: 99.885705 | N45: best_return_venue=Relay; max_out=99.885705 | O45: https://jumper.xyz/?fromChain=56&fromToken=0x8ac76a51cc950d9822d68b83fe1ad97b32cd580d&toChain=1151111081099710&toToken=EPjFWdd5AufqSSqeM2qN1xzybapC8G4wEGGkZwyTDt1v | P45: 20260923T141817Z | Q45: 2026-09-23T14:20:29.484Z | R45: 2026-09-23T14:20:28.729Z | S45: 0.004
A46: fa8b4231fde3 | B46: BSC->SOL | C46: 1 | D46: Across | E46: venue | F46: OK | G46: 2026-09-23T14:20:23.791Z | H46: 2026-09-23T14:20:25.098Z | I46: 2026-09-23T14:20:29.487Z | J46: 0.001 | K46: 99.981745 | O46: https://across.to/?from=bsc&to=solana&inputToken=USDC&outputToken=USDC | P46: 20260923T141817Z | Q46: 2026-09-23T14:20:29.481Z | R46: 2026-09-23T14:20:27.225Z | S46: 0.004
A47: fa8b4231fde3 | B47: BSC->SOL | C47: 1 | D47: Mayan | E47: venue | F47: OK | G47: 2026-09-23T14:20:23.791Z | H47: 2026-09-23T14:20:25.519Z | I47: 2026-09-23T14:20:29.488Z | J47: 0.001 | K47: 99.69 | N47: mode=Swift v2; eta=3s; display_decimals=2 | O47: https://swap.mayan.finance/ | P47: 20260923T141817Z | Q47: 2026-09-23T14:20:29.481Z | R47: 2026-09-23T14:20:27.645Z | S47: 0.004
A48: fa8b4231fde3 | B48: BSC->SOL | C48: 1 | D48: Husher | E48: venue | F48: OK | G48: 2026-09-23T14:20:23.793Z | H48: 2026-09-23T14:20:25.285Z | I48: 2026-09-23T14:20:29.495Z | J48: 0.001 | K48: 99.35 | N48: out_usd=$99.37; provider=Husher (Best Rate); rate_type=floating; fee_deducted=0.35; network_fee_deducted=0.3; api_receive=99.35000000; eta_s=40; display_decimals=2 | O48: https://www.husher.io/ | P48: 20260923T141817Z | Q48: 2026-09-23T14:20:29.481Z | R48: 2026-09-23T14:20:27.432Z | S48: 0.004
A49: fa8b4231fde3 | B49: BSC->SOL | C49: 1 | D49: Layerswap | E49: venue | F49: OK | G49: 2026-09-23T14:20:23.792Z | H49: 2026-09-23T14:20:26.199Z | I49: 2026-09-23T14:20:29.498Z | J49: 0.004 | K49: 99.633822 | N49: out_usd=$99.61; fee_usd=0.37; slippage=0.00%; eta=22 secs; to_token=USDC; to_chain=Solana; display_decimals=6 | O49: https://layerswap.io/app?from=BSC_MAINNET&to=SOLANA_MAINNET&fromAsset=USDC&toAsset=USDC | P49: 20260923T141817Z | Q49: 2026-09-23T14:20:29.484Z | R49: 2026-09-23T14:20:28.356Z | S49: 0.004
A50: fa8b4231fde3 | B50: BSC->SOL | C50: 1 | D50: Meson | E50: venue | F50: OK | G50: 2026-09-23T14:20:23.793Z | H50: 2026-09-23T14:20:24.270Z | I50: 2026-09-23T14:20:29.488Z | J50: 0 | K50: 99.6 | L50: 0 | N50: fees_deducted=[['Fee', 0.4, 'USDC']]; fee_total=0.4; fixed_fee_on_top=0.0; display_decimals=1 | O50: https://meson.fi/swap | P50: 20260923T141817Z | Q50: 2026-09-23T14:20:29.480Z | R50: 2026-09-23T14:20:26.411Z | S50: 0.004
A51: fa8b4231fde3 | B51: BSC->SOL | C51: 1 | D51: SimpleSwap | E51: venue | F51: OK | G51: 2026-09-23T14:20:23.795Z | H51: 2026-09-23T14:20:26.630Z | I51: 2026-09-23T14:20:29.634Z | J51: 0.004 | K51: 98.180302 | L51: 0 | M51: USDC | N51: best_card_out=98.180302; selected_card=Best rate; rate_type=floating; fixed_fee_on_top=0.0; fixed_fee_token=USDC; display_decimals=6; small_sum_warning=False | O51: https://simpleswap.io/?from=usdc-bsc&to=usdc-sol | P51: 20260923T141817Z | Q51: 2026-09-23T14:20:29.484Z | R51: 2026-09-23T14:20:28.851Z | S51: 0.004
A52: fa8b4231fde3 | B52: BSC->SOL | C52: 1 | D52: Symbiosis | E52: venue | F52: OK | G52: 2026-09-23T14:20:23.792Z | H52: 2026-09-23T14:20:27.336Z | I52: 2026-09-23T14:20:29.492Z | J52: 0 | K52: 98.355626 | L52: 0 | N52: min_received=97.8638; fee_usd_deducted=1.52; eta=2 - 3 Min; price_impact=-0.08%; slippage=2%; route=Bridge to Arbitrum One; fixed_fee_on_top=0.0; display_decimals=6 | O52: https://app.symbiosis.finance/swap?chainIn=BNB&chainOut=Solana&tokenIn=0x8ac76a51cc950d9822d68b83fe1ad97b32cd580d&tokenOut=0x0000000000000000000000000000000000000003 | P52: 20260923T141817Z | Q52: 2026-09-23T14:20:29.480Z | R52: 2026-09-23T14:20:29.480Z | S52: 0.004
A53: 53ab1ac32c3a | B53: SOL->Base | C53: 1 | D53: Bridg | E53: bridg | F53: OK | G53: 2026-09-23T14:21:02.757Z | H53: 2026-09-23T14:21:03.882Z | I53: 2026-09-23T14:21:09.361Z | K53: 99.943099 | N53: best via Skip Go; 15 venues priced; fees [['Skip Go fee', 0.006901], ['Bridg fee', 0.05]] | O53: https://bridg.now/swap/ | P53: 20260923T141817Z | Q53: 2026-09-23T14:21:09.321Z | R53: 2026-09-23T14:21:07.554Z | S53: 0.006
A54: 53ab1ac32c3a | B54: SOL->Base | C54: 1 | D54: Relay | E54: venue | F54: OK | G54: 2026-09-23T14:21:02.755Z | H54: 2026-09-23T14:21:04.473Z | I54: 2026-09-23T14:21:09.339Z | J54: 0.003 | K54: 99.937898 | N54: rate=0.9993 | O54: https://relay.link/bridge/base?fromChainId=792703809&fromCurrency=EPjFWdd5AufqSSqeM2qN1xzybapC8G4wEGGkZwyTDt1v&toCurrency=0x833589fcd6edb6e08f4c7c32d4f71b54bda02913 | P54: 20260923T141817Z | Q54: 2026-09-23T14:21:09.318Z | R54: 2026-09-23T14:21:06.935Z | S54: 0.006
A55: 53ab1ac32c3a | B55: SOL->Base | C55: 1 | D55: deBridge | E55: venue | F55: OK | G55: 2026-09-23T14:21:02.756Z | H55: 2026-09-23T14:21:05.343Z | I55: 2026-09-23T14:21:09.346Z | J55: 0.001 | K55: 99.880033 | L55: 1.5278 | M55: USDC | N55: fixed_fee_on_top=1.5278; fixed_fee_token=USDC | O55: https://app.debridge.com/?inputChain=7565164&outputChain=8453&inputCurrency=EPjFWdd5AufqSSqeM2qN1xzybapC8G4wEGGkZwyTDt1v&outputCurrency=0x833589fcd6edb6e08f4c7c32d4f71b54bda02913&dlnMode=simple | P55: 20260923T141817Z | Q55: 2026-09-23T14:21:09.320Z | R55: 2026-09-23T14:21:07.550Z | S55: 0.006
A56: 53ab1ac32c3a | B56: SOL->Base | C56: 1 | D56: LI.FI (Jumper) | E56: venue | F56: OK | G56: 2026-09-23T14:21:02.757Z | H56: 2026-09-23T14:21:07.186Z | I56: 2026-09-23T14:21:09.323Z | J56: 0.005 | K56: 100 | N56: best_return_venue=Eco; max_out=100.0 | O56: https://jumper.xyz/?fromChain=1151111081099710&fromToken=EPjFWdd5AufqSSqeM2qN1xzybapC8G4wEGGkZwyTDt1v&toChain=8453&toToken=0x833589fcd6edb6e08f4c7c32d4f71b54bda02913 | P56: 20260923T141817Z | Q56: 2026-09-23T14:21:09.316Z | R56: 2026-09-23T14:21:09.316Z | S56: 0.006
A57: 53ab1ac32c3a | B57: SOL->Base | C57: 1 | D57: Across | E57: venue | F57: OK | G57: 2026-09-23T14:21:02.756Z | H57: 2026-09-23T14:21:04.200Z | I57: 2026-09-23T14:21:09.325Z | J57: 0.004 | K57: 99.99 | O57: https://across.to/?from=solana&to=base&inputToken=USDC&outputToken=USDC | P57: 20260923T141817Z | Q57: 2026-09-23T14:21:09.317Z | R57: 2026-09-23T14:21:06.436Z | S57: 0.006
A58: 53ab1ac32c3a | B58: SOL->Base | C58: 1 | D58: Mayan | E58: venue | F58: OK | G58: 2026-09-23T14:21:02.754Z | H58: 2026-09-23T14:21:04.081Z | I58: 2026-09-23T14:21:09.324Z | J58: 0.005 | K58: 99.933 | N58: mode=Swift v2; eta=3s; display_decimals=3 | O58: https://swap.mayan.finance/ | P58: 20260923T141817Z | Q58: 2026-09-23T14:21:09.316Z | R58: 2026-09-23T14:21:06.306Z | S58: 0.006
A59: 53ab1ac32c3a | B59: SOL->Base | C59: 1 | D59: Allbridge Core | E59: venue | F59: OK | G59: 2026-09-23T14:21:02.757Z | H59: 2026-09-23T14:21:04.267Z | I59: 2026-09-23T14:21:09.608Z | J59: 0.004 | K59: 99.9 | L59: 0.002418 | M59: SOL (relayer fee, fee=native) | N59: out_input_box=99.9; out_details_2dp=99.9; fixed_fee_on_top=0.002418; fixed_fee_token=SOL (relayer fee, fee=native); transfer_fee=0.10 USDC; messenger=CCTP; eta=~1 min; display_decimals=1; picked=['USDC from Solana', 'USDC to Base'] | O59: https://core.allbridge.io/?fee=native&ft=USDC&tt=USDC&f=SOL&t=BAS | P59: 20260923T141817Z | Q59: 2026-09-23T14:21:09.317Z | R59: 2026-09-23T14:21:06.535Z | S59: 0.006
